Workbook
Name CUSTOMER_DETAILS: #REF!
Name InvoiceDetails: 'INVOICE DETAILS'!$A$2:$AG$1048714
Name CustDetails: 'CUSTOMER DETAILS'!$B$2:$H$1000
Name CustDetail1: 'CUSTOMER DETAILS'!$B$2:$H$1000
Name PRINT: 'CREDIT NOTE'!$A$2:$J$57
Name PRINT: 'INVOICE Other than MH'!$A$2:$J$57
Name PRINT: 'INVOICE Only MH'!$A$2:$J$58
Name InvoiceDetails: 'Copy of INVOICE DETAILS'!$A$2:$AF$1048576

Sheet INVOICE Only MH
B2: TAX INVOICE
B4: MAHALAXMI AGRO ENERGIES | F4: Invoice No. | I4: Dated
B5: 70 Mahakali Nagar 3, Mhalginagar, | F5: =IFERROR(VLOOKUP(F13,InvoiceDetails,11,FALSE)," ") -> 418 | I5: =VLOOKUP(F13,InvoiceDetails,4,FALSE) -> 46102
B6: Hudkeshwar Ring Road, Nagpur 34 | F6: Delivery Note | I6: Payment Mode/Terms
B7: 8550952303 | F7: =IFERROR(VLOOKUP(F13,InvoiceDetails,5,FALSE)," ") -> - | I7: =IFERROR(VLOOKUP(F13,InvoiceDetails,6,FALSE)," ") -> -
B8: GSTN: | C8: 27BOPPP0960N1Z7 | F8: Supplier Ref. | I8: Other Reference(s)
B9: State: | C9: MAHARASHTRA | E9: 440034 | F9: =IFERROR(VLOOKUP(F13,InvoiceDetails,7,FALSE)," ") -> - | I9: =IFERROR(VLOOKUP(#REF!,InvoiceDetails,8,FALSE)," ")
B10: Mail: | C10: biomassenergies@gmail.com | F10: Buyer's Order No. | I10: Dated
B11: Consignee | F11: =IFERROR(VLOOKUP(F13,InvoiceDetails,9,FALSE)," ") -> - | I11: =IFERROR(VLOOKUP(F13,InvoiceDetails,10,FALSE)," ") -> 46102
B12: =VLOOKUP(F13,InvoiceDetails,2,FALSE) -> GAURI,S TAVA TADKA | F12: Despatch Document No | I12: Delivery Note Date
B13: =VLOOKUP(B12,CustDetail1,2,FALSE) -> HARIDARSHAN APARTMENT TRIMURTI NAGAR BESIDE KRISHNA DENTAL CLINIC | F13: MAE060/25-26-0020 | I13: =IFERROR(VLOOKUP(#REF!,InvoiceDetails,12,FALSE)," ")
F15: Despatched Through | I15: Destination
B16: GSTN: | C16: =VLOOKUP(B12,CustDetail1,3,FALSE) | F16: =IFERROR(VLOOKUP(F13,InvoiceDetails,13,FALSE)," ") -> SELF PICKUP | I16: =IFERROR(VLOOKUP(F13,InvoiceDetails,14,FALSE)," ") -> NAGPUR
B17: State: | C17: =VLOOKUP(B12,CustDetail1,4,FALSE) -> MAHARASHTRA | E17: =VLOOKUP(B12,CustDetail1,5,FALSE)
B18: Mail: | C18: =VLOOKUP(B12,CustDetail1,6,FALSE) | F18: Bill of Landing/LR-RR No. | I18: Motor Vehicle Number
F19: =IFERROR(VLOOKUP(#REF!,InvoiceDetails,15,FALSE)," ") | I19: =IFERROR(VLOOKUP(F13,InvoiceDetails,16,FALSE)," ")
B21: Buyer (If Other Than Consignee) | F21: Terms Of Delivery
B22: =VLOOKUP(F13,InvoiceDetails,2,FALSE) -> GAURI,S TAVA TADKA
B23: =VLOOKUP(B22,CustDetail1,2,FALSE) -> HARIDARSHAN APARTMENT TRIMURTI NAGAR BESIDE KRISHNA DENTAL CLINIC
B25: GSTN: | C25: =VLOOKUP(B12,CustDetail1,3,FALSE)
B26: State: | C26: =VLOOKUP(B12,CustDetail1,4,FALSE) -> MAHARASHTRA | E26: =VLOOKUP(B12,CustDetail1,5,FALSE)
B27: Mail: | C27: =VLOOKUP(B12,CustDetail1,6,FALSE)
B28: Sr. No. | C28: Description Of Goods | F28: HSN Code | G28: Quatity | H28: Rate | I28: Per | J28: Amount
B29: 1 | C29: =IFERROR(VLOOKUP(F13,InvoiceDetails,17,FALSE)," ") -> BIOMASS PELLET STOVE 15KG | F29: =IFERROR(VLOOKUP(F13,InvoiceDetails,18,FALSE)," ") | G29: =IFERROR(VLOOKUP(F13,InvoiceDetails,19,FALSE)," ") -> 1 | H29: =IFERROR(VLOOKUP(F13,InvoiceDetails,20,FALSE)," ") -> 19000 | I29: =IFERROR(VLOOKUP(F13,InvoiceDetails,21,FALSE)," ") -> PCS | J29: =IFERROR(VLOOKUP(F13,InvoiceDetails,22,FALSE)," ") -> 19000
E31: SGST OUTPUT @ 2.5% | H31: =IFERROR(VLOOKUP(#REF!,InvoiceDetails,23,FALSE)," ") | J31: =IFERROR(VLOOKUP(F13,InvoiceDetails,30,FALSE)," ") -> 475
E32: CGST OUTPUT @ 2.5% | H32: =IFERROR(VLOOKUP(#REF!,InvoiceDetails,24,FALSE)," ") | J32: =IFERROR(VLOOKUP(F13,InvoiceDetails,31,FALSE)," ") -> 475
E33: ROUNDOFF | J33: =IFERROR(VLOOKUP(F13,InvoiceDetails,27,FALSE)," ") -> 0
E35: TRANSPORTATION | J35: =IFERROR(VLOOKUP(F13,InvoiceDetails,28,FALSE)," ")
E40: Total | G40: =SUM(G29:G39) -> 1 | J40: =IFERROR(VLOOKUP(F13,InvoiceDetails,26,FALSE)," ") -> 19950
B41: Amount Chargeable(in words) | J41: E. & O.E
B42: INR | C42: ="INR"&CHOOSE(LEFT(TEXT(J40,"000000000.00"))+1,,"One","Two","Three","Four","Five","Six","Seven","Eight","Nine") &IF(--LEFT(TEXT(J40,"000000000.00"))=0,,IF(AND(--MID(TEXT(J40,"000000000.00"),2,1)=0,--MID(TEXT(J40,"000000000.00"),3,1)=0)," Hundred"," Hundred and ")) &CHOOSE(MID(TEXT(J40,"000000000.00"),2,1)+1,,,"Twenty ","Thirty ","Forty ","Fifty ","Sixty ","Seventy ","Eighty ","Ninety ") &IF(--MID(TEXT(J40,"000000000.00"),2,1)<>1,CHOOSE(MID(TEXT(J40,"000000000.00"),3,1)+1,,"One","Two","Three","Four","Five","Six","Seven","Eight","Nine"), CHOOSE(MID(TEXT(J40,"000000000.00"),3,1)+1,"Ten","Eleven","Twelve","Thirteen","Fourteen","Fifteen","Sixteen","Seventeen","Eighteen","Nineteen")) &IF((--LEFT(TEXT(J40,"000000000.00"))+MID(TEXT(J40,"000000000.00"),2,1)+MID(TEXT(J40,"000000000.00"),3,1))=0,,IF(AND((--MID(TEXT(J40,"000000000.00"),4,1)+MID(TEXT(J40,"000000000.00"),5,1)+MID(TEXT(J40,"000000000.00"),6,1)+MID(TEXT(J40,"000000000.00"),7,1))=0,(--MID(TEXT(J40,"000000000.00"),8,1)+RIGHT(TEXT(J40,"000000000.00")))>0)," Million and "," Million ")) &CHOOSE(MID(TEXT(J40,"000000000.00"),4,1)+1,,"One","Two","Three","Four","Five","Six","Seven","Eight","Nine") &IF(--MID(TEXT(J40,"000000000.00"),4,1)=0,,IF(AND(--MID(TEXT(J40,"000000000.00"),5,1)=0,--MID(TEXT(J40,"000000000.00"),6,1)=0)," Hundred"," Hundred and")) &CHOOSE(MID(TEXT(J40,"000000000.00"),5,1)+1,,," Twenty"," Thirty"," Forty"," Fifty"," Sixty"," Seventy"," Eighty"," Ninety") &IF(--MID(TEXT(J40,"000000000.00"),5,1)<>1,CHOOSE(MID(TEXT(J40,"000000000.00"),6,1)+1,," One"," Two"," Three"," Four"," Five"," Six"," Seven"," Eight"," Nine"),CHOOSE(MID(TEXT(J40,"000000000.00"),6,1)+1," Ten"," Eleven"," Twelve"," Thirteen"," Fourteen"," Fifteen"," Sixteen"," Seventeen"," Eighteen"," Nineteen")) &IF((--MID(TEXT(J40,"000000000.00"),4,1)+MID(TEXT(J40,"000000000.00"),5,1)+MID(TEXT(J40,"000000000.00"),6,1))=0,,IF(OR((--MID(TEXT(J40,"000000000.00"),7,1)+MID(TEXT(J40,"000000000.00"),8,1)+MID(TEXT(J40,"000000000.00"),9,1))=0,--MID(TEXT(J40,"000000000.00"),7,1)<>0)," Thousand "," Thousand and ")) &CHOOSE(MID(TEXT(J40,"000000000.00"),7,1)+1,,"One","Two","Three","Four","Five","Six","Seven","Eight","Nine") &IF(--MID(TEXT(J40,"000000000.00"),7,1)=0,,IF(AND(--MID(TEXT(J40,"000000000.00"),8,1)=0,--MID(TEXT(J40,"000000000.00"),9,1)=0)," Hundred "," Hundred and "))& CHOOSE(MID(TEXT(J40,"000000000.00"),8,1)+1,,,"Twenty ","Thirty ","Forty ","Fifty ","Sixty ","Seventy ","Eighty ","Ninety ") &IF(--MID(TEXT(J40,"000000000.00"),8,1)<>1,CHOOSE(MID(TEXT(J40,"000000000.00"),9,1)+1,,"One","Two","Three","Four","Five","Six","Seven","Eight","Nine"),CHOOSE(MID(TEXT(J40,"000000000.00"),9,1)+1,"Ten","Eleven","Twelve","Thirteen","Fourteen","Fifteen","Sixteen","Seventeen","Eighteen","Nineteen")) &IF(RIGHT(TEXT(J40,"000000000.00"),2)>"000000000.00"," & "&RIGHT(TEXT(J40,"000000000.00"),2)&" Paise Only.","Only.") -> INR Nineteen Thousand Nine Hundred and Fifty Only.
B43: HSN Code | E43: Taxable Value | F43: Central Tax | H43: State Tax | J43: Total Tax Amount
F44: Rate | G44: Amount | H44: Rate | I44: Amount
B45: =IFERROR(VLOOKUP(F13,InvoiceDetails,18,FALSE)," ") | E45: =IFERROR(VLOOKUP(F13,InvoiceDetails,26,FALSE)," ") -> 19950 | F45: =IFERROR(VLOOKUP(F13,InvoiceDetails,23,FALSE)," ") -> 0.025 | G45: =IFERROR(VLOOKUP(F13,InvoiceDetails,30,FALSE)," ") -> 475 | H45: =IFERROR(VLOOKUP(F13,InvoiceDetails,24,FALSE)," ") -> 0.025 | I45: =IFERROR(VLOOKUP(F13,InvoiceDetails,31,FALSE)," ") -> 475 | J45: =IFERROR(VLOOKUP(F13,InvoiceDetails,33,FALSE)," ") -> 950
B46: Total | E46: =E45 -> 19950 | G46: =G45 -> 475 | I46: =I45 -> 475 | J46: =J45 -> 950
B47: Tax Amount(in words)
B48: INR | C48: ="INR"&CHOOSE(LEFT(TEXT(J46,"000000000.00"))+1,,"One","Two","Three","Four","Five","Six","Seven","Eight","Nine") &IF(--LEFT(TEXT(J46,"000000000.00"))=0,,IF(AND(--MID(TEXT(J46,"000000000.00"),2,1)=0,--MID(TEXT(J46,"000000000.00"),3,1)=0)," Hundred"," Hundred and ")) &CHOOSE(MID(TEXT(J46,"000000000.00"),2,1)+1,,,"Twenty ","Thirty ","Forty ","Fifty ","Sixty ","Seventy ","Eighty ","Ninety ") &IF(--MID(TEXT(J46,"000000000.00"),2,1)<>1,CHOOSE(MID(TEXT(J46,"000000000.00"),3,1)+1,,"One","Two","Three","Four","Five","Six","Seven","Eight","Nine"), CHOOSE(MID(TEXT(J46,"000000000.00"),3,1)+1,"Ten","Eleven","Twelve","Thirteen","Fourteen","Fifteen","Sixteen","Seventeen","Eighteen","Nineteen")) &IF((--LEFT(TEXT(J46,"000000000.00"))+MID(TEXT(J46,"000000000.00"),2,1)+MID(TEXT(J46,"000000000.00"),3,1))=0,,IF(AND((--MID(TEXT(J46,"000000000.00"),4,1)+MID(TEXT(J46,"000000000.00"),5,1)+MID(TEXT(J46,"000000000.00"),6,1)+MID(TEXT(J46,"000000000.00"),7,1))=0,(--MID(TEXT(J46,"000000000.00"),8,1)+RIGHT(TEXT(J46,"000000000.00")))>0)," Million and "," Million ")) &CHOOSE(MID(TEXT(J46,"000000000.00"),4,1)+1,,"One","Two","Three","Four","Five","Six","Seven","Eight","Nine") &IF(--MID(TEXT(J46,"000000000.00"),4,1)=0,,IF(AND(--MID(TEXT(J46,"000000000.00"),5,1)=0,--MID(TEXT(J46,"000000000.00"),6,1)=0)," Hundred"," Hundred and")) &CHOOSE(MID(TEXT(J46,"000000000.00"),5,1)+1,,," Twenty"," Thirty"," Forty"," Fifty"," Sixty"," Seventy"," Eighty"," Ninety") &IF(--MID(TEXT(J46,"000000000.00"),5,1)<>1,CHOOSE(MID(TEXT(J46,"000000000.00"),6,1)+1,," One"," Two"," Three"," Four"," Five"," Six"," Seven"," Eight"," Nine"),CHOOSE(MID(TEXT(J46,"000000000.00"),6,1)+1," Ten"," Eleven"," Twelve"," Thirteen"," Fourteen"," Fifteen"," Sixteen"," Seventeen"," Eighteen"," Nineteen")) &IF((--MID(TEXT(J46,"000000000.00"),4,1)+MID(TEXT(J46,"000000000.00"),5,1)+MID(TEXT(J46,"000000000.00"),6,1))=0,,IF(OR((--MID(TEXT(J46,"000000000.00"),7,1)+MID(TEXT(J46,"000000000.00"),8,1)+MID(TEXT(J46,"000000000.00"),9,1))=0,--MID(TEXT(J46,"000000000.00"),7,1)<>0)," Thousand "," Thousand and ")) &CHOOSE(MID(TEXT(J46,"000000000.00"),7,1)+1,,"One","Two","Three","Four","Five","Six","Seven","Eight","Nine") &IF(--MID(TEXT(J46,"000000000.00"),7,1)=0,,IF(AND(--MID(TEXT(J46,"000000000.00"),8,1)=0,--MID(TEXT(J46,"000000000.00"),9,1)=0)," Hundred "," Hundred and "))& CHOOSE(MID(TEXT(J46,"000000000.00"),8,1)+1,,,"Twenty ","Thirty ","Forty ","Fifty ","Sixty ","Seventy ","Eighty ","Ninety ") &IF(--MID(TEXT(J46,"000000000.00"),8,1)<>1,CHOOSE(MID(TEXT(J46,"000000000.00"),9,1)+1,,"One","Two","Three","Four","Five","Six","Seven","Eight","Nine"),CHOOSE(MID(TEXT(J46,"000000000.00"),9,1)+1,"Ten","Eleven","Twelve","Thirteen","Fourteen","Fifteen","Sixteen","Seventeen","Eighteen","Nineteen")) &IF(RIGHT(TEXT(J46,"000000000.00"),2)>"000000000.00"," & "&RIGHT(TEXT(J46,"000000000.00"),2)&" Paise Only.","Only.") -> INRNine Hundred and Fifty Only.
B50: Remarks: | F50: BANK NAME | H50: STATE BANK OF INDIA
F51: ACCOUNT NO. | H51: 39935045918
B52: PAN | C52: BOPPP0960N | F52: BRANCH & IFS CODE | H52: UDAY NAGAR SBIN0017637
B53: Declaration
B54: We declare that this invoice shows that the actual price of the goods described and that all particular are true and correct | H54: For MAHALAXMI AGRO ENERGIES (2024-2025)
H57: Authorised Signatory
B58: This is a computer Generated Invoice

Sheet INVOICE Other than MH
B2: TAX INVOICE
B4: MAHALAXMI AGRO ENERGIES | F4: Invoice No. | I4: Dated
B5: 70 Mahakali Nagar 3, Mhalginagar, | F5: =IFERROR(VLOOKUP(F13,InvoiceDetails,11,FALSE)," ") -> 416 | I5: =VLOOKUP(F13,InvoiceDetails,4,FALSE) -> 46021
B6: Hudkeshwar Ring Road, Nagpur 34 | F6: Delivery Note | I6: Payment Mode/Terms
B7: 8550952303 | F7: =IFERROR(VLOOKUP(F13,InvoiceDetails,5,FALSE)," ") -> - | I7: =IFERROR(VLOOKUP(F13,InvoiceDetails,6,FALSE)," ") -> -
B8: GSTN: | C8: 27BOPPP0960N1Z7 | F8: Supplier Ref. | I8: Other Reference(s)
B9: State: | C9: MAHARASHTRA | E9: 440034 | F9: =IFERROR(VLOOKUP(F13,InvoiceDetails,7,FALSE)," ") -> DM- 283 | I9: =IFERROR(VLOOKUP(F13,InvoiceDetails,8,FALSE)," ") -> -
B10: Mail: | C10: biomassenergies@gmail.com | F10: Buyer's Order No. | I10: Dated
B11: Consignee | F11: =IFERROR(VLOOKUP(F13,InvoiceDetails,9,FALSE)," ") -> - | I11: =IFERROR(VLOOKUP(F13,InvoiceDetails,10,FALSE)," ") -> 46021
B12: =VLOOKUP(F13,InvoiceDetails,2,FALSE) -> EXOTIC HOSPITALITY NAGPUR PVT LTD | F12: Despatch Document No. | I12: Delivery Note Date
B13: ='CUSTOMER DETAILS'!C60 -> TATHASTU PENCH PENCH TIGER RESERVE AWARGHANI TURIA SEONI | F13: MAE058/25-26-0018 | I13: =IFERROR(VLOOKUP(F13,InvoiceDetails,12,FALSE)," ") -> -
F14: Despatched Through | I14: Destination
B15: GSTN: | C15: ='CUSTOMER DETAILS'!D60 -> 23AAACE8761B1Z0 | F15: =IFERROR(VLOOKUP(F13,InvoiceDetails,13,FALSE)," ") -> SELF PICKUP | I15: =IFERROR(VLOOKUP(F13,InvoiceDetails,14,FALSE)," ") -> SOENI M.P
B16: State: | C16: ='CUSTOMER DETAILS'!E60 -> MADHYA PRADESH
B17: Mail: | C17: ='CUSTOMER DETAILS'!G60 -> ravi@sandeepdwellers.com | F17: Bill of Landing/LR-RR No. | I17: Motor Vehicle Number
F18: =IFERROR(VLOOKUP(F13,InvoiceDetails,15,FALSE)," ") -> - | I18: =IFERROR(VLOOKUP(F13,InvoiceDetails,16,FALSE)," ") -> MH-49BZ-1179
B20: Buyer (If Other Than Consignee) | F20: Terms Of Delivery
B21: =VLOOKUP(F13,InvoiceDetails,2,FALSE) -> EXOTIC HOSPITALITY NAGPUR PVT LTD
B22: =B13 -> TATHASTU PENCH PENCH TIGER RESERVE AWARGHANI TURIA SEONI
B24: GSTN: | C24: =C15 -> 23AAACE8761B1Z0
B25: State: | C25: =C16 -> MADHYA PRADESH
B26: Mail: | C26: =C17 -> ravi@sandeepdwellers.com
B27: Sr. No. | C27: Description Of Goods | F27: HSN Code | G27: Quatity | H27: Rate | I27: Per | J27: Amount
B28: 1 | C28: =IFERROR(VLOOKUP(F13,InvoiceDetails,17,FALSE)," ") -> BIOMASS BRIQUETTE 90MM | G28: =IFERROR(VLOOKUP(F13,InvoiceDetails,19,FALSE)," ") -> 2120 | H28: =IFERROR(VLOOKUP(F13,InvoiceDetails,20,FALSE)," ") -> 8.15 | I28: =IFERROR(VLOOKUP(F13,InvoiceDetails,21,FALSE)," ") -> KG | J28: =IFERROR(VLOOKUP(F13,InvoiceDetails,22,FALSE)," ") -> 17278
E30: IGST OUTPUT @ 5% | H30: =IFERROR(VLOOKUP(F13,InvoiceDetails,25,FALSE)," ") -> 0.05 | J30: =IFERROR(VLOOKUP(F13,InvoiceDetails,32,FALSE)," ") -> 863.9
E32: ROUNDOFF | J32: =IFERROR(VLOOKUP(F13,InvoiceDetails,27,FALSE)," ") -> 0.1
E34: TRANSPORT/UNLOADING | J34: =IFERROR(VLOOKUP(F13,InvoiceDetails,28,FALSE)," ")
E39: Total | G39: =SUM(G28:G38) -> 2120 | J39: =IFERROR(VLOOKUP(F13,InvoiceDetails,26,FALSE)," ") -> 18142
B40: Amount Chargeable(in words) | J40: E. & O.E
B41: INR | C41: ="INR"&CHOOSE(LEFT(TEXT(J39,"000000000.00"))+1,,"One","Two","Three","Four","Five","Six","Seven","Eight","Nine") &IF(--LEFT(TEXT(J39,"000000000.00"))=0,,IF(AND(--MID(TEXT(J39,"000000000.00"),2,1)=0,--MID(TEXT(J39,"000000000.00"),3,1)=0)," Hundred"," Hundred and ")) &CHOOSE(MID(TEXT(J39,"000000000.00"),2,1)+1,,,"Twenty ","Thirty ","Forty ","Fifty ","Sixty ","Seventy ","Eighty ","Ninety ") &IF(--MID(TEXT(J39,"000000000.00"),2,1)<>1,CHOOSE(MID(TEXT(J39,"000000000.00"),3,1)+1,,"One","Two","Three","Four","Five","Six","Seven","Eight","Nine"), CHOOSE(MID(TEXT(J39,"000000000.00"),3,1)+1,"Ten","Eleven","Twelve","Thirteen","Fourteen","Fifteen","Sixteen","Seventeen","Eighteen","Nineteen")) &IF((--LEFT(TEXT(J39,"000000000.00"))+MID(TEXT(J39,"000000000.00"),2,1)+MID(TEXT(J39,"000000000.00"),3,1))=0,,IF(AND((--MID(TEXT(J39,"000000000.00"),4,1)+MID(TEXT(J39,"000000000.00"),5,1)+MID(TEXT(J39,"000000000.00"),6,1)+MID(TEXT(J39,"000000000.00"),7,1))=0,(--MID(TEXT(J39,"000000000.00"),8,1)+RIGHT(TEXT(J39,"000000000.00")))>0)," Million and "," Million ")) &CHOOSE(MID(TEXT(J39,"000000000.00"),4,1)+1,,"One","Two","Three","Four","Five","Six","Seven","Eight","Nine") &IF(--MID(TEXT(J39,"000000000.00"),4,1)=0,,IF(AND(--MID(TEXT(J39,"000000000.00"),5,1)=0,--MID(TEXT(J39,"000000000.00"),6,1)=0)," Hundred"," Hundred and")) &CHOOSE(MID(TEXT(J39,"000000000.00"),5,1)+1,,," Twenty"," Thirty"," Forty"," Fifty"," Sixty"," Seventy"," Eighty"," Ninety") &IF(--MID(TEXT(J39,"000000000.00"),5,1)<>1,CHOOSE(MID(TEXT(J39,"000000000.00"),6,1)+1,," One"," Two"," Three"," Four"," Five"," Six"," Seven"," Eight"," Nine"),CHOOSE(MID(TEXT(J39,"000000000.00"),6,1)+1," Ten"," Eleven"," Twelve"," Thirteen"," Fourteen"," Fifteen"," Sixteen"," Seventeen"," Eighteen"," Nineteen")) &IF((--MID(TEXT(J39,"000000000.00"),4,1)+MID(TEXT(J39,"000000000.00"),5,1)+MID(TEXT(J39,"000000000.00"),6,1))=0,,IF(OR((--MID(TEXT(J39,"000000000.00"),7,1)+MID(TEXT(J39,"000000000.00"),8,1)+MID(TEXT(J39,"000000000.00"),9,1))=0,--MID(TEXT(J39,"000000000.00"),7,1)<>0)," Thousand "," Thousand and ")) &CHOOSE(MID(TEXT(J39,"000000000.00"),7,1)+1,,"One","Two","Three","Four","Five","Six","Seven","Eight","Nine") &IF(--MID(TEXT(J39,"000000000.00"),7,1)=0,,IF(AND(--MID(TEXT(J39,"000000000.00"),8,1)=0,--MID(TEXT(J39,"000000000.00"),9,1)=0)," Hundred "," Hundred and "))& CHOOSE(MID(TEXT(J39,"000000000.00"),8,1)+1,,,"Twenty ","Thirty ","Forty ","Fifty ","Sixty ","Seventy ","Eighty ","Ninety ") &IF(--MID(TEXT(J39,"000000000.00"),8,1)<>1,CHOOSE(MID(TEXT(J39,"000000000.00"),9,1)+1,,"One","Two","Three","Four","Five","Six","Seven","Eight","Nine"),CHOOSE(MID(TEXT(J39,"000000000.00"),9,1)+1,"Ten","Eleven","Twelve","Thirteen","Fourteen","Fifteen","Sixteen","Seventeen","Eighteen","Nineteen")) &IF(RIGHT(TEXT(J39,"000000000.00"),2)>"000000000.00"," & "&RIGHT(TEXT(J39,"000000000.00"),2)&" Paise Only.","Only.") -> INR Eighteen Thousand One Hundred and Forty TwoOnly.
B42: HSN Code | E42: Taxable Value | F42: Central Tax | H42: State Tax | J42: Total Tax Amount
F43: Rate | G43: Amount | H43: Rate | I43: Amount
B44: =IFERROR(VLOOKUP(F13,InvoiceDetails,18,FALSE)," ") -> 44011090 | E44: =IFERROR(VLOOKUP(F13,InvoiceDetails,26,FALSE)," ") -> 18142 | F44: =IFERROR(VLOOKUP(F13,InvoiceDetails,25,FALSE)," ") -> 0.05 | G44: =IFERROR(VLOOKUP(F13,InvoiceDetails,32,FALSE)," ") -> 863.9 | H44: 0 | I44: 0 | J44: =IFERROR(VLOOKUP(F13,InvoiceDetails,32,FALSE)," ") -> 863.9
B45: Total | E45: =E44 -> 18142 | G45: =G44 -> 863.9 | I45: =I44 -> 0 | J45: =J44 -> 863.9
B46: Tax Amount(in words)
B47: INR | C47: ="INR"&CHOOSE(LEFT(TEXT(J45,"000000000.00"))+1,,"One","Two","Three","Four","Five","Six","Seven","Eight","Nine") &IF(--LEFT(TEXT(J45,"000000000.00"))=0,,IF(AND(--MID(TEXT(J45,"000000000.00"),2,1)=0,--MID(TEXT(J45,"000000000.00"),3,1)=0)," Hundred"," Hundred and ")) &CHOOSE(MID(TEXT(J45,"000000000.00"),2,1)+1,,,"Twenty ","Thirty ","Forty ","Fifty ","Sixty ","Seventy ","Eighty ","Ninety ") &IF(--MID(TEXT(J45,"000000000.00"),2,1)<>1,CHOOSE(MID(TEXT(J45,"000000000.00"),3,1)+1,,"One","Two","Three","Four","Five","Six","Seven","Eight","Nine"), CHOOSE(MID(TEXT(J45,"000000000.00"),3,1)+1,"Ten","Eleven","Twelve","Thirteen","Fourteen","Fifteen","Sixteen","Seventeen","Eighteen","Nineteen")) &IF((--LEFT(TEXT(J45,"000000000.00"))+MID(TEXT(J45,"000000000.00"),2,1)+MID(TEXT(J45,"000000000.00"),3,1))=0,,IF(AND((--MID(TEXT(J45,"000000000.00"),4,1)+MID(TEXT(J45,"000000000.00"),5,1)+MID(TEXT(J45,"000000000.00"),6,1)+MID(TEXT(J45,"000000000.00"),7,1))=0,(--MID(TEXT(J45,"000000000.00"),8,1)+RIGHT(TEXT(J45,"000000000.00")))>0)," Million and "," Million ")) &CHOOSE(MID(TEXT(J45,"000000000.00"),4,1)+1,,"One","Two","Three","Four","Five","Six","Seven","Eight","Nine") &IF(--MID(TEXT(J45,"000000000.00"),4,1)=0,,IF(AND(--MID(TEXT(J45,"000000000.00"),5,1)=0,--MID(TEXT(J45,"000000000.00"),6,1)=0)," Hundred"," Hundred and")) &CHOOSE(MID(TEXT(J45,"000000000.00"),5,1)+1,,," Twenty"," Thirty"," Forty"," Fifty"," Sixty"," Seventy"," Eighty"," Ninety") &IF(--MID(TEXT(J45,"000000000.00"),5,1)<>1,CHOOSE(MID(TEXT(J45,"000000000.00"),6,1)+1,," One"," Two"," Three"," Four"," Five"," Six"," Seven"," Eight"," Nine"),CHOOSE(MID(TEXT(J45,"000000000.00"),6,1)+1," Ten"," Eleven"," Twelve"," Thirteen"," Fourteen"," Fifteen"," Sixteen"," Seventeen"," Eighteen"," Nineteen")) &IF((--MID(TEXT(J45,"000000000.00"),4,1)+MID(TEXT(J45,"000000000.00"),5,1)+MID(TEXT(J45,"000000000.00"),6,1))=0,,IF(OR((--MID(TEXT(J45,"000000000.00"),7,1)+MID(TEXT(J45,"000000000.00"),8,1)+MID(TEXT(J45,"000000000.00"),9,1))=0,--MID(TEXT(J45,"000000000.00"),7,1)<>0)," Thousand "," Thousand and ")) &CHOOSE(MID(TEXT(J45,"000000000.00"),7,1)+1,,"One","Two","Three","Four","Five","Six","Seven","Eight","Nine") &IF(--MID(TEXT(J45,"000000000.00"),7,1)=0,,IF(AND(--MID(TEXT(J45,"000000000.00"),8,1)=0,--MID(TEXT(J45,"000000000.00"),9,1)=0)," Hundred "," Hundred and "))& CHOOSE(MID(TEXT(J45,"000000000.00"),8,1)+1,,,"Twenty ","Thirty ","Forty ","Fifty ","Sixty ","Seventy ","Eighty ","Ninety ") &IF(--MID(TEXT(J45,"000000000.00"),8,1)<>1,CHOOSE(MID(TEXT(J45,"000000000.00"),9,1)+1,,"One","Two","Three","Four","Five","Six","Seven","Eight","Nine"),CHOOSE(MID(TEXT(J45,"000000000.00"),9,1)+1,"Ten","Eleven","Twelve","Thirteen","Fourteen","Fifteen","Sixteen","Seventeen","Eighteen","Nineteen")) &IF(RIGHT(TEXT(J45,"000000000.00"),2)>"000000000.00"," & "&RIGHT(TEXT(J45,"000000000.00"),2)&" Paise Only.","Only.") -> INREight Hundred and Sixty Three & 90 Paise Only.
B49: Remarks: | F49: BANK NAME | H49: STATE BANK OF INDIA
F50: ACCT NO. | H50: 39935045918
B51: PAN | C51: BOPPP0960N | F51: BRANCH & IFS CODE | H51: UDAY NAGAR SBIN0017637
B52: Declaration
B53: We declare that this invoice shows that the actual price of the goods described and that all particular are true and correct | H53: For MAHALAXMI AGRO ENERGIES (2024-2025)
H56: Authorised Signatory
B57: This is a computer Generated Invoice

Sheet CREDIT NOTE
B2: PURCHASE ORDER
B4: MAHALAXMI AGRO ENERGIES | F4: Invoice No. | I4: Dated
B5: 70 Mahakali Nagar 3, Mhalginagar, | F5: =IFERROR(VLOOKUP(F13,InvoiceDetails,11,FALSE)," ") | I5: =VLOOKUP(F13,InvoiceDetails,4,FALSE) -> 45757
B6: Hudkeshwar Ring Road, Nagpur 34 | F6: Delivery Note | I6: Payment Mode/Terms
B7: 8550952303 | F7: =IFERROR(VLOOKUP(F13,InvoiceDetails,5,FALSE)," ") -> - | I7: =IFERROR(VLOOKUP(F13,InvoiceDetails,6,FALSE)," ") -> -
B8: GSTN: | C8: 27BOPPP0960N1Z7 | F8: Supplier Ref. | I8: Other Reference(s)
B9: State: | C9: MAHARASHTRA | E9: 440034 | F9: =IFERROR(VLOOKUP(F13,InvoiceDetails,7,FALSE)," ") -> - | I9: =IFERROR(VLOOKUP(F13,InvoiceDetails,8,FALSE)," ") -> PO NO 25-26/001
B10: Mail: | C10: biomassenergies@gmail.com | F10: Buyer's Order No. | I10: Dated
B11: Consignee | F11: =IFERROR(VLOOKUP(F13,InvoiceDetails,9,FALSE)," ") -> - | I11: =IFERROR(VLOOKUP(F13,InvoiceDetails,10,FALSE)," ") -> 45757
B12: =VLOOKUP(F13,InvoiceDetails,2,FALSE) -> Sankalp Industries | F12: Despatch Document No. | I12: Delivery Note Date
B13: =VLOOKUP(B12,CustDetail1,2,FALSE) -> Nimbhora Lahe, Badnera Amravati | F13: MAE053 | I13: =IFERROR(VLOOKUP(F13,InvoiceDetails,12,FALSE)," ") -> -
F14: Despatched Through | I14: Destination
B15: GSTN: | C15: =VLOOKUP(B12,CustDetail1,3,FALSE) -> 27ACLFS7336L1ZF | F15: =IFERROR(VLOOKUP(F13,InvoiceDetails,13,FALSE)," ") | I15: =IFERROR(VLOOKUP(F13,InvoiceDetails,14,FALSE)," ")
B16: State: | C16: =VLOOKUP(B12,CustDetail1,4,FALSE) -> MAHARASHTRA | E16: =VLOOKUP(B12,CustDetail1,5,FALSE) -> 444601
B17: Mail: | C17: =VLOOKUP(B12,CustDetail1,6,FALSE) | F17: Bill of Landing/LR-RR No. | I17: Motor Vehicle Number
F18: =IFERROR(VLOOKUP(F13,InvoiceDetails,15,FALSE)," ") -> - | I18: =IFERROR(VLOOKUP(F13,InvoiceDetails,16,FALSE)," ")
B20: Buyer (If Other Than Consignee)
B21: =VLOOKUP(F13,InvoiceDetails,2,FALSE) -> Sankalp Industries
B22: =VLOOKUP(B21,CustDetail1,2,FALSE) -> Nimbhora Lahe, Badnera Amravati
B24: GSTN: | C24: =VLOOKUP(B12,CustDetail1,3,FALSE) -> 27ACLFS7336L1ZF
B25: State: | C25: =VLOOKUP(B12,CustDetail1,4,FALSE) -> MAHARASHTRA | E25: =VLOOKUP(B12,CustDetail1,5,FALSE) -> 444601
B26: Mail: | C26: =VLOOKUP(B12,CustDetail1,6,FALSE)
B27: Sr. No. | C27: Description Of Goods | F27: HSN Code | G27: Quatity | H27: Rate | I27: Per | J27: Amount
B28: 1 | C28: =IFERROR(VLOOKUP(F13,InvoiceDetails,17,FALSE)," ") -> BIOMASS BRIQUETTE 90MM | F28: =IFERROR(VLOOKUP(F13,InvoiceDetails,18,FALSE)," ") -> 44011090 | G28: =IFERROR(VLOOKUP(F13,InvoiceDetails,19,FALSE)," ") -> 50000 | H28: =IFERROR(VLOOKUP(F13,InvoiceDetails,20,FALSE)," ") -> 6.1 | I28: =IFERROR(VLOOKUP(F13,InvoiceDetails,21,FALSE)," ") -> KG | J28: =IFERROR(VLOOKUP(F13,InvoiceDetails,22,FALSE)," ") -> 305000
E30: IGST OUTPUT @ 5% | H30: =IFERROR(VLOOKUP(F13,InvoiceDetails,25,FALSE)," ") | J30: =IFERROR(VLOOKUP(F13,InvoiceDetails,32,FALSE)," ") -> 0
E32: ROUNDOFF | J32: =IFERROR(VLOOKUP(F13,InvoiceDetails,27,FALSE)," ") -> 0
E34: TRANSPORT/UNLOADING | J34: =IFERROR(VLOOKUP(F13,InvoiceDetails,28,FALSE)," ")
E39: Total | G39: =SUM(G28:G38) -> 50000 | J39: =IFERROR(VLOOKUP(F13,InvoiceDetails,26,FALSE)," ") -> 320250
B40: Amount Chargeable(in words) | J40: E. & O.E
B41: INR | C41: ="INR"&CHOOSE(LEFT(TEXT(J39,"000000000.00"))+1,,"One","Two","Three","Four","Five","Six","Seven","Eight","Nine") &IF(--LEFT(TEXT(J39,"000000000.00"))=0,,IF(AND(--MID(TEXT(J39,"000000000.00"),2,1)=0,--MID(TEXT(J39,"000000000.00"),3,1)=0)," Hundred"," Hundred and ")) &CHOOSE(MID(TEXT(J39,"000000000.00"),2,1)+1,,,"Twenty ","Thirty ","Forty ","Fifty ","Sixty ","Seventy ","Eighty ","Ninety ") &IF(--MID(TEXT(J39,"000000000.00"),2,1)<>1,CHOOSE(MID(TEXT(J39,"000000000.00"),3,1)+1,,"One","Two","Three","Four","Five","Six","Seven","Eight","Nine"), CHOOSE(MID(TEXT(J39,"000000000.00"),3,1)+1,"Ten","Eleven","Twelve","Thirteen","Fourteen","Fifteen","Sixteen","Seventeen","Eighteen","Nineteen")) &IF((--LEFT(TEXT(J39,"000000000.00"))+MID(TEXT(J39,"000000000.00"),2,1)+MID(TEXT(J39,"000000000.00"),3,1))=0,,IF(AND((--MID(TEXT(J39,"000000000.00"),4,1)+MID(TEXT(J39,"000000000.00"),5,1)+MID(TEXT(J39,"000000000.00"),6,1)+MID(TEXT(J39,"000000000.00"),7,1))=0,(--MID(TEXT(J39,"000000000.00"),8,1)+RIGHT(TEXT(J39,"000000000.00")))>0)," Million and "," Million ")) &CHOOSE(MID(TEXT(J39,"000000000.00"),4,1)+1,,"One","Two","Three","Four","Five","Six","Seven","Eight","Nine") &IF(--MID(TEXT(J39,"000000000.00"),4,1)=0,,IF(AND(--MID(TEXT(J39,"000000000.00"),5,1)=0,--MID(TEXT(J39,"000000000.00"),6,1)=0)," Hundred"," Hundred and")) &CHOOSE(MID(TEXT(J39,"000000000.00"),5,1)+1,,," Twenty"," Thirty"," Forty"," Fifty"," Sixty"," Seventy"," Eighty"," Ninety") &IF(--MID(TEXT(J39,"000000000.00"),5,1)<>1,CHOOSE(MID(TEXT(J39,"000000000.00"),6,1)+1,," One"," Two"," Three"," Four"," Five"," Six"," Seven"," Eight"," Nine"),CHOOSE(MID(TEXT(J39,"000000000.00"),6,1)+1," Ten"," Eleven"," Twelve"," Thirteen"," Fourteen"," Fifteen"," Sixteen"," Seventeen"," Eighteen"," Nineteen")) &IF((--MID(TEXT(J39,"000000000.00"),4,1)+MID(TEXT(J39,"000000000.00"),5,1)+MID(TEXT(J39,"000000000.00"),6,1))=0,,IF(OR((--MID(TEXT(J39,"000000000.00"),7,1)+MID(TEXT(J39,"000000000.00"),8,1)+MID(TEXT(J39,"000000000.00"),9,1))=0,--MID(TEXT(J39,"000000000.00"),7,1)<>0)," Thousand "," Thousand and ")) &CHOOSE(MID(TEXT(J39,"000000000.00"),7,1)+1,,"One","Two","Three","Four","Five","Six","Seven","Eight","Nine") &IF(--MID(TEXT(J39,"000000000.00"),7,1)=0,,IF(AND(--MID(TEXT(J39,"000000000.00"),8,1)=0,--MID(TEXT(J39,"000000000.00"),9,1)=0)," Hundred "," Hundred and "))& CHOOSE(MID(TEXT(J39,"000000000.00"),8,1)+1,,,"Twenty ","Thirty ","Forty ","Fifty ","Sixty ","Seventy ","Eighty ","Ninety ") &IF(--MID(TEXT(J39,"000000000.00"),8,1)<>1,CHOOSE(MID(TEXT(J39,"000000000.00"),9,1)+1,,"One","Two","Three","Four","Five","Six","Seven","Eight","Nine"),CHOOSE(MID(TEXT(J39,"000000000.00"),9,1)+1,"Ten","Eleven","Twelve","Thirteen","Fourteen","Fifteen","Sixteen","Seventeen","Eighteen","Nineteen")) &IF(RIGHT(TEXT(J39,"000000000.00"),2)>"000000000.00"," & "&RIGHT(TEXT(J39,"000000000.00"),2)&" Paise Only.","Only.") -> INRThree Hundred and Twenty Thousand Two Hundred and Fifty Only.
B42: HSN Code | E42: Taxable Value | F42: Central Tax | H42: State Tax | J42: Total Tax Amount
F43: Rate | G43: Amount | H43: Rate | I43: Amount
B44: =IFERROR(VLOOKUP(F13,InvoiceDetails,18,FALSE)," ") -> 44011090 | E44: =IFERROR(VLOOKUP(F13,InvoiceDetails,26,FALSE)," ") -> 320250 | F44: =IFERROR(VLOOKUP(F13,InvoiceDetails,25,FALSE)," ") | G44: =IFERROR(VLOOKUP(F13,InvoiceDetails,32,FALSE)," ") -> 0 | H44: 0 | I44: 0 | J44: =IFERROR(VLOOKUP(F13,InvoiceDetails,32,FALSE)," ") -> 0
B45: Total | E45: =E44 -> 320250 | G45: =G44 -> 0 | I45: =I44 -> 0 | J45: =J44 -> 0
B46: Tax Amount(in words)
B47: INR | C47: ="INR"&CHOOSE(LEFT(TEXT(J45,"000000000.00"))+1,,"One","Two","Three","Four","Five","Six","Seven","Eight","Nine") &IF(--LEFT(TEXT(J45,"000000000.00"))=0,,IF(AND(--MID(TEXT(J45,"000000000.00"),2,1)=0,--MID(TEXT(J45,"000000000.00"),3,1)=0)," Hundred"," Hundred and ")) &CHOOSE(MID(TEXT(J45,"000000000.00"),2,1)+1,,,"Twenty ","Thirty ","Forty ","Fifty ","Sixty ","Seventy ","Eighty ","Ninety ") &IF(--MID(TEXT(J45,"000000000.00"),2,1)<>1,CHOOSE(MID(TEXT(J45,"000000000.00"),3,1)+1,,"One","Two","Three","Four","Five","Six","Seven","Eight","Nine"), CHOOSE(MID(TEXT(J45,"000000000.00"),3,1)+1,"Ten","Eleven","Twelve","Thirteen","Fourteen","Fifteen","Sixteen","Seventeen","Eighteen","Nineteen")) &IF((--LEFT(TEXT(J45,"000000000.00"))+MID(TEXT(J45,"000000000.00"),2,1)+MID(TEXT(J45,"000000000.00"),3,1))=0,,IF(AND((--MID(TEXT(J45,"000000000.00"),4,1)+MID(TEXT(J45,"000000000.00"),5,1)+MID(TEXT(J45,"000000000.00"),6,1)+MID(TEXT(J45,"000000000.00"),7,1))=0,(--MID(TEXT(J45,"000000000.00"),8,1)+RIGHT(TEXT(J45,"000000000.00")))>0)," Million and "," Million ")) &CHOOSE(MID(TEXT(J45,"000000000.00"),4,1)+1,,"One","Two","Three","Four","Five","Six","Seven","Eight","Nine") &IF(--MID(TEXT(J45,"000000000.00"),4,1)=0,,IF(AND(--MID(TEXT(J45,"000000000.00"),5,1)=0,--MID(TEXT(J45,"000000000.00"),6,1)=0)," Hundred"," Hundred and")) &CHOOSE(MID(TEXT(J45,"000000000.00"),5,1)+1,,," Twenty"," Thirty"," Forty"," Fifty"," Sixty"," Seventy"," Eighty"," Ninety") &IF(--MID(TEXT(J45,"000000000.00"),5,1)<>1,CHOOSE(MID(TEXT(J45,"000000000.00"),6,1)+1,," One"," Two"," Three"," Four"," Five"," Six"," Seven"," Eight"," Nine"),CHOOSE(MID(TEXT(J45,"000000000.00"),6,1)+1," Ten"," Eleven"," Twelve"," Thirteen"," Fourteen"," Fifteen"," Sixteen"," Seventeen"," Eighteen"," Nineteen")) &IF((--MID(TEXT(J45,"000000000.00"),4,1)+MID(TEXT(J45,"000000000.00"),5,1)+MID(TEXT(J45,"000000000.00"),6,1))=0,,IF(OR((--MID(TEXT(J45,"000000000.00"),7,1)+MID(TEXT(J45,"000000000.00"),8,1)+MID(TEXT(J45,"000000000.00"),9,1))=0,--MID(TEXT(J45,"000000000.00"),7,1)<>0)," Thousand "," Thousand and ")) &CHOOSE(MID(TEXT(J45,"000000000.00"),7,1)+1,,"One","Two","Three","Four","Five","Six","Seven","Eight","Nine") &IF(--MID(TEXT(J45,"000000000.00"),7,1)=0,,IF(AND(--MID(TEXT(J45,"000000000.00"),8,1)=0,--MID(TEXT(J45,"000000000.00"),9,1)=0)," Hundred "," Hundred and "))& CHOOSE(MID(TEXT(J45,"000000000.00"),8,1)+1,,,"Twenty ","Thirty ","Forty ","Fifty ","Sixty ","Seventy ","Eighty ","Ninety ") &IF(--MID(TEXT(J45,"000000000.00"),8,1)<>1,CHOOSE(MID(TEXT(J45,"000000000.00"),9,1)+1,,"One","Two","Three","Four","Five","Six","Seven","Eight","Nine"),CHOOSE(MID(TEXT(J45,"000000000.00"),9,1)+1,"Ten","Eleven","Twelve","Thirteen","Fourteen","Fifteen","Sixteen","Seventeen","Eighteen","Nineteen")) &IF(RIGHT(TEXT(J45,"000000000.00"),2)>"000000000.00"," & "&RIGHT(TEXT(J45,"000000000.00"),2)&" Paise Only.","Only.") -> INROnly.
B49: Remarks: | F49: BANK NAME | H49: STATE BANK OF INDIA
F50: ACCT NO. | H50: 39935045918
B51: PAN | C51: BOPPP0960N | F51: BRANCH & IFS CODE | H51: UDAY NAGAR SBIN0017637
B52: Declaration
B53: We declare that this invoice shows that the actual price of the goods described and that all particular are true and correct | H53: For MAHALAXMI AGRO ENERGIES (2024-2025)
H56: Authorised Signatory
B57: This is a computer Generated Invoice

Sheet INVOICE DETAILS
A1: Invoice Number | B1: Consignee Name | C1: Buyer | D1: Dated | E1: Delivery Note | F1: Payment Mode/Terms | G1: Supplier Ref. | H1: Other Reference(s) | I1: Buyer's Order No. | J1: Date | K1: Despatch Document No. | L1: Delivery Note Date | M1: Despatch through | N1: Destination | O1: Bill of Landing/LR-RR No. | P1: Motor Vehicle Number | Q1: Description of Goods | R1: HSN Code | S1: QTY | T1: Rate | U1: per(wt) | V1: Amount | W1: SGST | X1: CGST | Y1: IGST | Z1: Total | AA1: Roundoff | AB1: Transport | AC1: Taxable Value | AD1: SGST AMT | AE1: CGST AMT | AF1: IGST | AG1: Tax Total | AH1: Month | AI1: Year
A2: MAE001/2021-24 | B2: =VLOOKUP((LEFT(A2,6)),CUSTOMER_DETAILS,2,FALSE) -> JEEVIKA YUGCHEM PVT LTD. | C2: - | D2: 44220 | E2: - | F2: - | G2: - | H2: - | I2: JYC/PO/PM/20-21/231 | J2: 44217 | K2: 1 | L2: - | M2: TRUCK | N2: MIDC Butibori | O2: - | P2: MH40N8211 | Q2: BIOMASS BRIQUETTE 90MM | R2: =VLOOKUP(Q2,'PRODUCT TABLE'!$A$2:$B$26,2,FALSE) -> 44011090 | S2: 10900 | T2: 5.05 | U2: KG | V2: =S2*T2 -> 55045 | W2: 0.025 | X2: 0.025 | Y2: 0 | Z2: =IF(((ROUNDUP((AG2+V2),0))-(AG2+V2))>0.49,ROUNDdown((AG2+V2),0),ROUNDup((AG2+V2),0)) + AB2 -> 57797 | AA2: =Z2-(V2+AG2 + AB2) -> -0.25 | AC2: =V2 -> 55045 | AD2: =AC2*W2 -> 1376.125 | AE2: =AC2*X2 -> 1376.125 | AF2: =AC2*Y2 -> 0 | AG2: =SUM(AD2:AF2) -> 2752.25 | AH2: =IFERROR(MONTH(D2)," ") -> 1 | AI2: =YEAR(D2) -> 2021
A3: MAE001/2021-02 | B3: =VLOOKUP((LEFT(A3,6)),CUSTOMER_DETAILS,2,FALSE) -> JEEVIKA YUGCHEM PVT LTD. | C3: - | D3: 44231 | E3: - | F3: - | G3: - | H3: - | I3: JYC/PO/PM/20-21/236 | J3: 44217 | K3: 2 | L3: - | M3: TRUCK | N3: MIDC Butibori | O3: - | P3: MH40N8725 | Q3: BIOMASS BRIQUETTE 90MM | R3: =VLOOKUP(Q3,'PRODUCT TABLE'!$A$2:$B$26,2,FALSE) -> 44011090 | S3: 9430 | T3: 5.05 | U3: KG | V3: =S3*T3 -> 47621.5 | W3: 0.025 | X3: 0.025 | Y3: 0 | Z3: =IF(((ROUNDUP((AG3+V3),0))-(AG3+V3))>0.49,ROUNDdown((AG3+V3),0),ROUNDup((AG3+V3),0)) + AB3 -> 50003 | AA3: =Z3-(V3+AG3 + AB3) -> 0.425 | AC3: =V3 -> 47621.5 | AD3: =AC3*W3 -> 1190.5375 | AE3: =AC3*X3 -> 1190.5375 | AF3: =AC3*Y3 -> 0 | AG3: =SUM(AD3:AF3) -> 2381.075 | AH3: =IFERROR(MONTH(D3)," ") -> 2 | AI3: =YEAR(D3) -> 2021
A4: MAE001/2021-03 | B4: =VLOOKUP((LEFT(A4,6)),CUSTOMER_DETAILS,2,FALSE) -> JEEVIKA YUGCHEM PVT LTD. | C4: - | D4: 44243 | E4: - | F4: - | G4: - | H4: - | I4: JYC/PO/PM/20-21/236 | J4: 44217 | K4: 3 | L4: - | M4: TRUCK | N4: MIDC Butibori | O4: - | P4: MH40N8500 | Q4: BIOMASS BRIQUETTE 90MM | R4: =VLOOKUP(Q4,'PRODUCT TABLE'!$A$2:$B$26,2,FALSE) -> 44011090 | S4: 9365 | T4: 5.05 | U4: KG | V4: =S4*T4 -> 47293.25 | W4: 0.025 | X4: 0.025 | Y4: 0 | Z4: =IF(((ROUNDUP((AG4+V4),0))-(AG4+V4))>0.49,ROUNDdown((AG4+V4),0),ROUNDup((AG4+V4),0)) + AB4 -> 49658 | AA4: =Z4-(V4+AG4 + AB4) -> 0.0875 | AC4: =V4 -> 47293.25 | AD4: =AC4*W4 -> 1182.3312 | AE4: =AC4*X4 -> 1182.3312 | AF4: =AC4*Y4 -> 0 | AG4: =SUM(AD4:AF4) -> 2364.6625 | AH4: =IFERROR(MONTH(D4)," ") -> 2 | AI4: =YEAR(D4) -> 2021
A5: MAE001/2021-04 | B5: =VLOOKUP((LEFT(A5,6)),CUSTOMER_DETAILS,2,FALSE) -> JEEVIKA YUGCHEM PVT LTD. | C5: - | D5: 44253 | E5: - | F5: - | G5: - | H5: - | I5: JYC/PO/PM/20-21/236 | J5: 44253 | K5: 4 | L5: - | M5: TRUCK | N5: MIDC Butibori | O5: - | P5: MH14BT0796 | Q5: BIOMASS BRIQUETTE 90MM | R5: =VLOOKUP(Q5,'PRODUCT TABLE'!$A$2:$B$26,2,FALSE) -> 44011090 | S5: 10030 | T5: 5.05 | U5: KG | V5: =S5*T5 -> 50651.5 | W5: 0.025 | X5: 0.025 | Y5: 0 | Z5: =IF(((ROUNDUP((AG5+V5),0))-(AG5+V5))>0.49,ROUNDdown((AG5+V5),0),ROUNDup((AG5+V5),0)) + AB5 -> 53184 | AA5: =Z5-(V5+AG5 + AB5) -> -0.075 | AC5: =V5 -> 50651.5 | AD5: =AC5*W5 -> 1266.2875 | AE5: =AC5*X5 -> 1266.2875 | AF5: =AC5*Y5 -> 0 | AG5: =SUM(AD5:AF5) -> 2532.575 | AH5: =IFERROR(MONTH(D5)," ") -> 2 | AI5: =YEAR(D5) -> 2021
A6: MAE001/2021-05 | B6: =VLOOKUP((LEFT(A6,6)),CUSTOMER_DETAILS,2,FALSE) -> JEEVIKA YUGCHEM PVT LTD. | C6: - | D6: 44277 | E6: - | F6: - | G6: - | H6: - | I6: JYC/PO/PM/20-21/236 | J6: 44277 | K6: 5 | L6: - | M6: TRUCK | N6: MIDC Butibori | O6: - | P6: MH40N8542 | Q6: BIOMASS BRIQUETTE 90MM | R6: =VLOOKUP(Q6,'PRODUCT TABLE'!$A$2:$B$26,2,FALSE) -> 44011090 | S6: 10640 | T6: 5.05 | U6: KG | V6: =S6*T6 -> 53732 | W6: 0.025 | X6: 0.025 | Y6: 0 | Z6: =IF(((ROUNDUP((AG6+V6),0))-(AG6+V6))>0.49,ROUNDdown((AG6+V6),0),ROUNDup((AG6+V6),0)) + AB6 -> 56419 | AA6: =Z6-(V6+AG6 + AB6) -> 0.4 | AC6: =V6 -> 53732 | AD6: =AC6*W6 -> 1343.3 | AE6: =AC6*X6 -> 1343.3 | AF6: =AC6*Y6 -> 0 | AG6: =SUM(AD6:AF6) -> 2686.6 | AH6: =IFERROR(MONTH(D6)," ") -> 3 | AI6: =YEAR(D6) -> 2021
A7: MAE001/2021-06 | B7: =VLOOKUP((LEFT(A7,6)),CUSTOMER_DETAILS,2,FALSE) -> JEEVIKA YUGCHEM PVT LTD. | C7: - | D7: 44305 | E7: - | F7: - | G7: - | H7: - | I7: JYC/PO/PM/20-21/236 | J7: =D7 -> 44305 | K7: 6 | L7: - | M7: TRUCK | N7: MIDC Butibori | O7: - | P7: MH07C7315 | Q7: BIOMASS BRIQUETTE 90MM | R7: =VLOOKUP(Q7,'PRODUCT TABLE'!$A$2:$B$26,2,FALSE) -> 44011090 | S7: 11120 | T7: 5.05 | U7: KG | V7: =S7*T7 -> 56156 | W7: 0.025 | X7: 0.025 | Y7: 0 | Z7: =IF(((ROUNDUP((AG7+V7),0))-(AG7+V7))>0.49,ROUNDdown((AG7+V7),0),ROUNDup((AG7+V7),0)) + AB7 -> 58964 | AA7: =Z7-(V7+AG7 + AB7) -> 0.2 | AC7: =V7 -> 56156 | AD7: =AC7*W7 -> 1403.9 | AE7: =AC7*X7 -> 1403.9 | AF7: =AC7*Y7 -> 0 | AG7: =SUM(AD7:AF7) -> 2807.8 | AH7: =IFERROR(MONTH(D7)," ") -> 4 | AI7: =YEAR(D7) -> 2021
A8: MAE002/2021-01 | B8: =VLOOKUP((LEFT(A8,6)),CUSTOMER_DETAILS,2,FALSE) -> PDDR MEDICAL PRODUCTS & SERVICES PVT LTD | C8: - | D8: 44317 | E8: - | F8: - | G8: - | H8: - | I8: - | J8: 44317 | K8: 7 | L8: - | M8: TRUCK | N8: Hingana | O8: - | P8: MH40N0129 | Q8: BIOMASS BRIQUETTE 90MM | R8: =VLOOKUP(Q8,'PRODUCT TABLE'!$A$2:$B$26,2,FALSE) -> 44011090 | S8: 10100 | T8: 5.05 | U8: KG | V8: =S8*T8 -> 51005 | W8: 0.025 | X8: 0.025 | Y8: 0 | Z8: =IF(((ROUNDUP((AG8+V8),0))-(AG8+V8))>0.49,ROUNDdown((AG8+V8),0),ROUNDup((AG8+V8),0)) + AB8 -> 53555 | AA8: =Z8-(V8+AG8 + AB8) -> -0.25 | AC8: =V8 -> 51005 | AD8: =AC8*W8 -> 1275.125 | AE8: =AC8*X8 -> 1275.125 | AF8: =AC8*Y8 -> 0 | AG8: =SUM(AD8:AF8) -> 2550.25 | AH8: =IFERROR(MONTH(D8)," ") -> 5 | AI8: =YEAR(D8) -> 2021
A9: MAE002/2021-02 | B9: =VLOOKUP((LEFT(A9,6)),CUSTOMER_DETAILS,2,FALSE) -> PDDR MEDICAL PRODUCTS & SERVICES PVT LTD | C9: - | D9: 44348 | E9: - | F9: - | G9: - | H9: - | I9: - | J9: 44348 | K9: 8 | L9: - | M9: TRUCK | N9: Hingana | O9: - | P9: MH40N6407 | Q9: BIOMASS BRIQUETTE 90MM | R9: =VLOOKUP(Q9,'PRODUCT TABLE'!$A$2:$B$26,2,FALSE) -> 44011090 | S9: 7760 | T9: 5.05 | U9: KG | V9: =S9*T9 -> 39188 | W9: 0.025 | X9: 0.025 | Y9: 0 | Z9: =IF(((ROUNDUP((AG9+V9),0))-(AG9+V9))>0.49,ROUNDdown((AG9+V9),0),ROUNDup((AG9+V9),0)) + AB9 -> 41147 | AA9: =Z9-(V9+AG9 + AB9) -> -0.4 | AC9: =V9 -> 39188 | AD9: =AC9*W9 -> 979.7 | AE9: =AC9*X9 -> 979.7 | AF9: =AC9*Y9 -> 0 | AG9: =SUM(AD9:AF9) -> 1959.4 | AH9: =IFERROR(MONTH(D9)," ") -> 6 | AI9: =YEAR(D9) -> 2021
A10: MAE003/2021-01 | B10: =VLOOKUP((LEFT(A10,6)),CUSTOMER_DETAILS,2,FALSE) -> SHREE GAYATRI PACKAGING | C10: - | D10: 44373 | E10: - | F10: - | G10: - | H10: - | I10: - | J10: 44373 | K10: 9 | L10: - | M10: PVT VHCL | N10: WARDHA | O10: - | P10: MH49AS | Q10: BIOMASS PELLET 06MM | R10: =VLOOKUP(Q10,'PRODUCT TABLE'!$A$2:$B$26,2,FALSE) -> 44011090 | S10: 630 | T10: 10.8 | U10: KG | V10: =S10*T10 -> 6804 | W10: 0.025 | X10: 0.025 | Y10: 0 | Z10: =IF(((ROUNDUP((AG10+V10),0))-(AG10+V10))>0.49,ROUNDdown((AG10+V10),0),ROUNDup((AG10+V10),0)) + AB10 -> 7144 | AA10: =Z10-(V10+AG10 + AB10) -> -0.2 | AC10: =V10 -> 6804 | AD10: =AC10*W10 -> 170.1 | AE10: =AC10*X10 -> 170.1 | AF10: =AC10*Y10 -> 0 | AG10: =SUM(AD10:AF10) -> 340.2 | AH10: =IFERROR(MONTH(D10)," ") -> 6 | AI10: =YEAR(D10) -> 2021
A11: MAE002/2021-03 | B11: =VLOOKUP((LEFT(A11,6)),CUSTOMER_DETAILS,2,FALSE) -> PDDR MEDICAL PRODUCTS & SERVICES PVT LTD | C11: - | D11: 44367 | E11: - | F11: - | G11: - | H11: - | I11: - | J11: 44367 | K11: 10 | L11: - | M11: TRUCK | N11: Hingana | O11: - | Q11: BIOMASS BRIQUETTE 90MM | R11: =VLOOKUP(Q11,'PRODUCT TABLE'!$A$2:$B$26,2,FALSE) -> 44011090 | S11: 7560 | T11: 5.15 | U11: KG | V11: =S11*T11 -> 38934 | W11: 0.025 | X11: 0.025 | Y11: 0 | Z11: =IF(((ROUNDUP((AG11+V11),0))-(AG11+V11))>0.49,ROUNDdown((AG11+V11),0),ROUNDup((AG11+V11),0)) + AB11 -> 40881 | AA11: =Z11-(V11+AG11 + AB11) -> 0.3 | AC11: =V11 -> 38934 | AD11: =AC11*W11 -> 973.35 | AE11: =AC11*X11 -> 973.35 | AF11: =AC11*Y11 -> 0 | AG11: =SUM(AD11:AF11) -> 1946.7 | AH11: =IFERROR(MONTH(D11)," ") -> 6 | AI11: =YEAR(D11) -> 2021
A12: MAE002/2021-04 | B12: =VLOOKUP((LEFT(A12,6)),CUSTOMER_DETAILS,2,FALSE) -> PDDR MEDICAL PRODUCTS & SERVICES PVT LTD | C12: - | D12: 44387 | E12: - | F12: - | G12: - | H12: - | I12: - | J12: 44389 | K12: 11 | L12: - | M12: TRUCK | N12: Hingana | O12: - | P12: MH40L2873 | Q12: BIOMASS BRIQUETTE 90MM | R12: =VLOOKUP(Q12,'PRODUCT TABLE'!$A$2:$B$26,2,FALSE) -> 44011090 | S12: 7420 | T12: 5.5 | U12: KG | V12: =S12*T12 -> 40810 | W12: 0.025 | X12: 0.025 | Y12: 0 | Z12: =IF(((ROUNDUP((AG12+V12),0))-(AG12+V12))>0.49,ROUNDdown((AG12+V12),0),ROUNDup((AG12+V12),0)) + AB12 -> 42850 | AA12: =Z12-(V12+AG12 + AB12) -> -0.5 | AC12: =V12 -> 40810 | AD12: =AC12*W12 -> 1020.25 | AE12: =AC12*X12 -> 1020.25 | AF12: =AC12*Y12 -> 0 | AG12: =SUM(AD12:AF12) -> 2040.5 | AH12: =IFERROR(MONTH(D12)," ") -> 7 | AI12: =YEAR(D12) -> 2021
A13: MAE003 | B13: =iferror(VLOOKUP((LEFT(A13,6)),CUSTOMER_DETAILS,2,FALSE),"-") -> SHREE GAYATRI PACKAGING | C13: - | D13: 44403 | E13: - | F13: - | G13: - | H13: - | I13: - | J13: =D13 -> 44403 | K13: 12 | L13: - | M13: TRUCK | N13: SELDOH NAGPUR | O13: - | Q13: BIOMASS PELLET 06MM | R13: =IFERROR(VLOOKUP(Q13,'PRODUCT TABLE'!$A$2:$B$26,2,FALSE),"-") -> 44011090 | S13: 900 | T13: 10.8 | U13: KG | V13: =S13*T13 -> 9720 | W13: 0.025 | X13: 0.025 | Y13: 0 | Z13: =IF(((ROUNDUP((AG13+V13),0))-(AG13+V13))>0.49,ROUNDdown((AG13+V13),0),ROUNDup((AG13+V13),0)) + AB13 -> 10206 | AA13: =Z13-(V13+AG13 + AB13) -> 0 | AC13: =V13 -> 9720 | AD13: =AC13*W13 -> 243 | AE13: =AC13*X13 -> 243 | AF13: =AC13*Y13 -> 0 | AG13: =SUM(AD13:AF13) -> 486 | AH13: =IFERROR(MONTH(D13)," ") -> 7 | AI13: =YEAR(D13) -> 2021
A14: MAE003 | B14: =iferror(VLOOKUP((LEFT(A14,6)),CUSTOMER_DETAILS,2,FALSE),"-") -> SHREE GAYATRI PACKAGING | C14: - | D14: 44416 | E14: - | F14: - | G14: - | H14: - | I14: - | J14: =D14 -> 44416 | K14: 15 | L14: - | M14: TRUCK | N14: SELDOH NAGPUR | O14: - | Q14: BIOMASS PELLET 06MM | R14: =IFERROR(VLOOKUP(Q14,'PRODUCT TABLE'!$A$2:$B$26,2,FALSE),"-") -> 44011090 | S14: 1000 | T14: 10.8 | U14: KG | V14: =S14*T14 -> 10800 | W14: 0.025 | X14: 0.025 | Y14: 0 | Z14: =IF(((ROUNDUP((AG14+V14),0))-(AG14+V14))>0.49,ROUNDdown((AG14+V14),0),ROUNDup((AG14+V14),0)) + AB14 -> 11340 | AA14: =Z14-(V14+AG14 + AB14) -> 0 | AC14: =V14 -> 10800 | AD14: =AC14*W14 -> 270 | AE14: =AC14*X14 -> 270 | AF14: =AC14*Y14 -> 0 | AG14: =SUM(AD14:AF14) -> 540 | AH14: =IFERROR(MONTH(D14)," ") -> 8 | AI14: =YEAR(D14) -> 2021
A15: MAE003 | B15: =iferror(VLOOKUP((LEFT(A15,6)),CUSTOMER_DETAILS,2,FALSE),"-") -> SHREE GAYATRI PACKAGING | C15: - | D15: 44438 | E15: - | F15: - | G15: - | H15: - | I15: - | J15: =D15 -> 44438 | K15: 16 | L15: - | M15: TRUCK | N15: SELDOH NAGPUR | O15: - | Q15: BIOMASS PELLET 06MM | R15: =IFERROR(VLOOKUP(Q15,'PRODUCT TABLE'!$A$2:$B$26,2,FALSE),"-") -> 44011090 | S15: 1625 | T15: 10.8 | U15: KG | V15: =S15*T15 -> 17550 | W15: 0.025 | X15: 0.025 | Y15: 0 | Z15: =IF(((ROUNDUP((AG15+V15),0))-(AG15+V15))>0.49,ROUNDdown((AG15+V15),0),ROUNDup((AG15+V15),0)) + AB15 -> 18427 | AA15: =Z15-(V15+AG15 + AB15) -> -0.5 | AC15: =V15 -> 17550 | AD15: =AC15*W15 -> 438.75 | AE15: =AC15*X15 -> 438.75 | AF15: =AC15*Y15 -> 0 | AG15: =SUM(AD15:AF15) -> 877.5 | AH15: =IFERROR(MONTH(D15)," ") -> 8 | AI15: =YEAR(D15) -> 2021
A16: MAE003 | B16: =iferror(VLOOKUP((LEFT(A16,6)),CUSTOMER_DETAILS,2,FALSE),"-") -> SHREE GAYATRI PACKAGING | C16: - | D16: 44482 | E16: - | F16: - | G16: - | H16: - | I16: - | J16: =D16 -> 44482 | K16: 17 | L16: - | M16: TRUCK | N16: SELDOH NAGPUR | O16: - | Q16: BIOMASS PELLET 06MM | R16: =IFERROR(VLOOKUP(Q16,'PRODUCT TABLE'!$A$2:$B$26,2,FALSE),"-") -> 44011090 | S16: 1000 | T16: 10.3 | U16: KG | V16: =S16*T16 -> 10300 | W16: 0.025 | X16: 0.025 | Y16: 0 | Z16: =IF(((ROUNDUP((AG16+V16),0))-(AG16+V16))>0.49,ROUNDdown((AG16+V16),0),ROUNDup((AG16+V16),0)) + AB16 -> 10815 | AA16: =Z16-(V16+AG16 + AB16) -> 0 | AC16: =V16 -> 10300 | AD16: =AC16*W16 -> 257.5 | AE16: =AC16*X16 -> 257.5 | AF16: =AC16*Y16 -> 0 | AG16: =SUM(AD16:AF16) -> 515 | AH16: =IFERROR(MONTH(D16)," ") -> 10 | AI16: =YEAR(D16) -> 2021
A17: MAE003 | B17: =iferror(VLOOKUP((LEFT(A17,6)),CUSTOMER_DETAILS,2,FALSE),"-") -> SHREE GAYATRI PACKAGING | C17: - | D17: 44518 | E17: - | F17: - | G17: - | H17: - | I17: - | J17: =D17 -> 44518 | K17: 18 | L17: - | M17: TRUCK | N17: SELDOH NAGPUR | O17: - | Q17: BIOMASS PELLET 06MM | R17: =IFERROR(VLOOKUP(Q17,'PRODUCT TABLE'!$A$2:$B$26,2,FALSE),"-") -> 44011090 | S17: 300 | T17: 10.3 | U17: KG | V17: =S17*T17 -> 3090 | W17: 0.025 | X17: 0.025 | Y17: 0 | Z17: =IF(((ROUNDUP((AG17+V17),0))-(AG17+V17))>0.49,ROUNDdown((AG17+V17),0),ROUNDup((AG17+V17),0)) + AB17 -> 3244 | AA17: =Z17-(V17+AG17 + AB17) -> -0.5 | AC17: =V17 -> 3090 | AD17: =AC17*W17 -> 77.25 | AE17: =AC17*X17 -> 77.25 | AF17: =AC17*Y17 -> 0 | AG17: =SUM(AD17:AF17) -> 154.5 | AH17: =IFERROR(MONTH(D17)," ") -> 11 | AI17: =YEAR(D17) -> 2021
A18: MAE010 | B18: =iferror(VLOOKUP((LEFT(A18,6)),CUSTOMER_DETAILS,2,FALSE),"-") -> KRISHNA ENTERPRISES | C18: - | D18: 44536 | E18: - | F18: - | G18: - | H18: - | I18: - | J18: =D18 -> 44536 | K18: 19 | L18: - | M18: TRUCK | N18: NAGPUR | O18: - | Q18: BIOMASS PELLET 06MM | R18: =IFERROR(VLOOKUP(Q18,'PRODUCT TABLE'!$A$2:$B$26,2,FALSE),"-") -> 44011090 | S18: 1360 | T18: 11 | U18: KG | V18: =S18*T18 -> 14960 | W18: 0.025 | X18: 0.025 | Y18: 0 | Z18: =IF(((ROUNDUP((AG18+V18),0))-(AG18+V18))>0.49,ROUNDdown((AG18+V18),0),ROUNDup((AG18+V18),0)) + AB18 -> 15708 | AA18: =Z18-(V18+AG18 + AB18) -> 0 | AC18: =V18 -> 14960 | AD18: =AC18*W18 -> 374 | AE18: =AC18*X18 -> 374 | AF18: =AC18*Y18 -> 0 | AG18: =SUM(AD18:AF18) -> 748 | AH18: =IFERROR(MONTH(D18)," ") -> 12 | AI18: =YEAR(D18) -> 2021
A19: MAE003 | B19: =iferror(VLOOKUP((LEFT(A19,6)),CUSTOMER_DETAILS,2,FALSE),"-") -> SHREE GAYATRI PACKAGING | C19: - | D19: 44545 | E19: - | F19: - | G19: - | H19: - | I19: - | J19: =D19 -> 44545 | K19: 20 | L19: - | M19: TRUCK | N19: SELDOH NAGPUR | O19: - | Q19: BIOMASS PELLET 06MM | R19: =IFERROR(VLOOKUP(Q19,'PRODUCT TABLE'!$A$2:$B$26,2,FALSE),"-") -> 44011090 | S19: 1115 | T19: 10.5 | U19: KG | V19: =S19*T19 -> 11707.5 | W19: 0.025 | X19: 0.025 | Y19: 0 | Z19: =IF(((ROUNDUP((AG19+V19),0))-(AG19+V19))>0.49,ROUNDdown((AG19+V19),0),ROUNDup((AG19+V19),0)) + AB19 -> 12293 | AA19: =Z19-(V19+AG19 + AB19) -> 0.125 | AC19: =V19 -> 11707.5 | AD19: =AC19*W19 -> 292.6875 | AE19: =AC19*X19 -> 292.6875 | AF19: =AC19*Y19 -> 0 | AG19: =SUM(AD19:AF19) -> 585.375 | AH19: =IFERROR(MONTH(D19)," ") -> 12 | AI19: =YEAR(D19) -> 2021
A20: MAE010 | B20: =iferror(VLOOKUP((LEFT(A20,6)),CUSTOMER_DETAILS,2,FALSE),"-") -> KRISHNA ENTERPRISES | C20: - | D20: 44544 | E20: - | F20: - | G20: - | H20: - | I20: - | J20: =D20 -> 44544 | K20: 21 | L20: - | M20: TRUCK | N20: SELDOH NAGPUR | O20: - | Q20: BIOMASS PELLET 06MM | R20: =IFERROR(VLOOKUP(Q20,'PRODUCT TABLE'!$A$2:$B$26,2,FALSE),"-") -> 44011090 | S20: 2000 | T20: 10.3 | U20: KG | V20: =S20*T20 -> 20600 | W20: 0.025 | X20: 0.025 | Y20: 0 | Z20: =IF(((ROUNDUP((AG20+V20),0))-(AG20+V20))>0.49,ROUNDdown((AG20+V20),0),ROUNDup((AG20+V20),0)) + AB20 -> 21630 | AA20: =Z20-(V20+AG20 + AB20) -> 0 | AC20: =V20 -> 20600 | AD20: =AC20*W20 -> 515 | AE20: =AC20*X20 -> 515 | AF20: =AC20*Y20 -> 0 | AG20: =SUM(AD20:AF20) -> 1030 | AH20: =IFERROR(MONTH(D20)," ") -> 12 | AI20: =YEAR(D20) -> 2021
A21: MAE003 | B21: =iferror(VLOOKUP((LEFT(A21,6)),CUSTOMER_DETAILS,2,FALSE),"-") -> SHREE GAYATRI PACKAGING | C21: - | D21: 44551 | E21: - | F21: - | G21: - | H21: - | I21: - | J21: =D21 -> 44551 | K21: 22 | L21: - | M21: TRUCK | N21: SELDOH NAGPUR | O21: - | Q21: BIOMASS PELLET 06MM | R21: =IFERROR(VLOOKUP(Q21,'PRODUCT TABLE'!$A$2:$B$26,2,FALSE),"-") -> 44011090 | S21: 1000 | T21: 10.5 | U21: KG | V21: =S21*T21 -> 10500 | W21: 0.025 | X21: 0.025 | Y21: 0 | Z21: =IF(((ROUNDUP((AG21+V21),0))-(AG21+V21))>0.49,ROUNDdown((AG21+V21),0),ROUNDup((AG21+V21),0)) + AB21 -> 11025 | AA21: =Z21-(V21+AG21 + AB21) -> 0 | AC21: =V21 -> 10500 | AD21: =AC21*W21 -> 262.5 | AE21: =AC21*X21 -> 262.5 | AF21: =AC21*Y21 -> 0 | AG21: =SUM(AD21:AF21) -> 525 | AH21: =IFERROR(MONTH(D21)," ") -> 12 | AI21: =YEAR(D21) -> 2021
A22: MAE010 | B22: =iferror(VLOOKUP((LEFT(A22,6)),CUSTOMER_DETAILS,2,FALSE),"-") -> KRISHNA ENTERPRISES | C22: - | D22: 44563 | E22: - | F22: - | G22: - | H22: - | I22: - | J22: =D22 -> 44563 | K22: 23 | L22: - | M22: TRUCK | N22: NAGPUR | O22: - | Q22: BIOMASS PELLET 06MM | R22: =IFERROR(VLOOKUP(Q22,'PRODUCT TABLE'!$A$2:$B$26,2,FALSE),"-") -> 44011090 | S22: 2100 | T22: 10.5 | U22: KG | V22: =S22*T22 -> 22050 | W22: 0.025 | X22: 0.025 | Y22: 0 | Z22: =IF(((ROUNDUP((AG22+V22),0))-(AG22+V22))>0.49,ROUNDdown((AG22+V22),0),ROUNDup((AG22+V22),0)) + AB22 -> 23152 | AA22: =Z22-(V22+AG22 + AB22) -> -0.5 | AC22: =V22 -> 22050 | AD22: =AC22*W22 -> 551.25 | AE22: =AC22*X22 -> 551.25 | AF22: =AC22*Y22 -> 0 | AG22: =SUM(AD22:AF22) -> 1102.5 | AH22: =IFERROR(MONTH(D22)," ") -> 1 | AI22: =YEAR(D22) -> 2022
A23: MAE010 | B23: =iferror(VLOOKUP((LEFT(A23,6)),CUSTOMER_DETAILS,2,FALSE),"-") -> KRISHNA ENTERPRISES | C23: - | D23: 44563 | E23: - | F23: - | G23: - | H23: - | I23: - | J23: =D23 -> 44563 | K23: 24 | L23: - | M23: TRUCK | N23: NAGPUR | O23: - | Q23: BIOMASS PELLET 06MM | R23: =IFERROR(VLOOKUP(Q23,'PRODUCT TABLE'!$A$2:$B$26,2,FALSE),"-") -> 44011090 | S23: 5550 | T23: 7.3 | U23: KG | V23: =S23*T23 -> 40515 | W23: 0.025 | X23: 0.025 | Y23: 0 | Z23: =IF(((ROUNDUP((AG23+V23),0))-(AG23+V23))>0.49,ROUNDdown((AG23+V23),0),ROUNDup((AG23+V23),0)) + AB23 -> 42541 | AA23: =Z23-(V23+AG23 + AB23) -> 0.25 | AC23: =V23 -> 40515 | AD23: =AC23*W23 -> 1012.875 | AE23: =AC23*X23 -> 1012.875 | AF23: =AC23*Y23 -> 0 | AG23: =SUM(AD23:AF23) -> 2025.75 | AH23: =IFERROR(MONTH(D23)," ") -> 1 | AI23: =YEAR(D23) -> 2022
A24: MAE | B24: PAVITRA FABRIC TAPE INDUSTRIES | C24: - | D24: 44570 | E24: - | F24: - | G24: - | H24: - | I24: - | J24: =D24 -> 44570 | K24: 25 | L24: - | M24: TRUCK | N24: HINGNA NAGPUR | O24: - | Q24: BIOMASS PELLET 06MM | R24: =IFERROR(VLOOKUP(Q24,'PRODUCT TABLE'!$A$2:$B$26,2,FALSE),"-") -> 44011090 | S24: 210 | T24: 11.5 | U24: KG | V24: =S24*T24 -> 2415 | W24: 0.025 | X24: 0.025 | Y24: 0 | Z24: =IF(((ROUNDUP((AG24+V24),0))-(AG24+V24))>0.49,ROUNDdown((AG24+V24),0),ROUNDup((AG24+V24),0)) + AB24 -> 2536 | AA24: =Z24-(V24+AG24 + AB24) -> 0.25 | AC24: =V24 -> 2415 | AD24: =AC24*W24 -> 60.375 | AE24: =AC24*X24 -> 60.375 | AF24: =AC24*Y24 -> 0 | AG24: =SUM(AD24:AF24) -> 120.75 | AH24: =IFERROR(MONTH(D24)," ") -> 1 | AI24: =YEAR(D24) -> 2022
A25: MAE | B25: PAVITRA FABRIC TAPE INDUSTRIES | C25: - | D25: 44577 | E25: - | F25: - | G25: - | H25: - | I25: - | J25: =D25 -> 44577 | K25: 26 | L25: - | M25: TRUCK | N25: HINGNA NAGPUR | O25: - | Q25: BIOMASS PELLET 06MM | R25: =IFERROR(VLOOKUP(Q25,'PRODUCT TABLE'!$A$2:$B$26,2,FALSE),"-") -> 44011090 | S25: 1020 | T25: 11 | U25: KG | V25: =S25*T25 -> 11220 | W25: 0.025 | X25: 0.025 | Y25: 0 | Z25: =IF(((ROUNDUP((AG25+V25),0))-(AG25+V25))>0.49,ROUNDdown((AG25+V25),0),ROUNDup((AG25+V25),0)) + AB25 -> 11781 | AA25: =Z25-(V25+AG25 + AB25) -> 0 | AC25: =V25 -> 11220 | AD25: =AC25*W25 -> 280.5 | AE25: =AC25*X25 -> 280.5 | AF25: =AC25*Y25 -> 0 | AG25: =SUM(AD25:AF25) -> 561 | AH25: =IFERROR(MONTH(D25)," ") -> 1 | AI25: =YEAR(D25) -> 2022
A26: MAE | B26: PAVITRA FABRIC TAPE INDUSTRIES | C26: - | D26: 44592 | E26: - | F26: - | G26: - | H26: - | I26: - | J26: =D26 -> 44592 | K26: 27 | L26: - | M26: TRUCK | N26: HINGNA NAGPUR | O26: - | Q26: BIOMASS PELLET 06MM | R26: =IFERROR(VLOOKUP(Q26,'PRODUCT TABLE'!$A$2:$B$26,2,FALSE),"-") -> 44011090 | S26: 1020 | T26: 11 | U26: KG | V26: =S26*T26 -> 11220 | W26: 0.025 | X26: 0.025 | Y26: 0 | Z26: =IF(((ROUNDUP((AG26+V26),0))-(AG26+V26))>0.49,ROUNDdown((AG26+V26),0),ROUNDup((AG26+V26),0)) + AB26 -> 11781 | AA26: =Z26-(V26+AG26 + AB26) -> 0 | AC26: =V26 -> 11220 | AD26: =AC26*W26 -> 280.5 | AE26: =AC26*X26 -> 280.5 | AF26: =AC26*Y26 -> 0 | AG26: =SUM(AD26:AF26) -> 561 | AH26: =IFERROR(MONTH(D26)," ") -> 1 | AI26: =YEAR(D26) -> 2022
A27: MAE | B27: PAVITRA FABRIC TAPE INDUSTRIES | C27: - | D27: 44602 | E27: - | F27: - | G27: - | H27: - | I27: - | J27: =D27 -> 44602 | K27: 28 | L27: - | M27: TRUCK | N27: HINGNA NAGPUR | O27: - | Q27: BIOMASS PELLET 06MM | R27: =IFERROR(VLOOKUP(Q27,'PRODUCT TABLE'!$A$2:$B$26,2,FALSE),"-") -> 44011090 | S27: 1020 | T27: 11 | U27: KG | V27: =S27*T27 -> 11220 | W27: 0.025 | X27: 0.025 | Y27: 0 | Z27: =IF(((ROUNDUP((AG27+V27),0))-(AG27+V27))>0.49,ROUNDdown((AG27+V27),0),ROUNDup((AG27+V27),0)) + AB27 -> 11781 | AA27: =Z27-(V27+AG27 + AB27) -> 0 | AC27: =V27 -> 11220 | AD27: =AC27*W27 -> 280.5 | AE27: =AC27*X27 -> 280.5 | AF27: =AC27*Y27 -> 0 | AG27: =SUM(AD27:AF27) -> 561 | AH27: =IFERROR(MONTH(D27)," ") -> 2 | AI27: =YEAR(D27) -> 2022
A28: MAE003 | B28: =iferror(VLOOKUP((LEFT(A28,6)),CUSTOMER_DETAILS,2,FALSE),"-") -> SHREE GAYATRI PACKAGING | C28: - | D28: 44610 | E28: - | F28: - | G28: - | H28: - | I28: - | J28: =D28 -> 44610 | K28: 29 | L28: - | M28: TRUCK | N28: SELDOH NAGPUR | O28: - | Q28: BIOMASS PELLET 06MM | R28: =IFERROR(VLOOKUP(Q28,'PRODUCT TABLE'!$A$2:$B$26,2,FALSE),"-") -> 44011090 | S28: 2100 | T28: 10.5 | U28: KG | V28: =S28*T28 -> 22050 | W28: 0.025 | X28: 0.025 | Y28: 0 | Z28: =IF(((ROUNDUP((AG28+V28),0))-(AG28+V28))>0.49,ROUNDdown((AG28+V28),0),ROUNDup((AG28+V28),0)) + AB28 -> 23152 | AA28: =Z28-(V28+AG28 + AB28) -> -0.5 | AC28: =V28 -> 22050 | AD28: =AC28*W28 -> 551.25 | AE28: =AC28*X28 -> 551.25 | AF28: =AC28*Y28 -> 0 | AG28: =SUM(AD28:AF28) -> 1102.5 | AH28: =IFERROR(MONTH(D28)," ") -> 2 | AI28: =YEAR(D28) -> 2022
A29: MAE | B29: PAVITRA FABRIC TAPE INDUSTRIES | C29: - | D29: 44612 | E29: - | F29: - | G29: - | H29: - | I29: - | J29: =D29 -> 44612 | K29: 30 | L29: - | M29: TRUCK | N29: HINGNA NAGPUR | O29: - | Q29: BIOMASS PELLET 06MM | R29: =IFERROR(VLOOKUP(Q29,'PRODUCT TABLE'!$A$2:$B$26,2,FALSE),"-") -> 44011090 | S29: 1020 | T29: 11 | U29: KG | V29: =S29*T29 -> 11220 | W29: 0.025 | X29: 0.025 | Y29: 0 | Z29: =IF(((ROUNDUP((AG29+V29),0))-(AG29+V29))>0.49,ROUNDdown((AG29+V29),0),ROUNDup((AG29+V29),0)) + AB29 -> 11781 | AA29: =Z29-(V29+AG29 + AB29) -> 0 | AC29: =V29 -> 11220 | AD29: =AC29*W29 -> 280.5 | AE29: =AC29*X29 -> 280.5 | AF29: =AC29*Y29 -> 0 | AG29: =SUM(AD29:AF29) -> 561 | AH29: =IFERROR(MONTH(D29)," ") -> 2 | AI29: =YEAR(D29) -> 2022
A30: MAE007 | B30: =iferror(VLOOKUP((LEFT(A30,6)),CUSTOMER_DETAILS,2,FALSE),"-") -> KABRA FOODS | C30: - | D30: 44616 | E30: - | F30: - | G30: - | H30: - | I30: - | J30: =D30 -> 44616 | K30: 31 | L30: - | M30: TRUCK | N30: JALGAO MH | O30: - | Q30: BIOMASS PELLET 06MM | R30: =IFERROR(VLOOKUP(Q30,'PRODUCT TABLE'!$A$2:$B$26,2,FALSE),"-") -> 44011090 | S30: 300 | T30: 10.8 | U30: KG | V30: =S30*T30 -> 3240 | W30: 0.025 | X30: 0.025 | Y30: 0 | Z30: =IF(((ROUNDUP((AG30+V30),0))-(AG30+V30))>0.49,ROUNDdown((AG30+V30),0),ROUNDup((AG30+V30),0)) + AB30 -> 3402 | AA30: =Z30-(V30+AG30 + AB30) -> 0 | AC30: =V30 -> 3240 | AD30: =AC30*W30 -> 81 | AE30: =AC30*X30 -> 81 | AF30: =AC30*Y30 -> 0 | AG30: =SUM(AD30:AF30) -> 162 | AH30: =IFERROR(MONTH(D30)," ") -> 2 | AI30: =YEAR(D30) -> 2022
A31: MAE010 | B31: =iferror(VLOOKUP((LEFT(A31,6)),CUSTOMER_DETAILS,2,FALSE),"-") -> KRISHNA ENTERPRISES | C31: - | D31: 44617 | E31: - | F31: - | G31: - | H31: - | I31: - | J31: =D31 -> 44617 | K31: 32 | L31: - | M31: TRUCK | N31: NAGPUR | O31: - | Q31: BIOMASS PELLET 06MM | R31: =IFERROR(VLOOKUP(Q31,'PRODUCT TABLE'!$A$2:$B$26,2,FALSE),"-") -> 44011090 | S31: 5100 | T31: 10.5 | U31: KG | V31: =S31*T31 -> 53550 | W31: 0.025 | X31: 0.025 | Y31: 0 | Z31: =IF(((ROUNDUP((AG31+V31),0))-(AG31+V31))>0.49,ROUNDdown((AG31+V31),0),ROUNDup((AG31+V31),0)) + AB31 -> 56227 | AA31: =Z31-(V31+AG31 + AB31) -> -0.5 | AC31: =V31 -> 53550 | AD31: =AC31*W31 -> 1338.75 | AE31: =AC31*X31 -> 1338.75 | AF31: =AC31*Y31 -> 0 | AG31: =SUM(AD31:AF31) -> 2677.5 | AH31: =IFERROR(MONTH(D31)," ") -> 2 | AI31: =YEAR(D31) -> 2022
A32: MAE | B32: PRABHAT ENTERPRISES | C32: - | D32: 44631 | E32: - | F32: - | G32: - | H32: - | I32: - | J32: =D32 -> 44631 | K32: 34 | L32: - | M32: TRUCK | N32: BHAYANDER MH | O32: - | Q32: BIOMASS PELLET 06MM | R32: =IFERROR(VLOOKUP(Q32,'PRODUCT TABLE'!$A$2:$B$26,2,FALSE),"-") -> 44011090 | S32: 300 | T32: 6 | U32: KG | V32: =S32*T32 -> 1800 | W32: 0.025 | X32: 0.025 | Y32: 0 | Z32: =IF(((ROUNDUP((AG32+V32),0))-(AG32+V32))>0.49,ROUNDdown((AG32+V32),0),ROUNDup((AG32+V32),0)) + AB32 -> 1890 | AA32: =Z32-(V32+AG32 + AB32) -> 0 | AC32: =V32 -> 1800 | AD32: =AC32*W32 -> 45 | AE32: =AC32*X32 -> 45 | AF32: =AC32*Y32 -> 0 | AG32: =SUM(AD32:AF32) -> 90 | AH32: =IFERROR(MONTH(D32)," ") -> 3 | AI32: =YEAR(D32) -> 2022
A33: MAE003 | B33: =iferror(VLOOKUP((LEFT(A33,6)),CUSTOMER_DETAILS,2,FALSE),"-") -> SHREE GAYATRI PACKAGING | C33: - | D33: 44642 | E33: - | F33: - | G33: - | H33: - | I33: - | J33: =D33 -> 44642 | K33: 35 | L33: - | M33: TRUCK | N33: SELDOH NAGPUR | O33: - | Q33: BIOMASS PELLET 06MM | R33: =IFERROR(VLOOKUP(Q33,'PRODUCT TABLE'!$A$2:$B$26,2,FALSE),"-") -> 44011090 | S33: 1020 | T33: 12 | U33: KG | V33: =S33*T33 -> 12240 | W33: 0.025 | X33: 0.025 | Y33: 0 | Z33: =IF(((ROUNDUP((AG33+V33),0))-(AG33+V33))>0.49,ROUNDdown((AG33+V33),0),ROUNDup((AG33+V33),0)) + AB33 -> 12852 | AA33: =Z33-(V33+AG33 + AB33) -> 0 | AC33: =V33 -> 12240 | AD33: =AC33*W33 -> 306 | AE33: =AC33*X33 -> 306 | AF33: =AC33*Y33 -> 0 | AG33: =SUM(AD33:AF33) -> 612 | AH33: =IFERROR(MONTH(D33)," ") -> 3 | AI33: =YEAR(D33) -> 2022
A34: MAE010 | B34: =iferror(VLOOKUP((LEFT(A34,6)),CUSTOMER_DETAILS,2,FALSE),"-") -> KRISHNA ENTERPRISES | C34: - | D34: 44644 | E34: - | F34: - | G34: - | H34: - | I34: - | J34: =D34 -> 44644 | K34: 36 | L34: - | M34: TRUCK | N34: NAGPUR | O34: - | Q34: BIOMASS PELLET 06MM | R34: =IFERROR(VLOOKUP(Q34,'PRODUCT TABLE'!$A$2:$B$26,2,FALSE),"-") -> 44011090 | S34: 7020 | T34: 10.9 | U34: KG | V34: =S34*T34 -> 76518 | W34: 0.025 | X34: 0.025 | Y34: 0 | Z34: =IF(((ROUNDUP((AG34+V34),0))-(AG34+V34))>0.49,ROUNDdown((AG34+V34),0),ROUNDup((AG34+V34),0)) + AB34 -> 80344 | AA34: =Z34-(V34+AG34 + AB34) -> 0.1 | AC34: =V34 -> 76518 | AD34: =AC34*W34 -> 1912.95 | AE34: =AC34*X34 -> 1912.95 | AF34: =AC34*Y34 -> 0 | AG34: =SUM(AD34:AF34) -> 3825.9 | AH34: =IFERROR(MONTH(D34)," ") -> 3 | AI34: =YEAR(D34) -> 2022
A35: MAE010 | B35: =iferror(VLOOKUP((LEFT(A35,6)),CUSTOMER_DETAILS,2,FALSE),"-") -> KRISHNA ENTERPRISES | C35: - | D35: 44649 | E35: - | F35: - | G35: - | H35: - | I35: - | J35: =D35 -> 44649 | K35: 37 | L35: - | M35: TRUCK | N35: NAGPUR | O35: - | Q35: BIOMASS PELLET 06MM | R35: =IFERROR(VLOOKUP(Q35,'PRODUCT TABLE'!$A$2:$B$26,2,FALSE),"-") -> 44011090 | S35: 4600 | T35: 11 | U35: KG | V35: =S35*T35 -> 50600 | W35: 0.025 | X35: 0.025 | Y35: 0 | Z35: =IF(((ROUNDUP((AG35+V35),0))-(AG35+V35))>0.49,ROUNDdown((AG35+V35),0),ROUNDup((AG35+V35),0)) + AB35 -> 53130 | AA35: =Z35-(V35+AG35 + AB35) -> 0 | AC35: =V35 -> 50600 | AD35: =AC35*W35 -> 1265 | AE35: =AC35*X35 -> 1265 | AF35: =AC35*Y35 -> 0 | AG35: =SUM(AD35:AF35) -> 2530 | AH35: =IFERROR(MONTH(D35)," ") -> 3 | AI35: =YEAR(D35) -> 2022
A36: MAE005/22-23/01 | B36: AEC PLAST | C36: - | D36: 44653 | E36: - | F36: - | G36: - | H36: - | I36: - | J36: =D36 -> 44653 | K36: 38 | L36: - | M36: TRUCK | N36: BUTIBORI MIDC | O36: - | Q36: BIOMASS BRIQUETTE 90MM | R36: =IFERROR(VLOOKUP(Q36,'PRODUCT TABLE'!$A$2:$B$26,2,FALSE),"-") -> 44011090 | S36: 10020 | T36: 5.7 | U36: KG | V36: =S36*T36 -> 57114 | W36: 0.025 | X36: 0.025 | Y36: 0 | Z36: =IF(((ROUNDUP((AG36+V36),0))-(AG36+V36))>0.49,ROUNDdown((AG36+V36),0),ROUNDup((AG36+V36),0)) + AB36 -> 59970 | AA36: =Z36-(V36+AG36 + AB36) -> 0.3 | AC36: =V36 -> 57114 | AD36: =AC36*W36 -> 1427.85 | AE36: =AC36*X36 -> 1427.85 | AF36: =AC36*Y36 -> 0 | AG36: =SUM(AD36:AF36) -> 2855.7 | AH36: =IFERROR(MONTH(D36)," ") -> 4 | AI36: =YEAR(D36) -> 2022
A37: MAE003/22-23/02 | B37: =iferror(VLOOKUP((LEFT(A37,6)),CUSTOMER_DETAILS,2,FALSE),"-") -> SHREE GAYATRI PACKAGING | C37: - | D37: 44661 | E37: - | F37: - | G37: - | H37: - | I37: - | J37: =D37 -> 44661 | K37: 39 | L37: - | M37: TRUCK | N37: SELDOH NAGPUR | O37: - | Q37: BIOMASS PELLET 06MM | R37: =IFERROR(VLOOKUP(Q37,'PRODUCT TABLE'!$A$2:$B$26,2,FALSE),"-") -> 44011090 | S37: 1500 | T37: 12 | U37: KG | V37: =S37*T37 -> 18000 | W37: 0.025 | X37: 0.025 | Y37: 0 | Z37: =IF(((ROUNDUP((AG37+V37),0))-(AG37+V37))>0.49,ROUNDdown((AG37+V37),0),ROUNDup((AG37+V37),0)) + AB37 -> 18900 | AA37: =Z37-(V37+AG37 + AB37) -> 0 | AC37: =V37 -> 18000 | AD37: =AC37*W37 -> 450 | AE37: =AC37*X37 -> 450 | AF37: =AC37*Y37 -> 0 | AG37: =SUM(AD37:AF37) -> 900 | AH37: =IFERROR(MONTH(D37)," ") -> 4 | AI37: =YEAR(D37) -> 2022
A38: MAE010/22-23/03 | B38: =iferror(VLOOKUP((LEFT(A38,6)),CUSTOMER_DETAILS,2,FALSE),"-") -> KRISHNA ENTERPRISES | C38: - | D38: 44667 | E38: - | F38: - | G38: - | H38: - | I38: - | J38: =D38 -> 44667 | K38: 40 | L38: - | M38: TRUCK | N38: NAGPUR | O38: - | Q38: BIOMASS PELLET 06MM | R38: =IFERROR(VLOOKUP(Q38,'PRODUCT TABLE'!$A$2:$B$26,2,FALSE),"-") -> 44011090 | S38: 7530 | T38: 11 | U38: KG | V38: =S38*T38 -> 82830 | W38: 0.025 | X38: 0.025 | Y38: 0 | Z38: =IF(((ROUNDUP((AG38+V38),0))-(AG38+V38))>0.49,ROUNDdown((AG38+V38),0),ROUNDup((AG38+V38),0)) + AB38 -> 86971 | AA38: =Z38-(V38+AG38 + AB38) -> -0.5 | AC38: =V38 -> 82830 | AD38: =AC38*W38 -> 2070.75 | AE38: =AC38*X38 -> 2070.75 | AF38: =AC38*Y38 -> 0 | AG38: =SUM(AD38:AF38) -> 4141.5 | AH38: =IFERROR(MONTH(D38)," ") -> 4 | AI38: =YEAR(D38) -> 2022
A39: MAE006/22-23/04 | B39: =iferror(VLOOKUP((LEFT(A39,6)),CUSTOMER_DETAILS,2,FALSE),"-") -> NAGPUR FUELS | C39: - | D39: 44682 | E39: - | F39: - | G39: - | H39: - | I39: - | J39: =D39 -> 44682 | K39: 41 | L39: - | M39: TRUCK | N39: NAGPUR | O39: - | Q39: BIOMASS PELLET 06MM | R39: =IFERROR(VLOOKUP(Q39,'PRODUCT TABLE'!$A$2:$B$26,2,FALSE),"-") -> 44011090 | S39: 7500 | T39: 6 | U39: KG | V39: =S39*T39 -> 45000 | W39: 0.025 | X39: 0.025 | Y39: 0 | Z39: =IF(((ROUNDUP((AG39+V39),0))-(AG39+V39))>0.49,ROUNDdown((AG39+V39),0),ROUNDup((AG39+V39),0)) + AB39 -> 47250 | AA39: =Z39-(V39+AG39 + AB39) -> 0 | AC39: =V39 -> 45000 | AD39: =AC39*W39 -> 1125 | AE39: =AC39*X39 -> 1125 | AF39: =AC39*Y39 -> 0 | AG39: =SUM(AD39:AF39) -> 2250 | AH39: =IFERROR(MONTH(D39)," ") -> 5 | AI39: =YEAR(D39) -> 2022
A40: MAE003/22-23/05 | B40: =iferror(VLOOKUP((LEFT(A40,6)),CUSTOMER_DETAILS,2,FALSE),"-") -> SHREE GAYATRI PACKAGING | C40: - | D40: 44688 | E40: - | F40: - | G40: - | H40: - | I40: - | J40: =D40 -> 44688 | K40: 43 | L40: - | M40: TRUCK | N40: SELDOH NAGPUR | O40: - | Q40: BIOMASS PELLET 06MM | R40: =IFERROR(VLOOKUP(Q40,'PRODUCT TABLE'!$A$2:$B$26,2,FALSE),"-") -> 44011090 | S40: 2010 | T40: 12 | U40: KG | V40: =S40*T40 -> 24120 | W40: 0.025 | X40: 0.025 | Y40: 0 | Z40: =IF(((ROUNDUP((AG40+V40),0))-(AG40+V40))>0.49,ROUNDdown((AG40+V40),0),ROUNDup((AG40+V40),0)) + AB40 -> 25326 | AA40: =Z40-(V40+AG40 + AB40) -> 0 | AC40: =V40 -> 24120 | AD40: =AC40*W40 -> 603 | AE40: =AC40*X40 -> 603 | AF40: =AC40*Y40 -> 0 | AG40: =SUM(AD40:AF40) -> 1206 | AH40: =IFERROR(MONTH(D40)," ") -> 5 | AI40: =YEAR(D40) -> 2022
A41: MAE030/22-23/06 | B41: CARE INDIA | C41: - | D41: 44690 | E41: - | F41: - | G41: - | H41: - | I41: - | J41: =D41 -> 44690 | K41: 44 | L41: - | M41: TRUCK | N41: GUJRAT | O41: - | Q41: BIOMASS PELLET 06MM | R41: =IFERROR(VLOOKUP(Q41,'PRODUCT TABLE'!$A$2:$B$26,2,FALSE),"-") -> 44011090 | S41: 210 | T41: 12 | U41: KG | V41: =S41*T41 -> 2520 | W41: 0.025 | X41: 0.025 | Y41: 0 | Z41: =IF(((ROUNDUP((AG41+V41),0))-(AG41+V41))>0.49,ROUNDdown((AG41+V41),0),ROUNDup((AG41+V41),0)) + AB41 -> 2646 | AA41: =Z41-(V41+AG41 + AB41) -> 0 | AC41: =V41 -> 2520 | AD41: =AC41*W41 -> 63 | AE41: =AC41*X41 -> 63 | AF41: =AC41*Y41 -> 0 | AG41: =SUM(AD41:AF41) -> 126 | AH41: =IFERROR(MONTH(D41)," ") -> 5 | AI41: =YEAR(D41) -> 2022
A42: MAE /22-23/07 | B42: SURYA SEGHDI | C42: - | D42: 44699 | E42: - | F42: - | G42: - | H42: - | I42: - | J42: =D42 -> 44699 | K42: 45 | L42: - | M42: TRUCK | N42: NASHIK | O42: - | Q42: BIOMASS PELLET 06MM | R42: =IFERROR(VLOOKUP(Q42,'PRODUCT TABLE'!$A$2:$B$26,2,FALSE),"-") -> 44011090 | S42: 90 | T42: 12 | U42: KG | V42: =S42*T42 -> 1080 | W42: 0.025 | X42: 0.025 | Y42: 0 | Z42: =IF(((ROUNDUP((AG42+V42),0))-(AG42+V42))>0.49,ROUNDdown((AG42+V42),0),ROUNDup((AG42+V42),0)) + AB42 -> 1134 | AA42: =Z42-(V42+AG42 + AB42) -> 0 | AC42: =V42 -> 1080 | AD42: =AC42*W42 -> 27 | AE42: =AC42*X42 -> 27 | AF42: =AC42*Y42 -> 0 | AG42: =SUM(AD42:AF42) -> 54 | AH42: =IFERROR(MONTH(D42)," ") -> 5 | AI42: =YEAR(D42) -> 2022
A43: MAE006/22-23/08 | B43: =iferror(VLOOKUP((LEFT(A43,6)),CUSTOMER_DETAILS,2,FALSE),"-") -> NAGPUR FUELS | C43: - | D43: 44694 | E43: - | F43: - | G43: - | H43: - | I43: - | J43: =D43 -> 44694 | K43: 46 | L43: - | M43: TRUCK | N43: NAGPUR | O43: - | Q43: BIOMASS PELLET 06MM | R43: =IFERROR(VLOOKUP(Q43,'PRODUCT TABLE'!$A$2:$B$26,2,FALSE),"-") -> 44011090 | S43: 10090 | T43: 6 | U43: KG | V43: =S43*T43 -> 60540 | W43: 0.025 | X43: 0.025 | Y43: 0 | Z43: =IF(((ROUNDUP((AG43+V43),0))-(AG43+V43))>0.49,ROUNDdown((AG43+V43),0),ROUNDup((AG43+V43),0)) + AB43 -> 63567 | AA43: =Z43-(V43+AG43 + AB43) -> 0 | AC43: =V43 -> 60540 | AD43: =AC43*W43 -> 1513.5 | AE43: =AC43*X43 -> 1513.5 | AF43: =AC43*Y43 -> 0 | AG43: =SUM(AD43:AF43) -> 3027 | AH43: =IFERROR(MONTH(D43)," ") -> 5 | AI43: =YEAR(D43) -> 2022
A44: MAE006/22-23/09 | B44: =iferror(VLOOKUP((LEFT(A44,6)),CUSTOMER_DETAILS,2,FALSE),"-") -> NAGPUR FUELS | C44: - | D44: 44702 | E44: - | F44: - | G44: - | H44: - | I44: - | J44: =D44 -> 44702 | K44: 47 | L44: - | M44: TRUCK | N44: NAGPUR | O44: - | Q44: BIOMASS PELLET 06MM | R44: =IFERROR(VLOOKUP(Q44,'PRODUCT TABLE'!$A$2:$B$26,2,FALSE),"-") -> 44011090 | S44: 12570 | T44: 6 | U44: KG | V44: =S44*T44 -> 75420 | W44: 0.025 | X44: 0.025 | Y44: 0 | Z44: =IF(((ROUNDUP((AG44+V44),0))-(AG44+V44))>0.49,ROUNDdown((AG44+V44),0),ROUNDup((AG44+V44),0)) + AB44 -> 79191 | AA44: =Z44-(V44+AG44 + AB44) -> 0 | AC44: =V44 -> 75420 | AD44: =AC44*W44 -> 1885.5 | AE44: =AC44*X44 -> 1885.5 | AF44: =AC44*Y44 -> 0 | AG44: =SUM(AD44:AF44) -> 3771 | AH44: =IFERROR(MONTH(D44)," ") -> 5 | AI44: =YEAR(D44) -> 2022
A45: MAE006/22-23/10 | B45: =iferror(VLOOKUP((LEFT(A45,6)),CUSTOMER_DETAILS,2,FALSE),"-") -> NAGPUR FUELS | C45: - | D45: 44588 | E45: - | F45: - | G45: - | H45: - | I45: - | J45: =D45 -> 44588 | K45: 48 | L45: - | M45: TRUCK | N45: NAGPUR | O45: - | Q45: BIOMASS PELLET 06MM | R45: =IFERROR(VLOOKUP(Q45,'PRODUCT TABLE'!$A$2:$B$26,2,FALSE),"-") -> 44011090 | S45: 7030 | T45: 7 | U45: KG | V45: =S45*T45 -> 49210 | W45: 0.025 | X45: 0.025 | Y45: 0 | Z45: =IF(((ROUNDUP((AG45+V45),0))-(AG45+V45))>0.49,ROUNDdown((AG45+V45),0),ROUNDup((AG45+V45),0)) + AB45 -> 51670 | AA45: =Z45-(V45+AG45 + AB45) -> -0.5 | AC45: =V45 -> 49210 | AD45: =AC45*W45 -> 1230.25 | AE45: =AC45*X45 -> 1230.25 | AF45: =AC45*Y45 -> 0 | AG45: =SUM(AD45:AF45) -> 2460.5 | AH45: =IFERROR(MONTH(D45)," ") -> 1 | AI45: =YEAR(D45) -> 2022
A46: MAE006/22-23/11 | B46: =iferror(VLOOKUP((LEFT(A46,6)),CUSTOMER_DETAILS,2,FALSE),"-") -> NAGPUR FUELS | C46: - | D46: 44589 | E46: - | F46: - | G46: - | H46: - | I46: - | J46: =D46 -> 44589 | K46: 49 | L46: - | M46: TRUCK | N46: NAGPUR | O46: - | Q46: BIOMASS PELLET 06MM | R46: =IFERROR(VLOOKUP(Q46,'PRODUCT TABLE'!$A$2:$B$26,2,FALSE),"-") -> 44011090 | S46: 10360 | T46: 7 | U46: KG | V46: =S46*T46 -> 72520 | W46: 0.025 | X46: 0.025 | Y46: 0 | Z46: =IF(((ROUNDUP((AG46+V46),0))-(AG46+V46))>0.49,ROUNDdown((AG46+V46),0),ROUNDup((AG46+V46),0)) + AB46 -> 76146 | AA46: =Z46-(V46+AG46 + AB46) -> 0 | AC46: =V46 -> 72520 | AD46: =AC46*W46 -> 1813 | AE46: =AC46*X46 -> 1813 | AF46: =AC46*Y46 -> 0 | AG46: =SUM(AD46:AF46) -> 3626 | AH46: =IFERROR(MONTH(D46)," ") -> 1 | AI46: =YEAR(D46) -> 2022
A47: MAE011/22-23/12 | B47: =iferror(VLOOKUP((LEFT(A47,6)),CUSTOMER_DETAILS,2,FALSE),"-") -> VIDARBHA SALES | C47: - | D47: 44709 | E47: - | F47: - | G47: - | H47: - | I47: - | J47: =D47 -> 44709 | K47: 50 | L47: - | M47: TRUCK | N47: HINGNA NAGPUR | O47: - | Q47: SAL SEED MEAL DOC | R47: =IFERROR(VLOOKUP(Q47,'PRODUCT TABLE'!$A$2:$B$26,2,FALSE),"-") -> 23069026 | S47: 1000 | T47: 10 | U47: KG | V47: =S47*T47 -> 10000 | W47: 0.025 | X47: 0.025 | Y47: 0 | Z47: =IF(((ROUNDUP((AG47+V47),0))-(AG47+V47))>0.49,ROUNDdown((AG47+V47),0),ROUNDup((AG47+V47),0)) + AB47 -> 10500 | AA47: =Z47-(V47+AG47 + AB47) -> 0 | AC47: =V47 -> 10000 | AD47: =AC47*W47 -> 250 | AE47: =AC47*X47 -> 250 | AF47: =AC47*Y47 -> 0 | AG47: =SUM(AD47:AF47) -> 500 | AH47: =IFERROR(MONTH(D47)," ") -> 5 | AI47: =YEAR(D47) -> 2022
A48: MAE006/22-23/13 | B48: =iferror(VLOOKUP((LEFT(A48,6)),CUSTOMER_DETAILS,2,FALSE),"-") -> NAGPUR FUELS | C48: - | D48: 44721 | E48: - | F48: - | G48: - | H48: - | I48: - | J48: =D48 -> 44721 | K48: 51 | L48: - | M48: TRUCK | N48: NAGPUR | O48: - | Q48: BIOMASS PELLET 06MM | R48: =IFERROR(VLOOKUP(Q48,'PRODUCT TABLE'!$A$2:$B$26,2,FALSE),"-") -> 44011090 | S48: 19750 | T48: 7 | U48: KG | V48: =S48*T48 -> 138250 | W48: 0.025 | X48: 0.025 | Y48: 0 | Z48: =IF(((ROUNDUP((AG48+V48),0))-(AG48+V48))>0.49,ROUNDdown((AG48+V48),0),ROUNDup((AG48+V48),0)) + AB48 -> 145162 | AA48: =Z48-(V48+AG48 + AB48) -> -0.5 | AC48: =V48 -> 138250 | AD48: =AC48*W48 -> 3456.25 | AE48: =AC48*X48 -> 3456.25 | AF48: =AC48*Y48 -> 0 | AG48: =SUM(AD48:AF48) -> 6912.5 | AH48: =IFERROR(MONTH(D48)," ") -> 6 | AI48: =YEAR(D48) -> 2022
A49: MAE003/22-23/14 | B49: =iferror(VLOOKUP((LEFT(A49,6)),CUSTOMER_DETAILS,2,FALSE),"-") -> SHREE GAYATRI PACKAGING | C49: - | D49: 44726 | E49: - | F49: - | G49: - | H49: - | I49: - | J49: =D49 -> 44726 | K49: 52 | L49: - | M49: TRUCK | N49: SELDOH NAGPUR | O49: - | Q49: BIOMASS PELLET 06MM | R49: =IFERROR(VLOOKUP(Q49,'PRODUCT TABLE'!$A$2:$B$26,2,FALSE),"-") -> 44011090 | S49: 2010 | T49: 12 | U49: KG | V49: =S49*T49 -> 24120 | W49: 0.025 | X49: 0.025 | Y49: 0 | Z49: =IF(((ROUNDUP((AG49+V49),0))-(AG49+V49))>0.49,ROUNDdown((AG49+V49),0),ROUNDup((AG49+V49),0)) + AB49 -> 25326 | AA49: =Z49-(V49+AG49 + AB49) -> 0 | AC49: =V49 -> 24120 | AD49: =AC49*W49 -> 603 | AE49: =AC49*X49 -> 603 | AF49: =AC49*Y49 -> 0 | AG49: =SUM(AD49:AF49) -> 1206 | AH49: =IFERROR(MONTH(D49)," ") -> 6 | AI49: =YEAR(D49) -> 2022
A50: MAE031/22-23/15 | B50: RSG AGRO & WASTE MANAGEMENT | C50: - | D50: 44726 | E50: - | F50: - | G50: - | H50: - | I50: - | J50: =D50 -> 44726 | K50: 55 | L50: - | M50: TRUCK | N50: BUTIBORI MIDC | O50: - | Q50: SAL SEED MEAL DOC | R50: =IFERROR(VLOOKUP(Q50,'PRODUCT TABLE'!$A$2:$B$26,2,FALSE),"-") -> 23069026 | S50: 3678 | T50: 10.15 | U50: KG | V50: =S50*T50 -> 37331.7 | W50: 0.025 | X50: 0.025 | Y50: 0 | Z50: =IF(((ROUNDUP((AG50+V50),0))-(AG50+V50))>0.49,ROUNDdown((AG50+V50),0),ROUNDup((AG50+V50),0)) + AB50 -> 39198 | AA50: =Z50-(V50+AG50 + AB50) -> -0.285 | AC50: =V50 -> 37331.7 | AD50: =AC50*W50 -> 933.2925 | AE50: =AC50*X50 -> 933.2925 | AF50: =AC50*Y50 -> 0 | AG50: =SUM(AD50:AF50) -> 1866.585 | AH50: =IFERROR(MONTH(D50)," ") -> 6 | AI50: =YEAR(D50) -> 2022
A51: MAE031/22-23/16 | B51: RSG AGRO & WASTE MANAGEMENT | C51: - | D51: 44728 | E51: - | F51: - | G51: - | H51: - | I51: - | J51: =D51 -> 44728 | K51: 56 | L51: - | M51: TRUCK | N51: BUTIBORI MIDC | O51: - | Q51: SAL SEED MEAL DOC | R51: =IFERROR(VLOOKUP(Q51,'PRODUCT TABLE'!$A$2:$B$26,2,FALSE),"-") -> 23069026 | S51: 4760 | T51: 10.5 | U51: KG | V51: =S51*T51 -> 49980 | W51: 0.025 | X51: 0.025 | Y51: 0 | Z51: =IF(((ROUNDUP((AG51+V51),0))-(AG51+V51))>0.49,ROUNDdown((AG51+V51),0),ROUNDup((AG51+V51),0)) + AB51 -> 52479 | AA51: =Z51-(V51+AG51 + AB51) -> 0 | AC51: =V51 -> 49980 | AD51: =AC51*W51 -> 1249.5 | AE51: =AC51*X51 -> 1249.5 | AF51: =AC51*Y51 -> 0 | AG51: =SUM(AD51:AF51) -> 2499 | AH51: =IFERROR(MONTH(D51)," ") -> 6 | AI51: =YEAR(D51) -> 2022
A52: MAE010/22-23/17 | B52: =iferror(VLOOKUP((LEFT(A52,6)),CUSTOMER_DETAILS,2,FALSE),"-") -> KRISHNA ENTERPRISES | C52: - | D52: 44730 | E52: - | F52: - | G52: - | H52: - | I52: - | J52: =D52 -> 44730 | K52: 57 | L52: - | M52: TRUCK | N52: NAGPUR | O52: - | Q52: BIOMASS PELLET 06MM | R52: =IFERROR(VLOOKUP(Q52,'PRODUCT TABLE'!$A$2:$B$26,2,FALSE),"-") -> 44011090 | S52: 8300 | T52: 7 | U52: KG | V52: =S52*T52 -> 58100 | W52: 0.025 | X52: 0.025 | Y52: 0 | Z52: =IF(((ROUNDUP((AG52+V52),0))-(AG52+V52))>0.49,ROUNDdown((AG52+V52),0),ROUNDup((AG52+V52),0)) + AB52 -> 61005 | AA52: =Z52-(V52+AG52 + AB52) -> 0 | AC52: =V52 -> 58100 | AD52: =AC52*W52 -> 1452.5 | AE52: =AC52*X52 -> 1452.5 | AF52: =AC52*Y52 -> 0 | AG52: =SUM(AD52:AF52) -> 2905 | AH52: =IFERROR(MONTH(D52)," ") -> 6 | AI52: =YEAR(D52) -> 2022
A53: MAE010/22-23/18 | B53: =iferror(VLOOKUP((LEFT(A53,6)),CUSTOMER_DETAILS,2,FALSE),"-") -> KRISHNA ENTERPRISES | C53: - | D53: 44736 | E53: - | F53: - | G53: - | H53: - | I53: - | J53: =D53 -> 44736 | K53: 58 | L53: - | M53: TRUCK | N53: NAGPUR | O53: - | Q53: BIOMASS PELLET 06MM | R53: =IFERROR(VLOOKUP(Q53,'PRODUCT TABLE'!$A$2:$B$26,2,FALSE),"-") -> 44011090 | S53: 18040 | T53: 7 | U53: KG | V53: =S53*T53 -> 126280 | W53: 0.025 | X53: 0.025 | Y53: 0 | Z53: =IF(((ROUNDUP((AG53+V53),0))-(AG53+V53))>0.49,ROUNDdown((AG53+V53),0),ROUNDup((AG53+V53),0)) + AB53 -> 132594 | AA53: =Z53-(V53+AG53 + AB53) -> 0 | AC53: =V53 -> 126280 | AD53: =AC53*W53 -> 3157 | AE53: =AC53*X53 -> 3157 | AF53: =AC53*Y53 -> 0 | AG53: =SUM(AD53:AF53) -> 6314 | AH53: =IFERROR(MONTH(D53)," ") -> 6 | AI53: =YEAR(D53) -> 2022
A54: MAE031/22-23/19 | B54: RSG AGRO & WASTE MANAGEMENT | C54: - | D54: 44754 | E54: - | F54: - | G54: - | H54: - | I54: - | J54: =D54 -> 44754 | K54: 59 | L54: - | M54: TRUCK | N54: BUTIBORI MIDC | O54: - | Q54: SAL SEED MEAL DOC | R54: =IFERROR(VLOOKUP(Q54,'PRODUCT TABLE'!$A$2:$B$26,2,FALSE),"-") -> 23069026 | S54: 7070 | T54: 10.95 | U54: KG | V54: =S54*T54 -> 77416.5 | W54: 0.025 | X54: 0.025 | Y54: 0 | Z54: =IF(((ROUNDUP((AG54+V54),0))-(AG54+V54))>0.49,ROUNDdown((AG54+V54),0),ROUNDup((AG54+V54),0)) + AB54 -> 81287 | AA54: =Z54-(V54+AG54 + AB54) -> -0.325 | AC54: =V54 -> 77416.5 | AD54: =AC54*W54 -> 1935.4125 | AE54: =AC54*X54 -> 1935.4125 | AF54: =AC54*Y54 -> 0 | AG54: =SUM(AD54:AF54) -> 3870.825 | AH54: =IFERROR(MONTH(D54)," ") -> 7 | AI54: =YEAR(D54) -> 2022
A55: MAE010/22-23/20 | B55: =iferror(VLOOKUP((LEFT(A55,6)),CUSTOMER_DETAILS,2,FALSE),"-") -> KRISHNA ENTERPRISES | C55: - | D55: 44757 | E55: - | F55: - | G55: - | H55: - | I55: - | J55: =D55 -> 44757 | K55: 60 | L55: - | M55: TRUCK | N55: NAGPUR | O55: - | Q55: BIOMASS PELLET 06MM | R55: =IFERROR(VLOOKUP(Q55,'PRODUCT TABLE'!$A$2:$B$26,2,FALSE),"-") -> 44011090 | S55: 9540 | T55: 7 | U55: KG | V55: =S55*T55 -> 66780 | W55: 0.025 | X55: 0.025 | Y55: 0 | Z55: =IF(((ROUNDUP((AG55+V55),0))-(AG55+V55))>0.49,ROUNDdown((AG55+V55),0),ROUNDup((AG55+V55),0)) + AB55 -> 70119 | AA55: =Z55-(V55+AG55 + AB55) -> 0 | AC55: =V55 -> 66780 | AD55: =AC55*W55 -> 1669.5 | AE55: =AC55*X55 -> 1669.5 | AF55: =AC55*Y55 -> 0 | AG55: =SUM(AD55:AF55) -> 3339 | AH55: =IFERROR(MONTH(D55)," ") -> 7 | AI55: =YEAR(D55) -> 2022
A56: MAE006/22-23/21 | B56: =iferror(VLOOKUP((LEFT(A56,6)),CUSTOMER_DETAILS,2,FALSE),"-") -> NAGPUR FUELS | C56: - | D56: 44759 | E56: - | F56: - | G56: - | H56: - | I56: - | J56: =D56 -> 44759 | K56: 61 | L56: - | M56: TRUCK | N56: NAGPUR | O56: - | Q56: BIOMASS PELLET 06MM | R56: =IFERROR(VLOOKUP(Q56,'PRODUCT TABLE'!$A$2:$B$26,2,FALSE),"-") -> 44011090 | S56: 10890 | T56: 8.5 | U56: KG | V56: =S56*T56 -> 92565 | W56: 0.025 | X56: 0.025 | Y56: 0 | Z56: =IF(((ROUNDUP((AG56+V56),0))-(AG56+V56))>0.49,ROUNDdown((AG56+V56),0),ROUNDup((AG56+V56),0)) + AB56 -> 97193 | AA56: =Z56-(V56+AG56 + AB56) -> -0.25 | AC56: =V56 -> 92565 | AD56: =AC56*W56 -> 2314.125 | AE56: =AC56*X56 -> 2314.125 | AF56: =AC56*Y56 -> 0 | AG56: =SUM(AD56:AF56) -> 4628.25 | AH56: =IFERROR(MONTH(D56)," ") -> 7 | AI56: =YEAR(D56) -> 2022
A57: MAE032/22-23/22 | B57: MPM PVT LTD | C57: - | D57: 44760 | E57: - | F57: - | G57: - | H57: - | I57: - | J57: =D57 -> 44760 | K57: 62 | L57: - | M57: TRUCK | N57: BUTIBORI MIDC | O57: - | Q57: SAL SEED MEAL DOC | R57: =IFERROR(VLOOKUP(Q57,'PRODUCT TABLE'!$A$2:$B$26,2,FALSE),"-") -> 23069026 | S57: 980 | T57: 12.5 | U57: KG | V57: =S57*T57 -> 12250 | W57: 0.025 | X57: 0.025 | Y57: 0 | Z57: =IF(((ROUNDUP((AG57+V57),0))-(AG57+V57))>0.49,ROUNDdown((AG57+V57),0),ROUNDup((AG57+V57),0)) + AB57 -> 12862 | AA57: =Z57-(V57+AG57 + AB57) -> -0.5 | AC57: =V57 -> 12250 | AD57: =AC57*W57 -> 306.25 | AE57: =AC57*X57 -> 306.25 | AF57: =AC57*Y57 -> 0 | AG57: =SUM(AD57:AF57) -> 612.5 | AH57: =IFERROR(MONTH(D57)," ") -> 7 | AI57: =YEAR(D57) -> 2022
A58: MAE033/22-23/23 | B58: SHAKTI INDUSTRIES | C58: - | D58: 44758 | E58: - | F58: - | G58: - | H58: - | I58: - | J58: =D58 -> 44758 | K58: 63 | L58: - | M58: TRUCK | N58: BUTIBORI MIDC | O58: - | Q58: BIOMASS BRIQUETTE 90MM | R58: =IFERROR(VLOOKUP(Q58,'PRODUCT TABLE'!$A$2:$B$26,2,FALSE),"-") -> 44011090 | S58: 10350 | T58: 6.2 | U58: KG | V58: =S58*T58 -> 64170 | W58: 0.025 | X58: 0.025 | Y58: 0 | Z58: =IF(((ROUNDUP((AG58+V58),0))-(AG58+V58))>0.49,ROUNDdown((AG58+V58),0),ROUNDup((AG58+V58),0)) + AB58 -> 67378 | AA58: =Z58-(V58+AG58 + AB58) -> -0.5 | AC58: =V58 -> 64170 | AD58: =AC58*W58 -> 1604.25 | AE58: =AC58*X58 -> 1604.25 | AF58: =AC58*Y58 -> 0 | AG58: =SUM(AD58:AF58) -> 3208.5 | AH58: =IFERROR(MONTH(D58)," ") -> 7 | AI58: =YEAR(D58) -> 2022
A59: MAE003/22-23/24 | B59: =iferror(VLOOKUP((LEFT(A59,6)),CUSTOMER_DETAILS,2,FALSE),"-") -> SHREE GAYATRI PACKAGING | C59: - | D59: 44764 | E59: - | F59: - | G59: - | H59: - | I59: - | J59: =D59 -> 44764 | K59: 64 | L59: - | M59: TRUCK | N59: SELDOH NAGPUR | O59: - | Q59: BIOMASS PELLET 06MM | R59: =IFERROR(VLOOKUP(Q59,'PRODUCT TABLE'!$A$2:$B$26,2,FALSE),"-") -> 44011090 | S59: 2220 | T59: 12 | U59: KG | V59: =S59*T59 -> 26640 | W59: 0.025 | X59: 0.025 | Y59: 0 | Z59: =IF(((ROUNDUP((AG59+V59),0))-(AG59+V59))>0.49,ROUNDdown((AG59+V59),0),ROUNDup((AG59+V59),0)) + AB59 -> 27972 | AA59: =Z59-(V59+AG59 + AB59) -> 0 | AC59: =V59 -> 26640 | AD59: =AC59*W59 -> 666 | AE59: =AC59*X59 -> 666 | AF59: =AC59*Y59 -> 0 | AG59: =SUM(AD59:AF59) -> 1332 | AH59: =IFERROR(MONTH(D59)," ") -> 7 | AI59: =YEAR(D59) -> 2022
A60: MAE033/22-23/25 | B60: SHAKTI INDUSTRIES | C60: - | D60: 44761 | E60: - | F60: - | G60: - | H60: - | I60: - | J60: =D60 -> 44761 | K60: 65 | L60: - | M60: TRUCK | N60: BUTIBORI MIDC | O60: - | Q60: BIOMASS BRIQUETTE 90MM | R60: =IFERROR(VLOOKUP(Q60,'PRODUCT TABLE'!$A$2:$B$26,2,FALSE),"-") -> 44011090 | S60: 13000 | T60: 6.2 | U60: KG | V60: =S60*T60 -> 80600 | W60: 0.025 | X60: 0.025 | Y60: 0 | Z60: =IF(((ROUNDUP((AG60+V60),0))-(AG60+V60))>0.49,ROUNDdown((AG60+V60),0),ROUNDup((AG60+V60),0)) + AB60 -> 84630 | AA60: =Z60-(V60+AG60 + AB60) -> 0 | AC60: =V60 -> 80600 | AD60: =AC60*W60 -> 2015 | AE60: =AC60*X60 -> 2015 | AF60: =AC60*Y60 -> 0 | AG60: =SUM(AD60:AF60) -> 4030 | AH60: =IFERROR(MONTH(D60)," ") -> 7 | AI60: =YEAR(D60) -> 2022
A61: MAE006/22-23/26 | B61: =iferror(VLOOKUP((LEFT(A61,6)),CUSTOMER_DETAILS,2,FALSE),"-") -> NAGPUR FUELS | C61: - | D61: 44763 | E61: - | F61: - | G61: - | H61: - | I61: - | J61: =D61 -> 44763 | K61: 66 | L61: - | M61: TRUCK | N61: NAGPUR | O61: - | Q61: BIOMASS PELLET 06MM | R61: =IFERROR(VLOOKUP(Q61,'PRODUCT TABLE'!$A$2:$B$26,2,FALSE),"-") -> 44011090 | S61: 9200 | T61: 6 | U61: KG | V61: =S61*T61 -> 55200 | W61: 0.025 | X61: 0.025 | Y61: 0 | Z61: =IF(((ROUNDUP((AG61+V61),0))-(AG61+V61))>0.49,ROUNDdown((AG61+V61),0),ROUNDup((AG61+V61),0)) + AB61 -> 57960 | AA61: =Z61-(V61+AG61 + AB61) -> 0 | AC61: =V61 -> 55200 | AD61: =AC61*W61 -> 1380 | AE61: =AC61*X61 -> 1380 | AF61: =AC61*Y61 -> 0 | AG61: =SUM(AD61:AF61) -> 2760 | AH61: =IFERROR(MONTH(D61)," ") -> 7 | AI61: =YEAR(D61) -> 2022
A62: MAE/22-23/27 | B62: TUSHAR TALE | C62: - | D62: 44774 | E62: - | F62: - | G62: - | H62: - | I62: - | J62: =D62 -> 44774 | K62: 67 | L62: - | M62: TRUCK | N62: AMARAVATI | O62: - | Q62: SAL SEED MEAL DOC | R62: =IFERROR(VLOOKUP(Q62,'PRODUCT TABLE'!$A$2:$B$26,2,FALSE),"-") -> 23069026 | S62: 1000 | T62: 15 | U62: KG | V62: =S62*T62 -> 15000 | W62: 0.025 | X62: 0.025 | Y62: 0 | Z62: =IF(((ROUNDUP((AG62+V62),0))-(AG62+V62))>0.49,ROUNDdown((AG62+V62),0),ROUNDup((AG62+V62),0)) + AB62 -> 15750 | AA62: =Z62-(V62+AG62 + AB62) -> 0 | AC62: =V62 -> 15000 | AD62: =AC62*W62 -> 375 | AE62: =AC62*X62 -> 375 | AF62: =AC62*Y62 -> 0 | AG62: =SUM(AD62:AF62) -> 750 | AH62: =IFERROR(MONTH(D62)," ") -> 8 | AI62: =YEAR(D62) -> 2022
A63: MAE033/22-23/28 | B63: SHAKTI INDUSTRIES | C63: - | D63: 44769 | E63: - | F63: - | G63: - | H63: - | I63: - | J63: =D63 -> 44769 | K63: 68 | L63: - | M63: TRUCK | N63: BUTIBORI MIDC | O63: - | Q63: BIOMASS BRIQUETTE 90MM | R63: =IFERROR(VLOOKUP(Q63,'PRODUCT TABLE'!$A$2:$B$26,2,FALSE),"-") -> 44011090 | S63: 10510 | T63: 6.2 | U63: KG | V63: =S63*T63 -> 65162 | W63: 0.025 | X63: 0.025 | Y63: 0 | Z63: =IF(((ROUNDUP((AG63+V63),0))-(AG63+V63))>0.49,ROUNDdown((AG63+V63),0),ROUNDup((AG63+V63),0)) + AB63 -> 68420 | AA63: =Z63-(V63+AG63 + AB63) -> -0.1 | AC63: =V63 -> 65162 | AD63: =AC63*W63 -> 1629.05 | AE63: =AC63*X63 -> 1629.05 | AF63: =AC63*Y63 -> 0 | AG63: =SUM(AD63:AF63) -> 3258.1 | AH63: =IFERROR(MONTH(D63)," ") -> 7 | AI63: =YEAR(D63) -> 2022
A64: MAE006/22-23/29 | B64: =iferror(VLOOKUP((LEFT(A64,6)),CUSTOMER_DETAILS,2,FALSE),"-") -> NAGPUR FUELS | C64: - | D64: 44774 | E64: - | F64: - | G64: - | H64: - | I64: - | J64: =D64 -> 44774 | K64: 69 | L64: - | M64: TRUCK | N64: NAGPUR | O64: - | Q64: BIOMASS PELLET 06MM | R64: =IFERROR(VLOOKUP(Q64,'PRODUCT TABLE'!$A$2:$B$26,2,FALSE),"-") -> 44011090 | S64: 20590 | T64: 9 | U64: KG | V64: =S64*T64 -> 185310 | W64: 0.025 | X64: 0.025 | Y64: 0 | Z64: =IF(((ROUNDUP((AG64+V64),0))-(AG64+V64))>0.49,ROUNDdown((AG64+V64),0),ROUNDup((AG64+V64),0)) + AB64 -> 194575 | AA64: =Z64-(V64+AG64 + AB64) -> -0.5 | AC64: =V64 -> 185310 | AD64: =AC64*W64 -> 4632.75 | AE64: =AC64*X64 -> 4632.75 | AF64: =AC64*Y64 -> 0 | AG64: =SUM(AD64:AF64) -> 9265.5 | AH64: =IFERROR(MONTH(D64)," ") -> 8 | AI64: =YEAR(D64) -> 2022
A65: MAE012/22-23/30 | B65: =iferror(VLOOKUP((LEFT(A65,6)),CUSTOMER_DETAILS,2,FALSE),"-") -> SHRI SHIVAY AGRO ENERGIES | C65: - | D65: 44775 | E65: - | F65: - | G65: - | H65: - | I65: - | J65: =D65 -> 44775 | K65: 70 | L65: - | M65: TRUCK | N65: KATANGI MP | O65: - | Q65: SAL SEED MEAL DOC | R65: =IFERROR(VLOOKUP(Q65,'PRODUCT TABLE'!$A$2:$B$26,2,FALSE),"-") -> 23069026 | S65: 5090 | T65: 12 | U65: KG | V65: =S65*T65 -> 61080 | W65: 0.025 | X65: 0.025 | Y65: 0 | Z65: =IF(((ROUNDUP((AG65+V65),0))-(AG65+V65))>0.49,ROUNDdown((AG65+V65),0),ROUNDup((AG65+V65),0)) + AB65 -> 64134 | AA65: =Z65-(V65+AG65 + AB65) -> 0 | AC65: =V65 -> 61080 | AD65: =AC65*W65 -> 1527 | AE65: =AC65*X65 -> 1527 | AF65: =AC65*Y65 -> 0 | AG65: =SUM(AD65:AF65) -> 3054 | AH65: =IFERROR(MONTH(D65)," ") -> 8 | AI65: =YEAR(D65) -> 2022
A66: MAE006/22-23/31 | B66: =iferror(VLOOKUP((LEFT(A66,6)),CUSTOMER_DETAILS,2,FALSE),"-") -> NAGPUR FUELS | C66: - | D66: 44777 | E66: - | F66: - | G66: - | H66: - | I66: - | J66: =D66 -> 44777 | K66: 71 | L66: - | M66: TRUCK | N66: NAGPUR | O66: - | Q66: BIOMASS PELLET 06MM | R66: =IFERROR(VLOOKUP(Q66,'PRODUCT TABLE'!$A$2:$B$26,2,FALSE),"-") -> 44011090 | S66: 10020 | T66: 9 | U66: KG | V66: =S66*T66 -> 90180 | W66: 0.025 | X66: 0.025 | Y66: 0 | Z66: =IF(((ROUNDUP((AG66+V66),0))-(AG66+V66))>0.49,ROUNDdown((AG66+V66),0),ROUNDup((AG66+V66),0)) + AB66 -> 94689 | AA66: =Z66-(V66+AG66 + AB66) -> 0 | AC66: =V66 -> 90180 | AD66: =AC66*W66 -> 2254.5 | AE66: =AC66*X66 -> 2254.5 | AF66: =AC66*Y66 -> 0 | AG66: =SUM(AD66:AF66) -> 4509 | AH66: =IFERROR(MONTH(D66)," ") -> 8 | AI66: =YEAR(D66) -> 2022
A67: MAE031/22-23/32 | B67: RSG AGRO & WASTE MANAGEMENT | C67: - | D67: 44777 | E67: - | F67: - | G67: - | H67: - | I67: - | J67: =D67 -> 44777 | K67: 72 | L67: - | M67: TRUCK | N67: BUTIBORI MIDC | O67: - | Q67: SAL SEED MEAL DOC | R67: =IFERROR(VLOOKUP(Q67,'PRODUCT TABLE'!$A$2:$B$26,2,FALSE),"-") -> 23069026 | S67: 10280 | T67: 11.9 | U67: KG | V67: =S67*T67 -> 122332 | W67: 0.025 | X67: 0.025 | Y67: 0 | Z67: =IF(((ROUNDUP((AG67+V67),0))-(AG67+V67))>0.49,ROUNDdown((AG67+V67),0),ROUNDup((AG67+V67),0)) + AB67 -> 128449 | AA67: =Z67-(V67+AG67 + AB67) -> 0.4 | AC67: =V67 -> 122332 | AD67: =AC67*W67 -> 3058.3 | AE67: =AC67*X67 -> 3058.3 | AF67: =AC67*Y67 -> 0 | AG67: =SUM(AD67:AF67) -> 6116.6 | AH67: =IFERROR(MONTH(D67)," ") -> 8 | AI67: =YEAR(D67) -> 2022
A68: MAE006/22-23/33 | B68: =iferror(VLOOKUP((LEFT(A68,6)),CUSTOMER_DETAILS,2,FALSE),"-") -> NAGPUR FUELS | C68: - | D68: 44786 | E68: - | F68: - | G68: - | H68: - | I68: - | J68: =D68 -> 44786 | K68: 73 | L68: - | M68: TRUCK | N68: NAGPUR | O68: - | Q68: BIOMASS PELLET 06MM | R68: =IFERROR(VLOOKUP(Q68,'PRODUCT TABLE'!$A$2:$B$26,2,FALSE),"-") -> 44011090 | S68: 20470 | T68: 9.5 | U68: KG | V68: =S68*T68 -> 194465 | W68: 0.025 | X68: 0.025 | Y68: 0 | Z68: =IF(((ROUNDUP((AG68+V68),0))-(AG68+V68))>0.49,ROUNDdown((AG68+V68),0),ROUNDup((AG68+V68),0)) + AB68 -> 204188 | AA68: =Z68-(V68+AG68 + AB68) -> -0.25 | AC68: =V68 -> 194465 | AD68: =AC68*W68 -> 4861.625 | AE68: =AC68*X68 -> 4861.625 | AF68: =AC68*Y68 -> 0 | AG68: =SUM(AD68:AF68) -> 9723.25 | AH68: =IFERROR(MONTH(D68)," ") -> 8 | AI68: =YEAR(D68) -> 2022
A69: MAE003/22-23/34 | B69: =iferror(VLOOKUP((LEFT(A69,6)),CUSTOMER_DETAILS,2,FALSE),"-") -> SHREE GAYATRI PACKAGING | C69: - | D69: 44787 | E69: - | F69: - | G69: - | H69: - | I69: - | J69: =D69 -> 44787 | K69: 74 | L69: - | M69: TRUCK | N69: SELDOH NAGPUR | O69: - | Q69: BIOMASS PELLET 06MM | R69: =IFERROR(VLOOKUP(Q69,'PRODUCT TABLE'!$A$2:$B$26,2,FALSE),"-") -> 44011090 | S69: 1350 | T69: 12 | U69: KG | V69: =S69*T69 -> 16200 | W69: 0.025 | X69: 0.025 | Y69: 0 | Z69: =IF(((ROUNDUP((AG69+V69),0))-(AG69+V69))>0.49,ROUNDdown((AG69+V69),0),ROUNDup((AG69+V69),0)) + AB69 -> 17010 | AA69: =Z69-(V69+AG69 + AB69) -> 0 | AC69: =V69 -> 16200 | AD69: =AC69*W69 -> 405 | AE69: =AC69*X69 -> 405 | AF69: =AC69*Y69 -> 0 | AG69: =SUM(AD69:AF69) -> 810 | AH69: =IFERROR(MONTH(D69)," ") -> 8 | AI69: =YEAR(D69) -> 2022
A70: MAE006/22-23/35 | B70: =iferror(VLOOKUP((LEFT(A70,6)),CUSTOMER_DETAILS,2,FALSE),"-") -> NAGPUR FUELS | C70: - | D70: 44750 | E70: - | F70: - | G70: - | H70: - | I70: - | J70: =D70 -> 44750 | K70: 75 | L70: - | M70: TRUCK | N70: NAGPUR | O70: - | Q70: BIOMASS PELLET 06MM | R70: =IFERROR(VLOOKUP(Q70,'PRODUCT TABLE'!$A$2:$B$26,2,FALSE),"-") -> 44011090 | S70: 20000 | T70: 9.5 | U70: KG | V70: =S70*T70 -> 190000 | W70: 0.025 | X70: 0.025 | Y70: 0 | Z70: =IF(((ROUNDUP((AG70+V70),0))-(AG70+V70))>0.49,ROUNDdown((AG70+V70),0),ROUNDup((AG70+V70),0)) + AB70 -> 199500 | AA70: =Z70-(V70+AG70 + AB70) -> 0 | AC70: =V70 -> 190000 | AD70: =AC70*W70 -> 4750 | AE70: =AC70*X70 -> 4750 | AF70: =AC70*Y70 -> 0 | AG70: =SUM(AD70:AF70) -> 9500 | AH70: =IFERROR(MONTH(D70)," ") -> 7 | AI70: =YEAR(D70) -> 2022
A71: MAE011/22-23/36 | B71: =iferror(VLOOKUP((LEFT(A71,6)),CUSTOMER_DETAILS,2,FALSE),"-") -> VIDARBHA SALES | C71: - | D71: 44789 | E71: - | F71: - | G71: - | H71: - | I71: - | J71: =D71 -> 44789 | K71: 76 | L71: - | M71: TRUCK | N71: HINGNA NAGPUR | O71: - | Q71: SAL SEED MEAL DOC | R71: =IFERROR(VLOOKUP(Q71,'PRODUCT TABLE'!$A$2:$B$26,2,FALSE),"-") -> 23069026 | S71: 45000 | T71: 15.5 | U71: KG | V71: =S71*T71 -> 697500 | W71: 0.025 | X71: 0.025 | Y71: 0 | Z71: =IF(((ROUNDUP((AG71+V71),0))-(AG71+V71))>0.49,ROUNDdown((AG71+V71),0),ROUNDup((AG71+V71),0)) + AB71 -> 732375 | AA71: =Z71-(V71+AG71 + AB71) -> 0 | AC71: =V71 -> 697500 | AD71: =AC71*W71 -> 17437.5 | AE71: =AC71*X71 -> 17437.5 | AF71: =AC71*Y71 -> 0 | AG71: =SUM(AD71:AF71) -> 34875 | AH71: =IFERROR(MONTH(D71)," ") -> 8 | AI71: =YEAR(D71) -> 2022
A72: MAE/22-23/37 | B72: NIKHIL TRADERS | C72: - | D72: 44791 | E72: - | F72: - | G72: - | H72: - | I72: - | J72: =D72 -> 44791 | K72: 77 | L72: - | M72: TRUCK | N72: SURAT | O72: - | Q72: SAL SEED MEAL DOC | R72: =IFERROR(VLOOKUP(Q72,'PRODUCT TABLE'!$A$2:$B$26,2,FALSE),"-") -> 23069026 | S72: 1283.26 | T72: 14.4 | U72: KG | V72: =S72*T72 -> 18478.944 | W72: 0.025 | X72: 0.025 | Y72: 0 | Z72: =IF(((ROUNDUP((AG72+V72),0))-(AG72+V72))>0.49,ROUNDdown((AG72+V72),0),ROUNDup((AG72+V72),0)) + AB72 -> 19403 | AA72: =Z72-(V72+AG72 + AB72) -> 0.1088 | AC72: =V72 -> 18478.944 | AD72: =AC72*W72 -> 461.9736 | AE72: =AC72*X72 -> 461.9736 | AF72: =AC72*Y72 -> 0 | AG72: =SUM(AD72:AF72) -> 923.9472 | AH72: =IFERROR(MONTH(D72)," ") -> 8 | AI72: =YEAR(D72) -> 2022
A73: MAE006/22-23/38 | B73: =iferror(VLOOKUP((LEFT(A73,6)),CUSTOMER_DETAILS,2,FALSE),"-") -> NAGPUR FUELS | C73: - | D73: 44759 | E73: - | F73: - | G73: - | H73: - | I73: - | J73: =D73 -> 44759 | K73: 78 | L73: - | M73: TRUCK | N73: NAGPUR | O73: - | Q73: BIOMASS PELLET 06MM | R73: =IFERROR(VLOOKUP(Q73,'PRODUCT TABLE'!$A$2:$B$26,2,FALSE),"-") -> 44011090 | S73: 20000 | T73: 9.5 | U73: KG | V73: =S73*T73 -> 190000 | W73: 0.025 | X73: 0.025 | Y73: 0 | Z73: =IF(((ROUNDUP((AG73+V73),0))-(AG73+V73))>0.49,ROUNDdown((AG73+V73),0),ROUNDup((AG73+V73),0)) + AB73 -> 199500 | AA73: =Z73-(V73+AG73 + AB73) -> 0 | AC73: =V73 -> 190000 | AD73: =AC73*W73 -> 4750 | AE73: =AC73*X73 -> 4750 | AF73: =AC73*Y73 -> 0 | AG73: =SUM(AD73:AF73) -> 9500 | AH73: =IFERROR(MONTH(D73)," ") -> 7 | AI73: =YEAR(D73) -> 2022
A74: MAE033/22-23/39 | B74: SHAKTI INDUSTRIES | C74: - | D74: 44792 | E74: - | F74: - | G74: - | H74: - | I74: - | J74: =D74 -> 44792 | K74: 79 | L74: - | M74: TRUCK | N74: BUTIBORI MIDC | O74: - | Q74: BIOMASS BRIQUETTE 90MM | R74: =IFERROR(VLOOKUP(Q74,'PRODUCT TABLE'!$A$2:$B$26,2,FALSE),"-") -> 44011090 | S74: 8480 | T74: 7 | U74: KG | V74: =S74*T74 -> 59360 | W74: 0.025 | X74: 0.025 | Y74: 0 | Z74: =IF(((ROUNDUP((AG74+V74),0))-(AG74+V74))>0.49,ROUNDdown((AG74+V74),0),ROUNDup((AG74+V74),0)) + AB74 -> 62328 | AA74: =Z74-(V74+AG74 + AB74) -> 0 | AC74: =V74 -> 59360 | AD74: =AC74*W74 -> 1484 | AE74: =AC74*X74 -> 1484 | AF74: =AC74*Y74 -> 0 | AG74: =SUM(AD74:AF74) -> 2968 | AH74: =IFERROR(MONTH(D74)," ") -> 8 | AI74: =YEAR(D74) -> 2022
A75: MAE006/22-23/40 | B75: =iferror(VLOOKUP((LEFT(A75,6)),CUSTOMER_DETAILS,2,FALSE),"-") -> NAGPUR FUELS | C75: - | D75: 44796 | E75: - | F75: - | G75: - | H75: - | I75: - | J75: =D75 -> 44796 | K75: 80 | L75: - | M75: TRUCK | N75: NAGPUR | O75: - | Q75: BIOMASS PELLET 06MM | R75: =IFERROR(VLOOKUP(Q75,'PRODUCT TABLE'!$A$2:$B$26,2,FALSE),"-") -> 44011090 | S75: 10030 | T75: 9.5 | U75: KG | V75: =S75*T75 -> 95285 | W75: 0.025 | X75: 0.025 | Y75: 0 | Z75: =IF(((ROUNDUP((AG75+V75),0))-(AG75+V75))>0.49,ROUNDdown((AG75+V75),0),ROUNDup((AG75+V75),0)) + AB75 -> 100049 | AA75: =Z75-(V75+AG75 + AB75) -> -0.25 | AC75: =V75 -> 95285 | AD75: =AC75*W75 -> 2382.125 | AE75: =AC75*X75 -> 2382.125 | AF75: =AC75*Y75 -> 0 | AG75: =SUM(AD75:AF75) -> 4764.25 | AH75: =IFERROR(MONTH(D75)," ") -> 8 | AI75: =YEAR(D75) -> 2022
A76: MAE006/22-23/41 | B76: =iferror(VLOOKUP((LEFT(A76,6)),CUSTOMER_DETAILS,2,FALSE),"-") -> NAGPUR FUELS | C76: - | D76: 44805 | E76: - | F76: - | G76: - | H76: - | I76: - | J76: =D76 -> 44805 | K76: 81 | L76: - | M76: TRUCK | N76: NAGPUR | O76: - | Q76: BIOMASS PELLET 06MM | R76: =IFERROR(VLOOKUP(Q76,'PRODUCT TABLE'!$A$2:$B$26,2,FALSE),"-") -> 44011090 | S76: 10110 | T76: 11.5 | U76: KG | V76: =S76*T76 -> 116265 | W76: 0.025 | X76: 0.025 | Y76: 0 | Z76: =IF(((ROUNDUP((AG76+V76),0))-(AG76+V76))>0.49,ROUNDdown((AG76+V76),0),ROUNDup((AG76+V76),0)) + AB76 -> 122078 | AA76: =Z76-(V76+AG76 + AB76) -> -0.25 | AC76: =V76 -> 116265 | AD76: =AC76*W76 -> 2906.625 | AE76: =AC76*X76 -> 2906.625 | AF76: =AC76*Y76 -> 0 | AG76: =SUM(AD76:AF76) -> 5813.25 | AH76: =IFERROR(MONTH(D76)," ") -> 9 | AI76: =YEAR(D76) -> 2022
A77: MAE033/22-23/42 | B77: SHAKTI INDUSTRIES | C77: - | D77: 44806 | E77: - | F77: - | G77: - | H77: - | I77: - | J77: =D77 -> 44806 | K77: 82 | L77: - | M77: TRUCK | N77: BUTIBORI MIDC | O77: - | Q77: BIOMASS BRIQUETTE 90MM | R77: =IFERROR(VLOOKUP(Q77,'PRODUCT TABLE'!$A$2:$B$26,2,FALSE),"-") -> 44011090 | S77: 6425 | T77: 7 | U77: KG | V77: =S77*T77 -> 44975 | W77: 0.025 | X77: 0.025 | Y77: 0 | Z77: =IF(((ROUNDUP((AG77+V77),0))-(AG77+V77))>0.49,ROUNDdown((AG77+V77),0),ROUNDup((AG77+V77),0)) + AB77 -> 47224 | AA77: =Z77-(V77+AG77 + AB77) -> 0.25 | AC77: =V77 -> 44975 | AD77: =AC77*W77 -> 1124.375 | AE77: =AC77*X77 -> 1124.375 | AF77: =AC77*Y77 -> 0 | AG77: =SUM(AD77:AF77) -> 2248.75 | AH77: =IFERROR(MONTH(D77)," ") -> 9 | AI77: =YEAR(D77) -> 2022
A78: MAE/22-23/43 | B78: SAFETY PACKAGING | C78: - | D78: 44806 | E78: - | F78: - | G78: - | H78: - | I78: - | J78: =D78 -> 44806 | K78: 83 | L78: - | M78: TRUCK | N78: JAMTHA NAGPUR | O78: - | Q78: BIOMASS BRIQUETTE 90MM | R78: =IFERROR(VLOOKUP(Q78,'PRODUCT TABLE'!$A$2:$B$26,2,FALSE),"-") -> 44011090 | S78: 6830 | T78: 7 | U78: KG | V78: =S78*T78 -> 47810 | W78: 0.025 | X78: 0.025 | Y78: 0 | Z78: =IF(((ROUNDUP((AG78+V78),0))-(AG78+V78))>0.49,ROUNDdown((AG78+V78),0),ROUNDup((AG78+V78),0)) + AB78 -> 50200 | AA78: =Z78-(V78+AG78 + AB78) -> -0.5 | AC78: =V78 -> 47810 | AD78: =AC78*W78 -> 1195.25 | AE78: =AC78*X78 -> 1195.25 | AF78: =AC78*Y78 -> 0 | AG78: =SUM(AD78:AF78) -> 2390.5 | AH78: =IFERROR(MONTH(D78)," ") -> 9 | AI78: =YEAR(D78) -> 2022
A79: MAE003/22-23/44 | B79: =iferror(VLOOKUP((LEFT(A79,6)),CUSTOMER_DETAILS,2,FALSE),"-") -> SHREE GAYATRI PACKAGING | C79: - | D79: 44805 | E79: - | F79: - | G79: - | H79: - | I79: - | J79: =D79 -> 44805 | K79: 84 | L79: - | M79: TRUCK | N79: SELDOH NAGPUR | O79: - | Q79: BIOMASS PELLET 06MM | R79: =IFERROR(VLOOKUP(Q79,'PRODUCT TABLE'!$A$2:$B$26,2,FALSE),"-") -> 44011090 | S79: 1020 | T79: 13 | U79: KG | V79: =S79*T79 -> 13260 | W79: 0.025 | X79: 0.025 | Y79: 0 | Z79: =IF(((ROUNDUP((AG79+V79),0))-(AG79+V79))>0.49,ROUNDdown((AG79+V79),0),ROUNDup((AG79+V79),0)) + AB79 -> 13923 | AA79: =Z79-(V79+AG79 + AB79) -> 0 | AC79: =V79 -> 13260 | AD79: =AC79*W79 -> 331.5 | AE79: =AC79*X79 -> 331.5 | AF79: =AC79*Y79 -> 0 | AG79: =SUM(AD79:AF79) -> 663 | AH79: =IFERROR(MONTH(D79)," ") -> 9 | AI79: =YEAR(D79) -> 2022
A80: MAE006/22-23/45 | B80: =iferror(VLOOKUP((LEFT(A80,6)),CUSTOMER_DETAILS,2,FALSE),"-") -> NAGPUR FUELS | C80: - | D80: 44809 | E80: - | F80: - | G80: - | H80: - | I80: - | J80: =D80 -> 44809 | K80: 85 | L80: - | M80: TRUCK | N80: NAGPUR | O80: - | Q80: BIOMASS PELLET 06MM | R80: =IFERROR(VLOOKUP(Q80,'PRODUCT TABLE'!$A$2:$B$26,2,FALSE),"-") -> 44011090 | S80: 7540 | T80: 11 | U80: KG | V80: =S80*T80 -> 82940 | W80: 0.025 | X80: 0.025 | Y80: 0 | Z80: =IF(((ROUNDUP((AG80+V80),0))-(AG80+V80))>0.49,ROUNDdown((AG80+V80),0),ROUNDup((AG80+V80),0)) + AB80 -> 87087 | AA80: =Z80-(V80+AG80 + AB80) -> 0 | AC80: =V80 -> 82940 | AD80: =AC80*W80 -> 2073.5 | AE80: =AC80*X80 -> 2073.5 | AF80: =AC80*Y80 -> 0 | AG80: =SUM(AD80:AF80) -> 4147 | AH80: =IFERROR(MONTH(D80)," ") -> 9 | AI80: =YEAR(D80) -> 2022
A81: MAE006/22-23/46 | B81: NAGPUR FUELS | C81: - | D81: 44810 | E81: - | F81: - | G81: - | H81: - | I81: - | J81: =D81 -> 44810 | K81: 86 | L81: - | M81: TRUCK | N81: NAGPUR | O81: - | Q81: BIOMASS PELLET 06MM | R81: =IFERROR(VLOOKUP(Q81,'PRODUCT TABLE'!$A$2:$B$26,2,FALSE),"-") -> 44011090 | S81: 2730 | T81: 11 | U81: KG | V81: =S81*T81 -> 30030 | W81: 0.025 | X81: 0.025 | Y81: 0 | Z81: =IF(((ROUNDUP((AG81+V81),0))-(AG81+V81))>0.49,ROUNDdown((AG81+V81),0),ROUNDup((AG81+V81),0)) + AB81 -> 31531 | AA81: =Z81-(V81+AG81 + AB81) -> -0.5 | AC81: =V81 -> 30030 | AD81: =AC81*W81 -> 750.75 | AE81: =AC81*X81 -> 750.75 | AF81: =AC81*Y81 -> 0 | AG81: =SUM(AD81:AF81) -> 1501.5 | AH81: =IFERROR(MONTH(D81)," ") -> 9 | AI81: =YEAR(D81) -> 2022
A82: MAE006/22-23/47 | B82: =iferror(VLOOKUP((LEFT(A82,6)),CUSTOMER_DETAILS,2,FALSE),"-") -> NAGPUR FUELS | C82: - | D82: 44810 | E82: - | F82: - | G82: - | H82: - | I82: - | J82: =D82 -> 44810 | K82: 87 | L82: - | M82: TRUCK | N82: NAGPUR | O82: - | Q82: BIOMASS PELLET 06MM | R82: =IFERROR(VLOOKUP(Q82,'PRODUCT TABLE'!$A$2:$B$26,2,FALSE),"-") -> 44011090 | S82: 7540 | T82: 11 | U82: KG | V82: =S82*T82 -> 82940 | W82: 0.025 | X82: 0.025 | Y82: 0 | Z82: =IF(((ROUNDUP((AG82+V82),0))-(AG82+V82))>0.49,ROUNDdown((AG82+V82),0),ROUNDup((AG82+V82),0)) + AB82 -> 87087 | AA82: =Z82-(V82+AG82 + AB82) -> 0 | AC82: =V82 -> 82940 | AD82: =AC82*W82 -> 2073.5 | AE82: =AC82*X82 -> 2073.5 | AF82: =AC82*Y82 -> 0 | AG82: =SUM(AD82:AF82) -> 4147 | AH82: =IFERROR(MONTH(D82)," ") -> 9 | AI82: =YEAR(D82) -> 2022
A83: MAE006/22-23/48 | B83: =iferror(VLOOKUP((LEFT(A83,6)),CUSTOMER_DETAILS,2,FALSE),"-") -> NAGPUR FUELS | C83: - | D83: 44812 | E83: - | F83: - | G83: - | H83: - | I83: - | J83: =D83 -> 44812 | K83: 88 | L83: - | M83: TRUCK | N83: NAGPUR | O83: - | Q83: BIOMASS PELLET 06MM | R83: =IFERROR(VLOOKUP(Q83,'PRODUCT TABLE'!$A$2:$B$26,2,FALSE),"-") -> 44011090 | S83: 3090 | T83: 11 | U83: KG | V83: =S83*T83 -> 33990 | W83: 0.025 | X83: 0.025 | Y83: 0 | Z83: =IF(((ROUNDUP((AG83+V83),0))-(AG83+V83))>0.49,ROUNDdown((AG83+V83),0),ROUNDup((AG83+V83),0)) + AB83 -> 35689 | AA83: =Z83-(V83+AG83 + AB83) -> -0.5 | AC83: =V83 -> 33990 | AD83: =AC83*W83 -> 849.75 | AE83: =AC83*X83 -> 849.75 | AF83: =AC83*Y83 -> 0 | AG83: =SUM(AD83:AF83) -> 1699.5 | AH83: =IFERROR(MONTH(D83)," ") -> 9 | AI83: =YEAR(D83) -> 2022
A84: MAE/22-23/49 | B84: VINATI ORGANICS LTD | C84: - | D84: 44814 | E84: - | F84: - | G84: - | H84: - | I84: - | J84: =D84 -> 44814 | K84: 89 | L84: - | M84: TRUCK | N84: RATNAGIRI MH | O84: - | Q84: SAL SEED MEAL DOC | R84: =IFERROR(VLOOKUP(Q84,'PRODUCT TABLE'!$A$2:$B$26,2,FALSE),"-") -> 23069026 | S84: 500 | T84: 17 | U84: KG | V84: =S84*T84 -> 8500 | W84: 0.025 | X84: 0.025 | Y84: 0 | Z84: =IF(((ROUNDUP((AG84+V84),0))-(AG84+V84))>0.49,ROUNDdown((AG84+V84),0),ROUNDup((AG84+V84),0)) + AB84 -> 8925 | AA84: =Z84-(V84+AG84 + AB84) -> 0 | AC84: =V84 -> 8500 | AD84: =AC84*W84 -> 212.5 | AE84: =AC84*X84 -> 212.5 | AF84: =AC84*Y84 -> 0 | AG84: =SUM(AD84:AF84) -> 425 | AH84: =IFERROR(MONTH(D84)," ") -> 9 | AI84: =YEAR(D84) -> 2022
A85: MAE006/22-23/50 | B85: =iferror(VLOOKUP((LEFT(A85,6)),CUSTOMER_DETAILS,2,FALSE),"-") -> NAGPUR FUELS | C85: - | D85: 44815 | E85: - | F85: - | G85: - | H85: - | I85: - | J85: =D85 -> 44815 | K85: 90 | L85: - | M85: TRUCK | N85: NAGPUR | O85: - | Q85: BIOMASS PELLET 06MM | R85: =IFERROR(VLOOKUP(Q85,'PRODUCT TABLE'!$A$2:$B$26,2,FALSE),"-") -> 44011090 | S85: 3000 | T85: 11 | U85: KG | V85: =S85*T85 -> 33000 | W85: 0.025 | X85: 0.025 | Y85: 0 | Z85: =IF(((ROUNDUP((AG85+V85),0))-(AG85+V85))>0.49,ROUNDdown((AG85+V85),0),ROUNDup((AG85+V85),0)) + AB85 -> 34650 | AA85: =Z85-(V85+AG85 + AB85) -> 0 | AC85: =V85 -> 33000 | AD85: =AC85*W85 -> 825 | AE85: =AC85*X85 -> 825 | AF85: =AC85*Y85 -> 0 | AG85: =SUM(AD85:AF85) -> 1650 | AH85: =IFERROR(MONTH(D85)," ") -> 9 | AI85: =YEAR(D85) -> 2022
A86: MAE003/22-23/51 | B86: =iferror(VLOOKUP((LEFT(A86,6)),CUSTOMER_DETAILS,2,FALSE),"-") -> SHREE GAYATRI PACKAGING | C86: - | D86: 44816 | E86: - | F86: - | G86: - | H86: - | I86: - | J86: =D86 -> 44816 | K86: 91 | L86: - | M86: TRUCK | N86: SELDOH NAGPUR | O86: - | Q86: BIOMASS PELLET 06MM | R86: =IFERROR(VLOOKUP(Q86,'PRODUCT TABLE'!$A$2:$B$26,2,FALSE),"-") -> 44011090 | S86: 1020 | T86: 13 | U86: KG | V86: =S86*T86 -> 13260 | W86: 0.025 | X86: 0.025 | Y86: 0 | Z86: =IF(((ROUNDUP((AG86+V86),0))-(AG86+V86))>0.49,ROUNDdown((AG86+V86),0),ROUNDup((AG86+V86),0)) + AB86 -> 13923 | AA86: =Z86-(V86+AG86 + AB86) -> 0 | AC86: =V86 -> 13260 | AD86: =AC86*W86 -> 331.5 | AE86: =AC86*X86 -> 331.5 | AF86: =AC86*Y86 -> 0 | AG86: =SUM(AD86:AF86) -> 663 | AH86: =IFERROR(MONTH(D86)," ") -> 9 | AI86: =YEAR(D86) -> 2022
A87: MAE006/22-23/52 | B87: =iferror(VLOOKUP((LEFT(A87,6)),CUSTOMER_DETAILS,2,FALSE),"-") -> NAGPUR FUELS | C87: - | D87: 44817 | E87: - | F87: - | G87: - | H87: - | I87: - | J87: =D87 -> 44817 | K87: 92 | L87: - | M87: TRUCK | N87: NAGPUR | O87: - | Q87: BIOMASS PELLET 06MM | R87: =IFERROR(VLOOKUP(Q87,'PRODUCT TABLE'!$A$2:$B$26,2,FALSE),"-") -> 44011090 | S87: 1120 | T87: 11 | U87: KG | V87: =S87*T87 -> 12320 | W87: 0.025 | X87: 0.025 | Y87: 0 | Z87: =IF(((ROUNDUP((AG87+V87),0))-(AG87+V87))>0.49,ROUNDdown((AG87+V87),0),ROUNDup((AG87+V87),0)) + AB87 -> 12936 | AA87: =Z87-(V87+AG87 + AB87) -> 0 | AC87: =V87 -> 12320 | AD87: =AC87*W87 -> 308 | AE87: =AC87*X87 -> 308 | AF87: =AC87*Y87 -> 0 | AG87: =SUM(AD87:AF87) -> 616 | AH87: =IFERROR(MONTH(D87)," ") -> 9 | AI87: =YEAR(D87) -> 2022
A88: MAE010/22-23/53 | B88: =iferror(VLOOKUP((LEFT(A88,6)),CUSTOMER_DETAILS,2,FALSE),"-") -> KRISHNA ENTERPRISES | C88: - | D88: 44818 | E88: - | F88: - | G88: - | H88: - | I88: - | J88: =D88 -> 44818 | K88: 93 | L88: - | M88: TRUCK | N88: NAGPUR | O88: - | Q88: BIOMASS PELLET 06MM | R88: =IFERROR(VLOOKUP(Q88,'PRODUCT TABLE'!$A$2:$B$26,2,FALSE),"-") -> 44011090 | S88: 5590 | T88: 11 | U88: KG | V88: =S88*T88 -> 61490 | W88: 0.025 | X88: 0.025 | Y88: 0 | Z88: =IF(((ROUNDUP((AG88+V88),0))-(AG88+V88))>0.49,ROUNDdown((AG88+V88),0),ROUNDup((AG88+V88),0)) + AB88 -> 64564 | AA88: =Z88-(V88+AG88 + AB88) -> -0.5 | AC88: =V88 -> 61490 | AD88: =AC88*W88 -> 1537.25 | AE88: =AC88*X88 -> 1537.25 | AF88: =AC88*Y88 -> 0 | AG88: =SUM(AD88:AF88) -> 3074.5 | AH88: =IFERROR(MONTH(D88)," ") -> 9 | AI88: =YEAR(D88) -> 2022
A89: MAE/22-23/54 | B89: OJAS FEEDS | C89: - | D89: 44820 | E89: - | F89: - | G89: - | H89: - | I89: - | J89: =D89 -> 44820 | K89: 94 | L89: - | M89: TRUCK | N89: KERALA | O89: - | Q89: SAL SEED MEAL DOC | R89: =IFERROR(VLOOKUP(Q89,'PRODUCT TABLE'!$A$2:$B$26,2,FALSE),"-") -> 23069026 | S89: 25.5 | T89: 18 | U89: KG | V89: =S89*T89 -> 459 | W89: 0.025 | X89: 0.025 | Y89: 0 | Z89: =IF(((ROUNDUP((AG89+V89),0))-(AG89+V89))>0.49,ROUNDdown((AG89+V89),0),ROUNDup((AG89+V89),0)) + AB89 -> 482 | AA89: =Z89-(V89+AG89 + AB89) -> 0.05 | AC89: =V89 -> 459 | AD89: =AC89*W89 -> 11.475 | AE89: =AC89*X89 -> 11.475 | AF89: =AC89*Y89 -> 0 | AG89: =SUM(AD89:AF89) -> 22.95 | AH89: =IFERROR(MONTH(D89)," ") -> 9 | AI89: =YEAR(D89) -> 2022
A90: MAE/22-23/55 | B90: SANTOSH DHUMAL | C90: - | D90: 44827 | E90: - | F90: - | G90: - | H90: - | I90: - | J90: =D90 -> 44827 | K90: 96 | L90: - | M90: TRUCK | N90: AURANGABAD | O90: - | Q90: BIOMASS PELLET 06MM | R90: =IFERROR(VLOOKUP(Q90,'PRODUCT TABLE'!$A$2:$B$26,2,FALSE),"-") -> 44011090 | S90: 30 | T90: 13 | U90: KG | V90: =S90*T90 -> 390 | Y90: 0 | Z90: =IF(((ROUNDUP((AG90+V90),0))-(AG90+V90))>0.49,ROUNDdown((AG90+V90),0),ROUNDup((AG90+V90),0)) + AB90 -> 390 | AA90: =Z90-(V90+AG90 + AB90) -> 0 | AC90: =V90 -> 390 | AD90: =AC90*W90 -> 0 | AE90: =AC90*X90 -> 0 | AF90: =AC90*Y90 -> 0 | AG90: =SUM(AD90:AF90) -> 0 | AH90: =IFERROR(MONTH(D90)," ") -> 9 | AI90: =YEAR(D90) -> 2022
A91: MAE/22-23/56 | B91: ADITYA AGRO INDUSTRIES | C91: - | D91: 44826 | E91: - | F91: - | G91: - | H91: - | I91: - | J91: =D91 -> 44826 | K91: 97 | L91: - | M91: TRUCK | N91: NAGPUR | O91: - | Q91: BIOMASS PELLET 06MM | R91: =IFERROR(VLOOKUP(Q91,'PRODUCT TABLE'!$A$2:$B$26,2,FALSE),"-") -> 44011090 | S91: 7620 | T91: 12.5 | U91: KG | V91: =S91*T91 -> 95250 | W91: 0.025 | X91: 0.025 | Y91: 0 | Z91: =IF(((ROUNDUP((AG91+V91),0))-(AG91+V91))>0.49,ROUNDdown((AG91+V91),0),ROUNDup((AG91+V91),0)) + AB91 -> 100012 | AA91: =Z91-(V91+AG91 + AB91) -> -0.5 | AC91: =V91 -> 95250 | AD91: =AC91*W91 -> 2381.25 | AE91: =AC91*X91 -> 2381.25 | AF91: =AC91*Y91 -> 0 | AG91: =SUM(AD91:AF91) -> 4762.5 | AH91: =IFERROR(MONTH(D91)," ") -> 9 | AI91: =YEAR(D91) -> 2022
A92: MAE003/22-23/57 | B92: =iferror(VLOOKUP((LEFT(A92,6)),CUSTOMER_DETAILS,2,FALSE),"-") -> SHREE GAYATRI PACKAGING | C92: - | D92: 44826 | E92: - | F92: - | G92: - | H92: - | I92: - | J92: =D92 -> 44826 | K92: 98 | L92: - | M92: TRUCK | N92: SELDOH NAGPUR | O92: - | Q92: BIOMASS PELLET 06MM | R92: =IFERROR(VLOOKUP(Q92,'PRODUCT TABLE'!$A$2:$B$26,2,FALSE),"-") -> 44011090 | S92: 870 | T92: 13 | U92: KG | V92: =S92*T92 -> 11310 | W92: 0.025 | X92: 0.025 | Y92: 0 | Z92: =IF(((ROUNDUP((AG92+V92),0))-(AG92+V92))>0.49,ROUNDdown((AG92+V92),0),ROUNDup((AG92+V92),0)) + AB92 -> 11875 | AA92: =Z92-(V92+AG92 + AB92) -> -0.5 | AC92: =V92 -> 11310 | AD92: =AC92*W92 -> 282.75 | AE92: =AC92*X92 -> 282.75 | AF92: =AC92*Y92 -> 0 | AG92: =SUM(AD92:AF92) -> 565.5 | AH92: =IFERROR(MONTH(D92)," ") -> 9 | AI92: =YEAR(D92) -> 2022
A93: MAE010/22-23/58 | B93: =iferror(VLOOKUP((LEFT(A93,6)),CUSTOMER_DETAILS,2,FALSE),"-") -> KRISHNA ENTERPRISES | C93: - | D93: 44823 | E93: - | F93: - | G93: - | H93: - | I93: - | J93: =D93 -> 44823 | K93: 99 | L93: - | M93: TRUCK | N93: NAGPUR | O93: - | Q93: BIOMASS PELLET 06MM | R93: =IFERROR(VLOOKUP(Q93,'PRODUCT TABLE'!$A$2:$B$26,2,FALSE),"-") -> 44011090 | S93: 2090 | T93: 11 | U93: KG | V93: =S93*T93 -> 22990 | W93: 0.025 | X93: 0.025 | Y93: 0 | Z93: =IF(((ROUNDUP((AG93+V93),0))-(AG93+V93))>0.49,ROUNDdown((AG93+V93),0),ROUNDup((AG93+V93),0)) + AB93 -> 24139 | AA93: =Z93-(V93+AG93 + AB93) -> -0.5 | AC93: =V93 -> 22990 | AD93: =AC93*W93 -> 574.75 | AE93: =AC93*X93 -> 574.75 | AF93: =AC93*Y93 -> 0 | AG93: =SUM(AD93:AF93) -> 1149.5 | AH93: =IFERROR(MONTH(D93)," ") -> 9 | AI93: =YEAR(D93) -> 2022
A94: MAE/22-23/59 | B94: PRIYANSHI INDUSTRIES | C94: - | D94: 44830 | E94: - | F94: - | G94: - | H94: - | I94: - | J94: =D94 -> 44830 | K94: 100 | L94: - | M94: TRUCK | N94: WADHAMANA NAGPUR | O94: - | Q94: BIOMASS PELLET 06MM | R94: =IFERROR(VLOOKUP(Q94,'PRODUCT TABLE'!$A$2:$B$26,2,FALSE),"-") -> 44011090 | S94: 2180 | T94: 12.25 | U94: KG | V94: =S94*T94 -> 26705 | W94: 0.025 | X94: 0.025 | Y94: 0 | Z94: =IF(((ROUNDUP((AG94+V94),0))-(AG94+V94))>0.49,ROUNDdown((AG94+V94),0),ROUNDup((AG94+V94),0)) + AB94 -> 28040 | AA94: =Z94-(V94+AG94 + AB94) -> -0.25 | AC94: =V94 -> 26705 | AD94: =AC94*W94 -> 667.625 | AE94: =AC94*X94 -> 667.625 | AF94: =AC94*Y94 -> 0 | AG94: =SUM(AD94:AF94) -> 1335.25 | AH94: =IFERROR(MONTH(D94)," ") -> 9 | AI94: =YEAR(D94) -> 2022
A95: MAE010/22-23/60 | B95: =iferror(VLOOKUP((LEFT(A95,6)),CUSTOMER_DETAILS,2,FALSE),"-") -> KRISHNA ENTERPRISES | C95: - | D95: 44832 | E95: - | F95: - | G95: - | H95: - | I95: - | J95: =D95 -> 44832 | K95: 101 | L95: - | M95: TRUCK | N95: NAGPUR | O95: - | Q95: BIOMASS PELLET 06MM | R95: =IFERROR(VLOOKUP(Q95,'PRODUCT TABLE'!$A$2:$B$26,2,FALSE),"-") -> 44011090 | S95: 1710 | T95: 11.5 | U95: KG | V95: =S95*T95 -> 19665 | W95: 0.025 | X95: 0.025 | Y95: 0 | Z95: =IF(((ROUNDUP((AG95+V95),0))-(AG95+V95))>0.49,ROUNDdown((AG95+V95),0),ROUNDup((AG95+V95),0)) + AB95 -> 20648 | AA95: =Z95-(V95+AG95 + AB95) -> -0.25 | AC95: =V95 -> 19665 | AD95: =AC95*W95 -> 491.625 | AE95: =AC95*X95 -> 491.625 | AF95: =AC95*Y95 -> 0 | AG95: =SUM(AD95:AF95) -> 983.25 | AH95: =IFERROR(MONTH(D95)," ") -> 9 | AI95: =YEAR(D95) -> 2022
A96: MAE/22-23/61 | B96: RAJENDRA PATEL | C96: - | D96: 44833 | E96: - | F96: - | G96: - | H96: - | I96: - | J96: =D96 -> 44833 | K96: 102 | L96: - | M96: TRUCK | N96: KATNI MP | O96: - | Q96: SAL SEED MEAL DOC | R96: =IFERROR(VLOOKUP(Q96,'PRODUCT TABLE'!$A$2:$B$26,2,FALSE),"-") -> 23069026 | S96: 600 | T96: 15 | U96: KG | V96: =S96*T96 -> 9000 | W96: 0.025 | X96: 0.025 | Y96: 0 | Z96: =IF(((ROUNDUP((AG96+V96),0))-(AG96+V96))>0.49,ROUNDdown((AG96+V96),0),ROUNDup((AG96+V96),0)) + AB96 -> 9450 | AA96: =Z96-(V96+AG96 + AB96) -> 0 | AC96: =V96 -> 9000 | AD96: =AC96*W96 -> 225 | AE96: =AC96*X96 -> 225 | AF96: =AC96*Y96 -> 0 | AG96: =SUM(AD96:AF96) -> 450 | AH96: =IFERROR(MONTH(D96)," ") -> 9 | AI96: =YEAR(D96) -> 2022
A97: MAE006/22-23/62 | B97: =iferror(VLOOKUP((LEFT(A97,6)),CUSTOMER_DETAILS,2,FALSE),"-") -> NAGPUR FUELS | C97: - | D97: 44833 | E97: - | F97: - | G97: - | H97: - | I97: - | J97: =D97 -> 44833 | K97: 103 | L97: - | M97: TRUCK | N97: NAGPUR | O97: - | Q97: BIOMASS PELLET 06MM | R97: =IFERROR(VLOOKUP(Q97,'PRODUCT TABLE'!$A$2:$B$26,2,FALSE),"-") -> 44011090 | S97: 4110 | T97: 11.5 | U97: KG | V97: =S97*T97 -> 47265 | W97: 0.025 | X97: 0.025 | Y97: 0 | Z97: =IF(((ROUNDUP((AG97+V97),0))-(AG97+V97))>0.49,ROUNDdown((AG97+V97),0),ROUNDup((AG97+V97),0)) + AB97 -> 49628 | AA97: =Z97-(V97+AG97 + AB97) -> -0.25 | AC97: =V97 -> 47265 | AD97: =AC97*W97 -> 1181.625 | AE97: =AC97*X97 -> 1181.625 | AF97: =AC97*Y97 -> 0 | AG97: =SUM(AD97:AF97) -> 2363.25 | AH97: =IFERROR(MONTH(D97)," ") -> 9 | AI97: =YEAR(D97) -> 2022
A98: MAE006/22-23/63 | B98: =iferror(VLOOKUP((LEFT(A98,6)),CUSTOMER_DETAILS,2,FALSE),"-") -> NAGPUR FUELS | C98: - | D98: 44836 | E98: - | F98: - | G98: - | H98: - | I98: - | J98: =D98 -> 44836 | K98: 104 | L98: - | M98: TRUCK | N98: NAGPUR | O98: - | Q98: BIOMASS PELLET 06MM | R98: =IFERROR(VLOOKUP(Q98,'PRODUCT TABLE'!$A$2:$B$26,2,FALSE),"-") -> 44011090 | S98: 7690 | T98: 11.5 | U98: KG | V98: =S98*T98 -> 88435 | W98: 0.025 | X98: 0.025 | Y98: 0 | Z98: =IF(((ROUNDUP((AG98+V98),0))-(AG98+V98))>0.49,ROUNDdown((AG98+V98),0),ROUNDup((AG98+V98),0)) + AB98 -> 92857 | AA98: =Z98-(V98+AG98 + AB98) -> 0.25 | AC98: =V98 -> 88435 | AD98: =AC98*W98 -> 2210.875 | AE98: =AC98*X98 -> 2210.875 | AF98: =AC98*Y98 -> 0 | AG98: =SUM(AD98:AF98) -> 4421.75 | AH98: =IFERROR(MONTH(D98)," ") -> 10 | AI98: =YEAR(D98) -> 2022
A99: MAE004/22-23/64 | B99: =iferror(VLOOKUP((LEFT(A99,6)),CUSTOMER_DETAILS,2,FALSE),"-") -> LECILITE INGREDIENTS PVT LTD | C99: - | D99: 44838 | E99: - | F99: - | G99: - | H99: - | I99: - | J99: =D99 -> 44838 | K99: 105 | L99: - | M99: TRUCK | N99: BUTIBORI MIDC | O99: - | Q99: BIOMASS BRIQUETTE 90MM | R99: =IFERROR(VLOOKUP(Q99,'PRODUCT TABLE'!$A$2:$B$26,2,FALSE),"-") -> 44011090 | S99: 8285 | T99: 8 | U99: KG | V99: =S99*T99 -> 66280 | W99: 0.025 | X99: 0.025 | Y99: 0 | Z99: =IF(((ROUNDUP((AG99+V99),0))-(AG99+V99))>0.49,ROUNDdown((AG99+V99),0),ROUNDup((AG99+V99),0)) + AB99 -> 69594 | AA99: =Z99-(V99+AG99 + AB99) -> 0 | AC99: =V99 -> 66280 | AD99: =AC99*W99 -> 1657 | AE99: =AC99*X99 -> 1657 | AF99: =AC99*Y99 -> 0 | AG99: =SUM(AD99:AF99) -> 3314 | AH99: =IFERROR(MONTH(D99)," ") -> 10 | AI99: =YEAR(D99) -> 2022
A100: MAE005/22-23/65 | B100: =iferror(VLOOKUP((LEFT(A100,6)),CUSTOMER_DETAILS,2,FALSE),"-") -> ACI CLEAN ENERGY PVT LTD | C100: - | D100: 44838 | E100: - | F100: - | G100: - | H100: - | I100: - | J100: =D100 -> 44838 | K100: 106 | L100: - | M100: TRUCK | N100: BUTIBORI MIDC | O100: - | Q100: SAWDUST | R100: =IFERROR(VLOOKUP(Q100,'PRODUCT TABLE'!$A$2:$B$26,2,FALSE),"-") -> - | S100: 9670 | T100: 4.5 | U100: KG | V100: =S100*T100 -> 43515 | W100: 0.025 | X100: 0.025 | Y100: 0 | Z100: =IF(((ROUNDUP((AG100+V100),0))-(AG100+V100))>0.49,ROUNDdown((AG100+V100),0),ROUNDup((AG100+V100),0)) + AB100 -> 45691 | AA100: =Z100-(V100+AG100 + AB100) -> 0.25 | AC100: =V100 -> 43515 | AD100: =AC100*W100 -> 1087.875 | AE100: =AC100*X100 -> 1087.875 | AF100: =AC100*Y100 -> 0 | AG100: =SUM(AD100:AF100) -> 2175.75 | AH100: =IFERROR(MONTH(D100)," ") -> 10 | AI100: =YEAR(D100) -> 2022
...

Sheet RICE HUSK BILL
B2: BILL OF SUPPLY
B4: MAHALAXMI AGRO ENERGIES | F4: Invoice No. | I4: Dated
B5: 70 Mahakali Nagar 3, Mhalginagar, | F5: =IFERROR(VLOOKUP(F13,InvoiceDetails,11,FALSE)," ") -> 359 | I5: =VLOOKUP(F13,InvoiceDetails,4,FALSE) -> 45397
B6: Hudkeshwar Ring Road, Nagpur 34 | F6: Delivery Note | I6: Payment Mode/Terms
B7: 8550952303 | F7: =IFERROR(VLOOKUP(F13,InvoiceDetails,5,FALSE)," ") -> - | I7: =IFERROR(VLOOKUP(F13,InvoiceDetails,6,FALSE)," ") -> 15 DAYS WITHIN DELIVERY
B8: GSTN: | C8: 27BOPPP0960N1Z7 | F8: Supplier Ref. | I8: Other Reference(s)
B9: State: | C9: MAHARASHTRA | E9: 440034 | F9: =IFERROR(VLOOKUP(F13,InvoiceDetails,7,FALSE)," ") -> - | I9: =IFERROR(VLOOKUP(#REF!,InvoiceDetails,8,FALSE)," ")
B10: Mail: | C10: biomassenergies@gmail.com | F10: Buyer's Order No. | I10: Dated
B11: Consignee | F11: =IFERROR(VLOOKUP(F13,InvoiceDetails,9,FALSE)," ") -> WE23Y-00268 | I11: =IFERROR(VLOOKUP(F13,InvoiceDetails,10,FALSE)," ") -> 45397
B12: =VLOOKUP(F13,InvoiceDetails,2,FALSE) -> SIDDHAYU AYURVEDIC RESEARCH FOUNDATION PVT LTD | F12: Despatch Document No. | I12: Delivery Note Date
B13: =VLOOKUP(B12,CustDetail1,2,FALSE) -> FACTORY 172 LAKHANDUR ROAD DESAIGANJ WADSA | F13: MAE045/24-25-007 | I13: =IFERROR(VLOOKUP(#REF!,InvoiceDetails,12,FALSE)," ")
F14: Despatched Through | I14: Destination
B15: GSTN: | C15: =VLOOKUP(B12,CustDetail1,3,FALSE) -> 27AAACS8335F1ZC | F15: =IFERROR(VLOOKUP(F13,InvoiceDetails,13,FALSE)," ") -> TRUCK | I15: =IFERROR(VLOOKUP(F13,InvoiceDetails,14,FALSE)," ") -> WADSA GADCHIROLI
B16: State: | C16: =VLOOKUP(B12,CustDetail1,4,FALSE) -> MAHARASHTRA | E16: =VLOOKUP(B12,CustDetail1,5,FALSE) -> 441207
B17: Mail: | C17: =VLOOKUP(B12,CustDetail1,6,FALSE) | F17: Bill of Landing/LR-RR No. | I17: Motor Vehicle Number
F18: =IFERROR(VLOOKUP(#REF!,InvoiceDetails,15,FALSE)," ") | I18: =IFERROR(VLOOKUP(F13,InvoiceDetails,16,FALSE)," ") -> MH40CT0181
B20: Buyer (If Other Than Consignee) | F20: Terms Of Delivery
B21: =VLOOKUP(F13,InvoiceDetails,2,FALSE) -> SIDDHAYU AYURVEDIC RESEARCH FOUNDATION PVT LTD
B22: =VLOOKUP(B21,CustDetail1,2,FALSE) -> FACTORY 172 LAKHANDUR ROAD DESAIGANJ WADSA
B24: GSTN: | C24: =VLOOKUP(B12,CustDetail1,3,FALSE) -> 27AAACS8335F1ZC
B25: State: | C25: =VLOOKUP(B12,CustDetail1,4,FALSE) -> MAHARASHTRA | E25: =VLOOKUP(B12,CustDetail1,5,FALSE) -> 441207
B26: Mail: | C26: =VLOOKUP(B12,CustDetail1,6,FALSE)
B27: Sr. No. | C27: Description Of Goods | F27: HSN Code | G27: Quatity | H27: Rate | I27: Per | J27: Amount
B28: 1 | C28: =IFERROR(VLOOKUP(F13,InvoiceDetails,17,FALSE)," ") -> BIOMASS RICE HUSK | F28: =IFERROR(VLOOKUP(F13,InvoiceDetails,18,FALSE)," ") -> 1213 | G28: =IFERROR(VLOOKUP(F13,InvoiceDetails,19,FALSE)," ") -> 10830 | H28: =IFERROR(VLOOKUP(F13,InvoiceDetails,20,FALSE)," ") -> 4.45 | I28: =IFERROR(VLOOKUP(F13,InvoiceDetails,21,FALSE)," ") -> KG | J28: =IFERROR(VLOOKUP(F13,InvoiceDetails,22,FALSE)," ") -> 48193.5
H30: =IFERROR(VLOOKUP(#REF!,InvoiceDetails,23,FALSE)," ") | J30: =IFERROR(VLOOKUP(F13,InvoiceDetails,30,FALSE)," ") -> 0
H31: =IFERROR(VLOOKUP(#REF!,InvoiceDetails,24,FALSE)," ") | J31: =IFERROR(VLOOKUP(F13,InvoiceDetails,31,FALSE)," ") -> 0
E32: ROUNDOFF | J32: =IFERROR(VLOOKUP(F13,InvoiceDetails,27,FALSE)," ") -> -0.5
E34: TRANSPORTATION | J34: =IFERROR(VLOOKUP(F13,InvoiceDetails,28,FALSE)," ")
E39: Total | G39: =SUM(G28:G38) -> 10830 | J39: =IFERROR(VLOOKUP(F13,InvoiceDetails,26,FALSE)," ") -> 48193
B40: Amount Chargeable(in words) | J40: E. & O.E
B41: INR | C41: ="INR"&CHOOSE(LEFT(TEXT(J39,"000000000.00"))+1,,"One","Two","Three","Four","Five","Six","Seven","Eight","Nine") &IF(--LEFT(TEXT(J39,"000000000.00"))=0,,IF(AND(--MID(TEXT(J39,"000000000.00"),2,1)=0,--MID(TEXT(J39,"000000000.00"),3,1)=0)," Hundred"," Hundred and ")) &CHOOSE(MID(TEXT(J39,"000000000.00"),2,1)+1,,,"Twenty ","Thirty ","Forty ","Fifty ","Sixty ","Seventy ","Eighty ","Ninety ") &IF(--MID(TEXT(J39,"000000000.00"),2,1)<>1,CHOOSE(MID(TEXT(J39,"000000000.00"),3,1)+1,,"One","Two","Three","Four","Five","Six","Seven","Eight","Nine"), CHOOSE(MID(TEXT(J39,"000000000.00"),3,1)+1,"Ten","Eleven","Twelve","Thirteen","Fourteen","Fifteen","Sixteen","Seventeen","Eighteen","Nineteen")) &IF((--LEFT(TEXT(J39,"000000000.00"))+MID(TEXT(J39,"000000000.00"),2,1)+MID(TEXT(J39,"000000000.00"),3,1))=0,,IF(AND((--MID(TEXT(J39,"000000000.00"),4,1)+MID(TEXT(J39,"000000000.00"),5,1)+MID(TEXT(J39,"000000000.00"),6,1)+MID(TEXT(J39,"000000000.00"),7,1))=0,(--MID(TEXT(J39,"000000000.00"),8,1)+RIGHT(TEXT(J39,"000000000.00")))>0)," Million and "," Million ")) &CHOOSE(MID(TEXT(J39,"000000000.00"),4,1)+1,,"One","Two","Three","Four","Five","Six","Seven","Eight","Nine") &IF(--MID(TEXT(J39,"000000000.00"),4,1)=0,,IF(AND(--MID(TEXT(J39,"000000000.00"),5,1)=0,--MID(TEXT(J39,"000000000.00"),6,1)=0)," Hundred"," Hundred and")) &CHOOSE(MID(TEXT(J39,"000000000.00"),5,1)+1,,," Twenty"," Thirty"," Forty"," Fifty"," Sixty"," Seventy"," Eighty"," Ninety") &IF(--MID(TEXT(J39,"000000000.00"),5,1)<>1,CHOOSE(MID(TEXT(J39,"000000000.00"),6,1)+1,," One"," Two"," Three"," Four"," Five"," Six"," Seven"," Eight"," Nine"),CHOOSE(MID(TEXT(J39,"000000000.00"),6,1)+1," Ten"," Eleven"," Twelve"," Thirteen"," Fourteen"," Fifteen"," Sixteen"," Seventeen"," Eighteen"," Nineteen")) &IF((--MID(TEXT(J39,"000000000.00"),4,1)+MID(TEXT(J39,"000000000.00"),5,1)+MID(TEXT(J39,"000000000.00"),6,1))=0,,IF(OR((--MID(TEXT(J39,"000000000.00"),7,1)+MID(TEXT(J39,"000000000.00"),8,1)+MID(TEXT(J39,"000000000.00"),9,1))=0,--MID(TEXT(J39,"000000000.00"),7,1)<>0)," Thousand "," Thousand and ")) &CHOOSE(MID(TEXT(J39,"000000000.00"),7,1)+1,,"One","Two","Three","Four","Five","Six","Seven","Eight","Nine") &IF(--MID(TEXT(J39,"000000000.00"),7,1)=0,,IF(AND(--MID(TEXT(J39,"000000000.00"),8,1)=0,--MID(TEXT(J39,"000000000.00"),9,1)=0)," Hundred "," Hundred and "))& CHOOSE(MID(TEXT(J39,"000000000.00"),8,1)+1,,,"Twenty ","Thirty ","Forty ","Fifty ","Sixty ","Seventy ","Eighty ","Ninety ") &IF(--MID(TEXT(J39,"000000000.00"),8,1)<>1,CHOOSE(MID(TEXT(J39,"000000000.00"),9,1)+1,,"One","Two","Three","Four","Five","Six","Seven","Eight","Nine"),CHOOSE(MID(TEXT(J39,"000000000.00"),9,1)+1,"Ten","Eleven","Twelve","Thirteen","Fourteen","Fifteen","Sixteen","Seventeen","Eighteen","Nineteen")) &IF(RIGHT(TEXT(J39,"000000000.00"),2)>"000000000.00"," & "&RIGHT(TEXT(J39,"000000000.00"),2)&" Paise Only.","Only.") -> INR Forty Eight Thousand One Hundred and Ninety ThreeOnly.
B42: HSN Code | E42: Taxable Value | F42: Central Tax | H42: State Tax | J42: Total Tax Amount
F43: Rate | G43: Amount | H43: Rate | I43: Amount
B44: =IFERROR(VLOOKUP(F13,InvoiceDetails,18,FALSE)," ") -> 1213 | E44: =IFERROR(VLOOKUP(F13,InvoiceDetails,26,FALSE)," ") -> 48193 | F44: =IFERROR(VLOOKUP(F13,InvoiceDetails,23,FALSE)," ") | G44: =IFERROR(VLOOKUP(F13,InvoiceDetails,30,FALSE)," ") -> 0 | H44: =IFERROR(VLOOKUP(F13,InvoiceDetails,24,FALSE)," ") | I44: =IFERROR(VLOOKUP(F13,InvoiceDetails,31,FALSE)," ") -> 0 | J44: =IFERROR(VLOOKUP(F13,InvoiceDetails,33,FALSE)," ") -> 0
B45: Total | E45: =E44 -> 48193 | G45: =G44 -> 0 | I45: =I44 -> 0 | J45: =J44 -> 0
B46: Tax Amount(in words)
B47: INR | C47: ="INR"&CHOOSE(LEFT(TEXT(J45,"000000000.00"))+1,,"One","Two","Three","Four","Five","Six","Seven","Eight","Nine") &IF(--LEFT(TEXT(J45,"000000000.00"))=0,,IF(AND(--MID(TEXT(J45,"000000000.00"),2,1)=0,--MID(TEXT(J45,"000000000.00"),3,1)=0)," Hundred"," Hundred and ")) &CHOOSE(MID(TEXT(J45,"000000000.00"),2,1)+1,,,"Twenty ","Thirty ","Forty ","Fifty ","Sixty ","Seventy ","Eighty ","Ninety ") &IF(--MID(TEXT(J45,"000000000.00"),2,1)<>1,CHOOSE(MID(TEXT(J45,"000000000.00"),3,1)+1,,"One","Two","Three","Four","Five","Six","Seven","Eight","Nine"), CHOOSE(MID(TEXT(J45,"000000000.00"),3,1)+1,"Ten","Eleven","Twelve","Thirteen","Fourteen","Fifteen","Sixteen","Seventeen","Eighteen","Nineteen")) &IF((--LEFT(TEXT(J45,"000000000.00"))+MID(TEXT(J45,"000000000.00"),2,1)+MID(TEXT(J45,"000000000.00"),3,1))=0,,IF(AND((--MID(TEXT(J45,"000000000.00"),4,1)+MID(TEXT(J45,"000000000.00"),5,1)+MID(TEXT(J45,"000000000.00"),6,1)+MID(TEXT(J45,"000000000.00"),7,1))=0,(--MID(TEXT(J45,"000000000.00"),8,1)+RIGHT(TEXT(J45,"000000000.00")))>0)," Million and "," Million ")) &CHOOSE(MID(TEXT(J45,"000000000.00"),4,1)+1,,"One","Two","Three","Four","Five","Six","Seven","Eight","Nine") &IF(--MID(TEXT(J45,"000000000.00"),4,1)=0,,IF(AND(--MID(TEXT(J45,"000000000.00"),5,1)=0,--MID(TEXT(J45,"000000000.00"),6,1)=0)," Hundred"," Hundred and")) &CHOOSE(MID(TEXT(J45,"000000000.00"),5,1)+1,,," Twenty"," Thirty"," Forty"," Fifty"," Sixty"," Seventy"," Eighty"," Ninety") &IF(--MID(TEXT(J45,"000000000.00"),5,1)<>1,CHOOSE(MID(TEXT(J45,"000000000.00"),6,1)+1,," One"," Two"," Three"," Four"," Five"," Six"," Seven"," Eight"," Nine"),CHOOSE(MID(TEXT(J45,"000000000.00"),6,1)+1," Ten"," Eleven"," Twelve"," Thirteen"," Fourteen"," Fifteen"," Sixteen"," Seventeen"," Eighteen"," Nineteen")) &IF((--MID(TEXT(J45,"000000000.00"),4,1)+MID(TEXT(J45,"000000000.00"),5,1)+MID(TEXT(J45,"000000000.00"),6,1))=0,,IF(OR((--MID(TEXT(J45,"000000000.00"),7,1)+MID(TEXT(J45,"000000000.00"),8,1)+MID(TEXT(J45,"000000000.00"),9,1))=0,--MID(TEXT(J45,"000000000.00"),7,1)<>0)," Thousand "," Thousand and ")) &CHOOSE(MID(TEXT(J45,"000000000.00"),7,1)+1,,"One","Two","Three","Four","Five","Six","Seven","Eight","Nine") &IF(--MID(TEXT(J45,"000000000.00"),7,1)=0,,IF(AND(--MID(TEXT(J45,"000000000.00"),8,1)=0,--MID(TEXT(J45,"000000000.00"),9,1)=0)," Hundred "," Hundred and "))& CHOOSE(MID(TEXT(J45,"000000000.00"),8,1)+1,,,"Twenty ","Thirty ","Forty ","Fifty ","Sixty ","Seventy ","Eighty ","Ninety ") &IF(--MID(TEXT(J45,"000000000.00"),8,1)<>1,CHOOSE(MID(TEXT(J45,"000000000.00"),9,1)+1,,"One","Two","Three","Four","Five","Six","Seven","Eight","Nine"),CHOOSE(MID(TEXT(J45,"000000000.00"),9,1)+1,"Ten","Eleven","Twelve","Thirteen","Fourteen","Fifteen","Sixteen","Seventeen","Eighteen","Nineteen")) &IF(RIGHT(TEXT(J45,"000000000.00"),2)>"000000000.00"," & "&RIGHT(TEXT(J45,"000000000.00"),2)&" Paise Only.","Only.") -> INROnly.
B49: Remarks: | F49: BANK NAME | H49: STATE BANK OF INDIA
F50: ACCOUNT NO. | H50: 39935045918
B51: PAN | C51: BOPPP0960N | F51: BRANCH & IFS CODE | H51: UDAY NAGAR SBIN0017637
B52: Declaration
B53: We declare that this invoice shows that the actual price of the goods described and that all particular are true and correct | H53: For MAHALAXMI AGRO ENERGIES (2022-2023)
H56: Authorised Signatory
B57: This is a computer Generated Invoice

Sheet CUSTOMER DETAILS
A1: CODE | B1: Cust Name | C1: Address | D1: GSTN | E1: State Name | F1: Pin Code | G1: Email | H1: CODE
A2: MAE001 | B2: JEEVIKA YUGCHEM PVT LTD. | C2: K - 53, MIDC, BUTIBORI FIVE STAR INDUSTRIAL AREA, DIST-NAGPUR | D2: 27AACCJ5745Q1ZW | E2: MAHARASHTRA | F2: 441122 | G2: jeevika.yugchem@gmail.com | H2: MAE001
B3: SUPERIOR DRINKS PVT LTD. | C3: B-220, MIDC, INDUSTRIAL AREA, BUTIBORI, MAHARASHTRA, 441122 | E3: MAHARASHTRA | F3: 441122 | G3: akhilesh@superiordrinks.com
A4: MAE002 | B4: PDDR MEDICAL PRODUCTS & SERVICES PVT LTD | C4: 122/2 MOUJA SANGAM OPP. DADASAHEB KALMEGH DENTAL COLLEGE, WANADONGARI, HINGNA ROAD, NAGPUR | D4: 27AAICP9043P1ZM | E4: MAHARASHTRA | F4: 441110 | G4: info@dhobitech.com | H4: MAE002
A5: MAE003 | B5: SHREE GAYATRI PACKAGING | C5: S302, SELDOH-SELU, SELDOH, WARDHA, MH 442001 | D5: 27CWDPS6036D1ZH | E5: MAHARASHTRA | F5: 442001 | H5: MAE003
A6: MAE004 | B6: LECILITE INGREDIENTS PVT LTD | C6: PLOT NO - D63, OPP RELIANCE POWER PLANT, MIDC, BUTIBORI, NAGPUR | D6: 27AANCA0464E1ZT | E6: MAHARASHTRA | F6: 441122 | G6: accounts@lecilite.com | H6: MAE004
A7: MAE005 | B7: ACI CLEAN ENERGY PVT LTD | C7: PLOT NO H-22, KANHOLIBARA ROAD, BUTIBORI, MIDC, NAGPUR | D7: 27AAICA1854D1ZW | E7: MAHARASHTRA | F7: 441122 | H7: MAE005
A8: MAE006 | B8: NAGPUR FUELS | C8: 663, GHAT ROAD, NEAR POOJA DAIRY, NAGPUR | D8: 27AAMFN0334Q1ZT | E8: MAHARASHTRA | F8: 440008 | H8: MAE006
A9: MAE007 | B9: KABRA FOODS | C9: J - 97, MIDC, JALGAON | D9: URB | E9: MAHARASHTRA | F9: 425001 | H9: MAE007
A10: MAE008 | B10: PRABHAT ENTERPRISES | C10: RAVINDRADATTA, CO-OP HOUSING SOCIETY, B/3063 BP CROSS ROAD, BHAYANDAR, MUMBAI | D10: 27ABCPD4196R1Z4 | E10: MAHARASHTRA | F10: 401105 | H10: MAE008
A11: MAE009 | B11: AMAN TRADERS | C11: NEAR ROCKY TALKIES, KMPU, LASHKAR ROAD, GWALIOR | D11: 23JHQPK7753C1Z0 | E11: MADHYA PRADESH | F11: 474001 | H11: MAE009
A12: MAE010 | B12: KRISHNA ENTERPRISES | C12: 663, GHAT ROAD, NEAR POOJA DAIRY, NAGPUR | D12: 27AANFK6943M1ZK | E12: MAHARASHTRA | F12: 440008 | H12: MAE010
A13: MAE011 | B13: VIDARBHA SALES | C13: A - 705 LOKMAT BHAWAN, WARDHA ROAD, NAGPUR | D13: 27AAGFV1027J1Z5 | E13: MAHARASHTRA | F13: 440012 | H13: MAE011
A14: MAE012 | B14: SHRI SHIVAY AGRO ENERGIES | C14: WARD NO. 5, KATANGI, DIST BALAGHAT | D14: 23BQRPT4944C1CK | E14: MADHYA PRADESH | F14: 481445 | H14: MAE012
A15: MAE013 | B15: SHREE BAIDYANATH AYUR BHAWAN PVT LTD | C15: GREAT NAG ROAD NAGPUR | D15: 27AAECS54081ZK | E15: MAHARASHTRA | F15: 440024 | G15: care@baidyanath.info | H15: MAE013
A16: MAE014 | B16: SIDDHAYU AYURVEDIC RESEARCH FOUNDATION PVT LTD | C16: KH NO. 103, MOUZA BAHADURA, UMRED ROAD, NAGPUR | D16: 27AAACS83351ZC | E16: MAHARASHTRA | F16: 441204 | H16: MAE014
A17: MAE015 | B17: ASIAN GLOBAL EXIM | C17: PLOT NO. 61, WARD NO.3, TEMBHRI, AALAGONDI, NAGPUR | D17: 27DDFPP8418E1ZC | E17: MAHARASHTRA | F17: 441108 | H17: MAE015
A18: MAE016 | B18: BHARTI ENTERPRISES | C18: FLAT NO 401 TYPE 1 WING A KASTURI NAG GOTAL PANJRI BESA NAGPUR | D18: 27GVHPD1357R1ZZ | E18: MAHARASHTRA | F18: 440034 | H18: MAE016
A19: MAE017 | B19: SAI KALYANI AGENCY | C19: PLOT NO-GV/39, JAGANNATHA NAGAR, ROAD NO-11, PO-GGP COLONY, Bhubaneswar, Khordha, Odisha, 751025 | D19: 21AXYPP6560F1Z2 | E19: ODISHA | F19: 751025 | G19: JITENDRAPANIGRAHI84@GMAIL.COM | H19: MAE017
A20: MAE018 | B20: AMBARATI | C20: M 22 MIDC HINGNA NAGPUR 440016 | D20: 27AAAFA3435F1ZX | E20: MAHARASHTRA | F20: 440016 | H20: MAE018
A21: MAE019 | B21: NITIKA PHARMACEUTICALS SPECIALITIES PVT. LTD | C21: 26 PANKAJ PRABHA DHARAMPETH NAGPUR 440010 | D21: 27AADCN7442F1ZG | E21: MAHARASHTRA | F21: 440010 | H21: MAE019
A22: MAE020 | B22: A K WAFER PRODUCTS | C22: NEAR GANJESHAHEEDA MASJID JINSI ROAD BAIJI PURA AURANGABAD M.H | D22: 27AUSPS3059H1ZZ | E22: MAHARASHTRA | G22: 9325200232 | H22: MAE020
A23: MAE021 | B23: HARIWANSH PACKAGING PVT LTD | C23: PLOT NO K 62, OPP GAMMON INDIA BUTIBORI NAGPUR | D23: 27AACCH4833P1Z5 | E23: MAHARASHTRA | F23: 441122 | G23: PURCHASE@HARIWANSH.COM | H23: MAE021
A24: MAE022 | B24: BIO ENERGY | C24: SR NO. 48/2 CHAVAN INDUSTRIES GODOWN NO 8 NEAR BENKAR VASTI DHAYARI PUNE 411041 | D24: 27AAYFB8353R1Z8 | E24: MAHARASHTRA | F24: 411041 | G24: BIOENERGYPUNE@GMAIL.COM | H24: MAE022
A25: MAE023 | B25: GREENWAKE ENERGY SOLUTIONS | C25: SHARDA SAGAR CHSL 003 GR.FLOOR ROAD NO 7 PLOT NO 167-168 SECTOR 10 NEW PANVEL MAHARASTRA | D25: URB | E25: MAHARASHTRA | F25: 410206 | G25: 9870314819 | H25: MAE023
A26: MAE024 | B26: NATURE BLISS AGRO FARMS | C26: KARANJA MAHARASTRA | D26: URB | E26: MAHARASHTRA | H26: MAE024
A27: MAE025 | B27: SHIVA TRADERS | C27: SHREEYA COMPLEX RING ROAD NO 2 TATIBANDH RAIPUR | D27: 22AGVPS3688K1ZH | E27: CHATTISGARH | F27: 492099 | H27: MAE025
A28: MAE026 | B28: MITTAL COAL COMPANY | C28: JAGANNATH PURI BEHIND BAHADUR MOTORS DELHI ROAD MEERUT | D28: 09AABFM8974G1ZU | E28: UTTAR PRADESH | F28: 250002 | H28: MAE026
A29: MAE027 | B29: AERO AGRO CHEMICAL INDUSTRIES | C29: 427/3 INDUSTRIAL AREA BHANPURI RAIPUR CHATTISGARH 493221 | D29: 22AACCA4247N1ZQ | E29: CHATTISGARH | F29: 493221 | H29: MAE027
A30: MAE028 | B30: CRYSTAL CROP PROTECTION LIMITED | C30: G-54 MIDC INDUSTRIAL AREA BUTIBORI NAGPUR | D30: 27AABCJ3574E2ZM | E30: MAHARASHTRA | F30: 441122 | H30: MAE028
A31: MAE029 | B31: AEC PLAST PRIVATE LIMITED | C31: PLOT NO B-32 TO 35,TEMBHARI,MIDC BUTIBORI NAGPUR | D31: 27AAUCA1519R1ZX | E31: MAHARASHTRA | F31: 441110 | H31: MAE029
A32: MAE030 | B32: CARE INDIA | C32: 5,SAHIL PARK SOCIETY,NR. S.T. BUS STAND,JAMBUSAR,DISTRICT-BHARUCH,GUJARAT | D32: 24AADCC3639H1ZU | E32: GUJRAT | F32: 392150 | H32: MAE030
A33: MAE031 | B33: RSG AGRO WASTE MANAGEMENT | C33: PLOT NO A-14/1,BUTIBORI MIDC | D33: 27ABEFR4697M1ZD | E33: MAHARASHTRA | F33: 441122 | H33: MAE031
A34: MAE032 | B34: MPM PVT LIMITED | C34: M-22, HINGNA MIDC, | E34: MAHARASHTRA | F34: 440016 | H34: MAE032
A35: MAE033 | B35: SHAKTI INDUSTRIES | C35: SHAKTI INDUSTRIES , CHATRAPATI NAGAR,AURANGABAD | D35: 27AKEPJ1893J1ZV | E35: MAHARASHTRA | F35: 431001 | H35: MAE033
A36: MAE034 | B36: SHREE GAJANAN ENTERPRISES | C36: PLOT NO 8 SHRI KRISHNA NAGAR GODHANI ROAD ZINGABAI TAKLI NAGPUR 440030 | D36: 27AKYPI7194M1Z0 | E36: MAHARASHTRA | F36: 440030 | H36: MAE034
A37: MAE035 | B37: SRJ ENERGY | C37: 172SUDAM ROAD BAPURAO GALLI ITWARI NAGPUR 440002 | D37: 27ANJPJ0780C1Z7 | E37: MAHARASHTRA | F37: 440002 | H37: MAE035
A38: MAE036 | B38: NJ RENEWABLE ENERGY PVT LIMITED | C38: 410 4th FLOOR TECHNO I T PARK EKSAR LINK ROAD BORIWALI WEST MUMBAI 400092 | D38: 27AAGCN9404L1Z2 | E38: MAHARASHTRA | F38: 400092 | G38: njrepl@yahoo.com | H38: MAE036
A39: MAE037 | B39: BAIDYANATH BIOFUELS PVT LIMITED | C39: PLOT NO B-48 ADDL BUTIBORI INDUSTRIAL AREA VILLAGE BRAMHNI NAGPUR -441122 | D39: 27AAJCB2196C1ZR | E39: MAHARASHTRA | F39: 441122 | H39: MAE037
A40: MAE038 | B40: VENUS ENTERPRISES ENERGY PVT LTD | C40: B.NO 28,50 GREEN HEIGHTS OPPOSITE KAMALNAYAN BAJAJ HOSPITAL BEED BYPASS AURANGABAD | D40: 27AAICV6412C1ZH | E40: MAHARASHTRA | F40: 431001 | G40: venusgogreen@gmail.com | H40: MAE038
A41: MAE039 | B41: GNG AGRITECH WASTE MANAGEMENT PVT LTD | C41: K.KHATA 35/57 VILLAGE BABUPUR NEAR DAULATABAD,GURUGRAM,HARYANA | D41: 06AAHCG0807D1Z4 | E41: HARYANA | G41: accounts@gnggroup.com | H41: MAE039
A42: MAE040 | B42: GVR NUTRIES PVT LTD | C42: AT CHICHGHAT (RATHI) POST SHEGAON (KUNDI) TAH HINGANGHAT WARDHA | D42: 27AAECG7015J1ZK | E42: MAHARASHTRA | G42: WARUNRATHI@GMAIL.COM | H42: MAE040
A43: MAE041 | B43: VANDANA FOODS | C43: PL No-C-9/2,MIDC HINGNA ROAD, NAGPUR | D43: 27AAFFV2157C1ZC | E43: MAHARASHTRA | H43: MAE041
A44: MAE042 | B44: THE URBAN INFRA INC | C44: OPP L AND T GANE NO 7,12,1202, SHRISTI GALAXY POWAI,SAKINAKA,MUMBAI MUMBAI SUBURBAN,MAHARASTRA | E44: MAHARASHTRA | F44: 400072 | H44: MAE042
A45: MAE043 | B45: SIDDHAYU LIFE SCIENCES PVT LTD | C45: J71,J72,J73,J74,J75,J76 IGC BORGAON SECTOR KHAIRITAIGAON CHINDWARA MADHYAPRADESH | D45: 23ABECS8506K1Z6 | E45: MADHYA PRADESH | F45: 480106 | H45: MAE043
A46: MAE044 | B46: JAI DURGA ENTERPRISES | C46: AT PO TUBEY PS JARPADA DIST ANGUL ODISHA | D46: 21DJZPS8796C1ZB | E46: ODISHA | F46: 759132 | H46: MAE044
A47: MAE045 | B47: SIDDHAYU AYURVEDIC RESEARCH FOUNDATION PVT LTD | C47: FACTORY 172 LAKHANDUR ROAD DESAIGANJ WADSA | D47: 27AAACS8335F1ZC | E47: MAHARASHTRA | F47: 441207 | H47: MAE045
A48: MAE046 | B48: MAHI ENTERPRISES | C48: PLOT 68 WARD NO 3 BEHIND DATTA MEGHE COLLEGE SAROJINI LAYOUT RAJIV NAGAR WANADONGRI HINGNA | D48: 27FLBPB9524F1Z8 | E48: MAHARASHTRA | F48: 441110 | H48: MAE046
A49: MAE047 | B49: SHRI HARI FOOD INDUSTRIES | C49: PLOT NO M-15 ADDITIONAL MIDC NANDGAONPETH AMRAVATI | D49: 27KAAPS0192H1ZG | E49: MAHARASHTRA | F49: 444901
A50: MAE048 | B50: VITUS OIL SOLUTIONS PVT LTD | C50: DREAMZLAND BUSINESS PARK B-4 SHOP NO 31 AMRAVATI | D50: 27AAKCV2083M1ZR | E50: MAHARASHTRA | F50: 444901 | H50: MAE048
A51: MAE049 | B51: TTD METAL UDYOG | C51: 49 Gajanan nagar midc electronic zone square Hingna road Nagpur 16 | D51: 27ATBPD3858P1Z9 | E51: MAHARASHTRA | F51: 440016 | H51: MAE049
A52: MAE050 | B52: M/S BISEN BIO ENERGIES | C52: WARD NO 1 MUNDAPAR BARGHAT DSIT. SEONI (M.P) 480667 | D52: 23BTWPB6798Q3ZG | E52: MAHARASHTRA | F52: 480667 | H52: MAE050
A53: MAE051 | B53: VAISHNAW TRADING COMPANY | C53: DABKI ROAD OLD CITY AKOLA MAHARASTRA 444002 | D53: 27BZZPV9605H1ZA | E53: MAHARASHTRA | F53: 444002 | H53: MAE051
A54: MAE052 | B54: MAA BAGLA TRADERS | C54: KHATA NO 7 MAUJA GOGA MANPUR GAYA GAYA BIHAR | D54: 10FAUPR7910H1ZD | E54: BIHAR | F54: 823002 | H54: MAE052
A55: MAE053 | B55: Sankalp Industries | C55: Nimbhora Lahe, Badnera Amravati | D55: 27ACLFS7336L1ZF | E55: MAHARASHTRA | F55: 444601 | H55: MAE053
A56: MAE054 | B56: SAI STEAM SERVICES | C56: OPP DEVEDAYA NAGAR, B 102, IRIS UNNATHI GARDENS,OFF POKHRAN RD 1, PRABHAKAR KUTHE MARG, Thane,Maharashtra, 400606 | D56: 27ACWPD5063G1ZD | E56: MAHARASHTRA | F56: 400606 | H56: MAE054
A57: MAE055 | B57: GAUTAM ENTERPRISES | C57: CS NO 2494, BESIDE ASHWOOD MEMORIAL HOSPITAL DAUND MAHARASHTRA | D57: 27FTOPM7205K2Z2 | E57: MAHARASHTRA | F57: 413801 | H57: MAE055
A58: MAE056 | B58: BHUTTATVA BIOTECH | C58: Shop No 2, Commercial Phase 1, First City, MIHAN, Khapri, Nagpur 441108 | D58: 27ERGPK4411J1ZQ | E58: MAHARASHTRA | F58: 441108 | G58: adept.infra@gmail.com | H58: MAE056
A59: MAE057 | B59: PARMESHWAR KALE | C59: 7-3-123/A/2 PLOT NO 44 SY NO 72 & 25 GAGAN PAHAD RAJENDRA NAGAR TELANGANA | D59: URB | E59: HYDRABAD | F59: 500077 | G59: 9870314819 | H59: MAE057
A60: MAE058 | B60: EXOTIC HOSPITALITY NAGPUR PVT LTD | C60: TATHASTU PENCH PENCH TIGER RESERVE AWARGHANI TURIA SEONI | D60: 23AAACE8761B1Z0 | E60: MADHYA PRADESH | F60: 480881 | G60: ravi@sandeepdwellers.com | H60: MAE058
A61: MAE059 | B61: SGB AMRUT PRASAD CLEANING HOUSE | C61: SHAHPUR BHANDARA | E61: MAHARASHTRA | H61: MAE059
A62: MAE060 | B62: GAURI,S TAVA TADKA | C62: HARIDARSHAN APARTMENT TRIMURTI NAGAR BESIDE KRISHNA DENTAL CLINIC | E62: MAHARASHTRA | H62: MAE060
A63: MAE061

Sheet PRODUCT TABLE
A1: PRODUCT NAME | B1: HSN CODE
A2: BIOMASS BRIQUETTE 90MM | B2: 44011090
A3: BIOMASS PELLET 06MM | B3: 44011090
A4: BIOMASS PELLET 08MM | B4: 44011090
A5: SAL SEED MEAL DOC | B5: 23069026
A6: SAWDUST | B6: -
A7: KAJU DOC | B7: 44011010
A8: WOOD CHARCOAL | B8: 4402
A9: BIOMASS RICE HUSK | B9: 1213
A10: BAGS | B10: 0
A11: PACKING PALLETS | B11: 4415
A12: BIOMASS PELLET STOVE 15KG
A13: BIOMASS PELLET STOVE 10KG

Sheet Business Overview
B1: Turnover Data
A3: January
A4: February
A5: March
A6: April
A7: May
A8: June
A9: July
A10: August
A11: September
A12: October
A13: November
A14: December
F18: #DIV/0!
A21: In MT | E21: Average Profit Share | F21: =SUM(E23:E27) -> 993322.56
A23: =C23/1000 -> 0.2 | E23: =D23*9% -> 117
A24: =C24/1000 -> 500.305 | E24: =D24*5% -> 169422.91
A25: =C25/1000 -> 413.82325 | E25: =D25*5% -> 258091.25
A26: =C26/1000 -> 304.58 | E26: =D26*10% -> 364730.45
A27: =C27/1000 -> 429.125 | E27: =D27*10% -> 200960.95

Sheet Copy of INVOICE DETAILS
A1: Invoice Number | B1: Consignee Name | C1: Buyer | D1: Dated | E1: Delivery Note | F1: Payment Mode/Terms | G1: Supplier Ref. | H1: Other Reference(s) | I1: Buyer's Order No. | J1: Date | K1: Despatch Document No. | L1: Delivery Note Date | M1: Despatch through | N1: Destination | O1: Bill of Landing/LR-RR No. | P1: Motor Vehicle Number | Q1: Description of Goods | R1: HSN Code | S1: QTY | T1: Rate | U1: per(wt) | V1: Amount | W1: SGST | X1: CGST | Y1: IGST | Z1: Total | AA1: Roundoff | AB1: Taxable Value | AC1: SGST AMT | AD1: CGST AMT | AE1: IGST | AF1: Tax Total
A2: MAE001/2021-24 | B2: JEEVIKA YUGCHEM PVT LTD. | C2: - | D2: 44220 | E2: - | F2: - | G2: - | H2: - | I2: JYC/PO/PM/20-21/231 | J2: 44217 | K2: 1 | L2: - | M2: TRUCK | N2: MIDC Butibori | O2: - | P2: MH40N8211 | Q2: Biomass Briquette 90mm | R2: 44011090 | S2: 10.9 | T2: 5050 | U2: MT | V2: =S2*T2 -> 55045 | W2: 0.025 | X2: 0.025 | Y2: 0 | Z2: =ROUNDUP((AF2+V2),0) -> 57798 | AA2: =Z2-(V2+AF2) -> 0.75 | AB2: =V2 -> 55045 | AC2: =AB2*W2 -> 1376.125 | AD2: =AB2*X2 -> 1376.125 | AE2: =AB2*Y2 -> 0 | AF2: =SUM(AC2:AE2) -> 2752.25
A3: MAE001/2021-02 | B3: JEEVIKA YUGCHEM PVT LTD. | C3: - | D3: 44231 | E3: - | F3: - | G3: - | H3: - | I3: JYC/PO/PM/20-21/236 | J3: 44217 | K3: 2 | L3: - | M3: TRUCK | N3: MIDC Butibori | O3: - | P3: MH40N8725 | Q3: Biomass Briquette 90mm | R3: 44011090 | S3: 9.43 | T3: 5050 | U3: MT | V3: =S3*T3 -> 47621.5 | W3: 0.025 | X3: 0.025 | Y3: 0 | Z3: =ROUNDUP((AF3+V3),0) -> 50003 | AA3: =Z3-(V3+AF3) -> 0.425 | AB3: =V3 -> 47621.5 | AC3: =AB3*W3 -> 1190.5375 | AD3: =AB3*X3 -> 1190.5375 | AE3: =AB3*Y3 -> 0 | AF3: =SUM(AC3:AE3) -> 2381.075
A4: MAE001/2021-03 | B4: JEEVIKA YUGCHEM PVT LTD. | C4: - | D4: 44243 | E4: - | F4: - | G4: - | H4: - | I4: JYC/PO/PM/20-21/236 | J4: 44217 | K4: 3 | L4: - | M4: TRUCK | N4: MIDC Butibori | O4: - | P4: MH40N8500 | Q4: Biomass Briquette 90mm | R4: 44011090 | S4: 9.365 | T4: 5050 | U4: MT | V4: =S4*T4 -> 47293.25 | W4: 0.025 | X4: 0.025 | Y4: 0 | Z4: =ROUNDUP((AF4+V4),0) -> 49658 | AA4: =Z4-(V4+AF4) -> 0.0875 | AB4: =V4 -> 47293.25 | AC4: =AB4*W4 -> 1182.3312 | AD4: =AB4*X4 -> 1182.3312 | AE4: =AB4*Y4 -> 0 | AF4: =SUM(AC4:AE4) -> 2364.6625
A5: MAE001/2021-04 | B5: JEEVIKA YUGCHEM PVT LTD. | C5: - | D5: 44253 | E5: - | F5: - | G5: - | H5: - | I5: JYC/PO/PM/20-21/236 | J5: 44253 | K5: 4 | L5: - | M5: TRUCK | N5: MIDC Butibori | O5: - | P5: MH14BT0796 | Q5: Biomass Briquette 90mm | R5: 44011090 | S5: 10.03 | T5: 5050 | U5: MT | V5: =S5*T5 -> 50651.5 | W5: 0.025 | X5: 0.025 | Y5: 0 | Z5: =ROUNDUP((AF5+V5),0) -> 53185 | AA5: =Z5-(V5+AF5) -> 0.925 | AB5: =V5 -> 50651.5 | AC5: =AB5*W5 -> 1266.2875 | AD5: =AB5*X5 -> 1266.2875 | AE5: =AB5*Y5 -> 0 | AF5: =SUM(AC5:AE5) -> 2532.575
A6: MAE001/2021-05 | B6: JEEVIKA YUGCHEM PVT LTD. | C6: - | D6: 44277 | E6: - | F6: - | G6: - | H6: - | I6: JYC/PO/PM/20-21/236 | J6: 44277 | K6: 5 | L6: - | M6: TRUCK | N6: MIDC Butibori | O6: - | P6: MH40N8542 | Q6: Biomass Briquette 90mm | R6: 44011090 | S6: 10.64 | T6: 5050 | U6: MT | V6: =S6*T6 -> 53732 | W6: 0.025 | X6: 0.025 | Y6: 0 | Z6: =ROUNDUP((AF6+V6),0) -> 56419 | AA6: =Z6-(V6+AF6) -> 0.4 | AB6: =V6 -> 53732 | AC6: =AB6*W6 -> 1343.3 | AD6: =AB6*X6 -> 1343.3 | AE6: =AB6*Y6 -> 0 | AF6: =SUM(AC6:AE6) -> 2686.6
A7: MAE001/2021-06 | B7: JEEVIKA YUGCHEM PVT LTD. | C7: - | D7: 44305 | E7: - | F7: - | G7: - | H7: - | I7: JYC/PO/PM/20-21/236 | J7: =D7 -> 44305 | K7: 6 | L7: - | M7: TRUCK | N7: MIDC Butibori | O7: - | P7: MH07C7315 | Q7: Biomass Briquette 90mm | R7: 44011090 | S7: 11.12 | T7: 5050 | U7: MT | V7: =S7*T7 -> 56156 | W7: 0.025 | X7: 0.025 | Y7: 0 | Z7: =ROUNDUP((AF7+V7),0) -> 58964 | AA7: =Z7-(V7+AF7) -> 0.2 | AB7: =V7 -> 56156 | AC7: =AB7*W7 -> 1403.9 | AD7: =AB7*X7 -> 1403.9 | AE7: =AB7*Y7 -> 0 | AF7: =SUM(AC7:AE7) -> 2807.8
A8: MAE002/2021-01 | B8: PDDR MEDICAL PRODUCTS & SERVICES PVT LTD | C8: - | D8: 44317 | E8: - | F8: - | G8: - | H8: - | I8: - | J8: 44317 | K8: 7 | L8: - | M8: TRUCK | N8: Hingana | O8: - | P8: MH40N0129 | Q8: Biomass Briquette 90mm | R8: 44011090 | S8: 10.1 | T8: 5150 | U8: MT | V8: =S8*T8 -> 52015 | W8: 0.025 | X8: 0.025 | Y8: 0 | Z8: =ROUNDUP((AF8+V8),0) -> 54616 | AA8: =Z8-(V8+AF8) -> 0.25 | AB8: =V8 -> 52015 | AC8: =AB8*W8 -> 1300.375 | AD8: =AB8*X8 -> 1300.375 | AE8: =AB8*Y8 -> 0 | AF8: =SUM(AC8:AE8) -> 2600.75
A9: MAE002/2021-02 | B9: PDDR MEDICAL PRODUCTS & SERVICES PVT LTD | C9: - | D9: 44348 | E9: - | F9: - | G9: - | H9: - | I9: - | J9: 44348 | K9: 8 | L9: - | M9: TRUCK | N9: Hingana | O9: - | P9: MH40N6407 | Q9: Biomass Briquette 90mm | R9: 44011090 | S9: 7.76 | T9: 5150 | U9: MT | V9: =S9*T9 -> 39964 | W9: 0.025 | X9: 0.025 | Y9: 0 | Z9: =ROUNDUP((AF9+V9),0) -> 41963 | AA9: =Z9-(V9+AF9) -> 0.8 | AB9: =V9 -> 39964 | AC9: =AB9*W9 -> 999.1 | AD9: =AB9*X9 -> 999.1 | AE9: =AB9*Y9 -> 0 | AF9: =SUM(AC9:AE9) -> 1998.2
A10: MAE003/2021-01 | B10: SHREE GAYATRI PACKAGING | C10: - | D10: 44373 | E10: - | F10: - | G10: - | H10: - | I10: - | J10: 44373 | K10: 9 | L10: - | M10: PVT VHCL | N10: WARDHA | O10: - | P10: MH49AS | Q10: Biomass Pallete 6 MM | R10: 44011090 | S10: 0.63 | T10: 10800 | U10: MT | V10: =S10*T10 -> 6804 | W10: 0.025 | X10: 0.025 | Y10: 0 | Z10: =ROUNDUP((AF10+V10),0) -> 7145 | AA10: =Z10-(V10+AF10) -> 0.8 | AB10: =V10 -> 6804 | AC10: =AB10*W10 -> 170.1 | AD10: =AB10*X10 -> 170.1 | AE10: =AB10*Y10 -> 0 | AF10: =SUM(AC10:AE10) -> 340.2
A11: MAE002/2021-03 | B11: PDDR MEDICAL PRODUCTS & SERVICES PVT LTD | C11: - | D11: 44367 | E11: - | F11: - | G11: - | H11: - | I11: - | J11: 44367 | K11: 10 | L11: - | M11: TRUCK | N11: Hingana | O11: - | Q11: Biomass Briquette 90mm | R11: 44011090 | S11: 7.56 | T11: 5150 | U11: MT | V11: =S11*T11 -> 38934 | W11: 0.025 | X11: 0.025 | Y11: 0 | Z11: =ROUNDUP((AF11+V11),0) -> 40881 | AA11: =Z11-(V11+AF11) -> 0.3 | AB11: =V11 -> 38934 | AC11: =AB11*W11 -> 973.35 | AD11: =AB11*X11 -> 973.35 | AE11: =AB11*Y11 -> 0 | AF11: =SUM(AC11:AE11) -> 1946.7
A12: MAE002/2021-04 | B12: PDDR MEDICAL PRODUCTS & SERVICES PVT LTD | C12: - | D12: 44387 | E12: - | F12: - | G12: - | H12: - | I12: - | J12: 44389 | K12: 11 | L12: - | M12: TRUCK | N12: Hingana | O12: - | P12: MH40L2873 | Q12: Biomass Briquette 90mm | R12: 44011090 | S12: 7.42 | T12: 5500 | U12: MT | V12: =S12*T12 -> 40810 | W12: 0.025 | X12: 0.025 | Y12: 0 | Z12: =ROUNDUP((AF12+V12),0) -> 42851 | AA12: =Z12-(V12+AF12) -> 0.5 | AB12: =V12 -> 40810 | AC12: =AB12*W12 -> 1020.25 | AD12: =AB12*X12 -> 1020.25 | AE12: =AB12*Y12 -> 0 | AF12: =SUM(AC12:AE12) -> 2040.5
V13: =S13*T13 -> 0 | Z13: =ROUNDUP((AF13+V13),0) -> 0 | AA13: =Z13-(V13+AF13) -> 0 | AB13: =V13 -> 0 | AC13: =AB13*W13 -> 0 | AD13: =AB13*X13 -> 0 | AE13: =AB13*Y13 -> 0 | AF13: =SUM(AC13:AE13) -> 0
V14: =S14*T14 -> 0 | Z14: =ROUNDUP((AF14+V14),0) -> 0 | AA14: =Z14-(V14+AF14) -> 0 | AB14: =V14 -> 0 | AC14: =AB14*W14 -> 0 | AD14: =AB14*X14 -> 0 | AE14: =AB14*Y14 -> 0 | AF14: =SUM(AC14:AE14) -> 0
V15: =S15*T15 -> 0 | Z15: =ROUNDUP((AF15+V15),0) -> 0 | AA15: =Z15-(V15+AF15) -> 0 | AB15: =V15 -> 0 | AC15: =AB15*W15 -> 0 | AD15: =AB15*X15 -> 0 | AE15: =AB15*Y15 -> 0 | AF15: =SUM(AC15:AE15) -> 0
V16: =S16*T16 -> 0 | Z16: =ROUNDUP((AF16+V16),0) -> 0 | AA16: =Z16-(V16+AF16) -> 0 | AB16: =V16 -> 0 | AC16: =AB16*W16 -> 0 | AD16: =AB16*X16 -> 0 | AE16: =AB16*Y16 -> 0 | AF16: =SUM(AC16:AE16) -> 0
V17: =S17*T17 -> 0 | Z17: =ROUNDUP((AF17+V17),0) -> 0 | AA17: =Z17-(V17+AF17) -> 0 | AB17: =V17 -> 0 | AC17: =AB17*W17 -> 0 | AD17: =AB17*X17 -> 0 | AE17: =AB17*Y17 -> 0 | AF17: =SUM(AC17:AE17) -> 0
V18: =S18*T18 -> 0 | Z18: =ROUNDUP((AF18+V18),0) -> 0 | AA18: =Z18-(V18+AF18) -> 0 | AB18: =V18 -> 0 | AC18: =AB18*W18 -> 0 | AD18: =AB18*X18 -> 0 | AE18: =AB18*Y18 -> 0 | AF18: =SUM(AC18:AE18) -> 0
V19: =S19*T19 -> 0 | Z19: =ROUNDUP((AF19+V19),0) -> 0 | AA19: =Z19-(V19+AF19) -> 0 | AB19: =V19 -> 0 | AC19: =AB19*W19 -> 0 | AD19: =AB19*X19 -> 0 | AE19: =AB19*Y19 -> 0 | AF19: =SUM(AC19:AE19) -> 0
V20: =S20*T20 -> 0 | Z20: =ROUNDUP((AF20+V20),0) -> 0 | AA20: =Z20-(V20+AF20) -> 0 | AB20: =V20 -> 0 | AC20: =AB20*W20 -> 0 | AD20: =AB20*X20 -> 0 | AE20: =AB20*Y20 -> 0 | AF20: =SUM(AC20:AE20) -> 0
V21: =S21*T21 -> 0 | Z21: =ROUNDUP((AF21+V21),0) -> 0 | AA21: =Z21-(V21+AF21) -> 0 | AB21: =V21 -> 0 | AC21: =AB21*W21 -> 0 | AD21: =AB21*X21 -> 0 | AE21: =AB21*Y21 -> 0 | AF21: =SUM(AC21:AE21) -> 0
V22: =S22*T22 -> 0 | Z22: =ROUNDUP((AF22+V22),0) -> 0 | AA22: =Z22-(V22+AF22) -> 0 | AB22: =V22 -> 0 | AC22: =AB22*W22 -> 0 | AD22: =AB22*X22 -> 0 | AE22: =AB22*Y22 -> 0 | AF22: =SUM(AC22:AE22) -> 0
V23: =S23*T23 -> 0 | Z23: =ROUNDUP((AF23+V23),0) -> 0 | AA23: =Z23-(V23+AF23) -> 0 | AB23: =V23 -> 0 | AC23: =AB23*W23 -> 0 | AD23: =AB23*X23 -> 0 | AE23: =AB23*Y23 -> 0 | AF23: =SUM(AC23:AE23) -> 0
V24: =S24*T24 -> 0 | Z24: =ROUNDUP((AF24+V24),0) -> 0 | AA24: =Z24-(V24+AF24) -> 0 | AB24: =V24 -> 0 | AC24: =AB24*W24 -> 0 | AD24: =AB24*X24 -> 0 | AE24: =AB24*Y24 -> 0 | AF24: =SUM(AC24:AE24) -> 0
... V31: =S31*T31 -> 0 | Z31: =ROUNDUP((AF31+V31),0) -> 0 | AA31: =Z31-(V31+AF31) -> 0 | AB31: =V31 -> 0 | AC31: =AB31*W31 -> 0 | AD31: =AB31*X31 -> 0 | AE31: =AB31*Y31 -> 0 | AF31: =SUM(AC31:AE31) -> 0
V32: =S32*T32 -> 0 | Z32: =ROUNDUP((AF32+V32),0) -> 0 | AA32: =Z32-(V32+AF32) -> 0 | AB32: =V32 -> 0 | AC32: =AB32*W32 -> 0 | AD32: =AB32*X32 -> 0 | AF32: =SUM(AC32:AE32) -> 0
V33: =S33*T33 -> 0 | Z33: =ROUNDUP((AF33+V33),0) -> 0 | AA33: =Z33-(V33+AF33) -> 0 | AB33: =V33 -> 0 | AC33: =AB33*W33 -> 0 | AD33: =AB33*X33 -> 0 | AF33: =SUM(AC33:AE33) -> 0
V34: =S34*T34 -> 0 | Z34: =ROUNDUP((AF34+V34),0) -> 0 | AA34: =Z34-(V34+AF34) -> 0 | AB34: =V34 -> 0 | AC34: =AB34*W34 -> 0 | AD34: =AB34*X34 -> 0 | AF34: =SUM(AC34:AE34) -> 0
V35: =S35*T35 -> 0 | Z35: =ROUNDUP((AF35+V35),0) -> 0 | AA35: =Z35-(V35+AF35) -> 0 | AB35: =V35 -> 0 | AC35: =AB35*W35 -> 0 | AD35: =AB35*X35 -> 0 | AF35: =SUM(AC35:AE35) -> 0
V36: =S36*T36 -> 0 | Z36: =ROUNDUP((AF36+V36),0) -> 0 | AA36: =Z36-(V36+AF36) -> 0 | AB36: =V36 -> 0 | AC36: =AB36*W36 -> 0 | AD36: =AB36*X36 -> 0 | AF36: =SUM(AC36:AE36) -> 0
V37: =S37*T37 -> 0 | Z37: =ROUNDUP((AF37+V37),0) -> 0 | AA37: =Z37-(V37+AF37) -> 0 | AB37: =V37 -> 0 | AC37: =AB37*W37 -> 0 | AD37: =AB37*X37 -> 0 | AF37: =SUM(AC37:AE37) -> 0
V38: =S38*T38 -> 0 | Z38: =ROUNDUP((AF38+V38),0) -> 0 | AA38: =Z38-(V38+AF38) -> 0 | AB38: =V38 -> 0 | AC38: =AB38*W38 -> 0 | AD38: =AB38*X38 -> 0 | AF38: =SUM(AC38:AE38) -> 0
V39: =S39*T39 -> 0 | Z39: =ROUNDUP((AF39+V39),0) -> 0 | AA39: =Z39-(V39+AF39) -> 0 | AB39: =V39 -> 0 | AC39: =AB39*W39 -> 0 | AD39: =AB39*X39 -> 0 | AF39: =SUM(AC39:AE39) -> 0
V40: =S40*T40 -> 0 | Z40: =ROUNDUP((AF40+V40),0) -> 0 | AA40: =Z40-(V40+AF40) -> 0 | AB40: =V40 -> 0 | AC40: =AB40*W40 -> 0 | AD40: =AB40*X40 -> 0 | AF40: =SUM(AC40:AE40) -> 0
V41: =S41*T41 -> 0 | Z41: =ROUNDUP((AF41+V41),0) -> 0 | AA41: =Z41-(V41+AF41) -> 0 | AB41: =V41 -> 0 | AC41: =AB41*W41 -> 0 | AD41: =AB41*X41 -> 0 | AF41: =SUM(AC41:AE41) -> 0
V42: =S42*T42 -> 0 | Z42: =ROUNDUP((AF42+V42),0) -> 0 | AA42: =Z42-(V42+AF42) -> 0 | AB42: =V42 -> 0 | AC42: =AB42*W42 -> 0 | AD42: =AB42*X42 -> 0 | AF42: =SUM(AC42:AE42) -> 0
V43: =S43*T43 -> 0 | Z43: =ROUNDUP((AF43+V43),0) -> 0 | AA43: =Z43-(V43+AF43) -> 0 | AB43: =V43 -> 0 | AC43: =AB43*W43 -> 0 | AD43: =AB43*X43 -> 0 | AF43: =SUM(AC43:AE43) -> 0
... V1000: =S1000*T1000 -> 0 | Z1000: =ROUNDUP((AF1000+V1000),0) -> 0 | AA1000: =Z1000-(V1000+AF1000) -> 0 | AB1000: =V1000 -> 0 | AC1000: =AB1000*W1000 -> 0 | AD1000: =AB1000*X1000 -> 0 | AF1000: =SUM(AC1000:AE1000) -> 0

Sheet Sheet1
A1: Sr. No. | B1: Date | C1: Motor Vehicle Number | D1: Description of Goods | E1: HSN Code | F1: QTY | G1: Rate | H1: per(wt) | I1: Amount | J1: SGST | K1: CGST | L1: IGST | M1: Total | N1: Roundoff | O1: Taxable Value | P1: SGST AMT | Q1: CGST AMT | R1: IGST | S1: Tax Total | T1: Pay To DSP | U1: Remarks | V1: Balance | W1: Transport | X1: Labour
A2: 1 | B2: 44220 | C2: MH40N8211 | D2: Biomass Briquette 90mm | E2: 44011090 | F2: 10.81 | G2: 3850 | H2: MT | I2: =F2*G2 -> 41618.5 | J2: 0.025 | K2: 0.025 | L2: 0 | M2: =ROUNDUP((S2+I2),0) -> 43700 | N2: =M2-(I2+S2) -> 0.575 | O2: =I2 -> 41618.5 | P2: =O2*J2 -> 1040.4625 | Q2: =O2*K2 -> 1040.4625 | R2: =O2*L2 -> 0 | S2: =SUM(P2:R2) -> 2080.925 | T2: =I2+S2 -> 43699.425 | U2: Cleared | V2: 4000 | W2: 4600 | X2: 900 | Y2: Sandeep
A3: 2 | B3: 44231 | C3: MH40N8725 | D3: Biomass Briquette 90mm | E3: 44011090 | F3: 9.43 | G3: 3850 | H3: MT | I3: =F3*G3 -> 36305.5 | J3: 0.025 | K3: 0.025 | L3: 0 | M3: =ROUNDUP((S3+I3),0) -> 38121 | N3: =M3-(I3+S3) -> 0.225 | O3: =I3 -> 36305.5 | P3: =O3*J3 -> 907.6375 | Q3: =O3*K3 -> 907.6375 | R3: =O3*L3 -> 0 | S3: =SUM(P3:R3) -> 1815.275 | T3: =I3+S3 -> 38120.775 | U3: Disputed | V3: 0 | W3: 4600 | X3: 800 | Y3: Yaman
A4: 3 | B4: 44243 | C4: MH40N8500 | D4: Biomass Briquette 90mm | E4: 44011090 | F4: 9.365 | G4: 3850 | H4: MT | I4: =F4*G4 -> 36055.25 | J4: 0.025 | K4: 0.025 | L4: 0 | M4: =ROUNDUP((S4+I4),0) -> 37859 | N4: =M4-(I4+S4) -> 0.9875 | O4: =I4 -> 36055.25 | P4: =O4*J4 -> 901.38125 | Q4: =O4*K4 -> 901.38125 | R4: =O4*L4 -> 0 | S4: =SUM(P4:R4) -> 1802.7625 | T4: =I4+S4 -> 37858.012 | U4: Cleared | V4: 0 | W4: 5000 | X4: 800 | Y4: Yaman
A5: 4 | B5: 44253 | C5: MH14BT0796 | D5: Biomass Briquette 90mm | E5: 44011090 | F5: 10.03 | G5: 3850 | H5: MT | I5: =F5*G5 -> 38615.5 | J5: 0.025 | K5: 0.025 | L5: 0 | M5: =ROUNDUP((S5+I5),0) -> 40547 | N5: =M5-(I5+S5) -> 0.725 | O5: =I5 -> 38615.5 | P5: =O5*J5 -> 965.3875 | Q5: =O5*K5 -> 965.3875 | R5: =O5*L5 -> 0 | S5: =SUM(P5:R5) -> 1930.775 | T5: =I5+S5 -> 40546.275 | U5: Cleared | V5: 0 | W5: 4600 | X5: 900 | Y5: Yaman
A6: 5 | B6: 44277 | C6: MH40N8542 | D6: Biomass Briquette 90mm | E6: 44011090 | F6: 10.64 | G6: 3750 | H6: MT | I6: =F6*G6 -> 39900 | J6: 0.025 | K6: 0.025 | L6: 0 | M6: =ROUNDUP((S6+I6),0) -> 41895 | N6: =M6-(I6+S6) -> 0 | O6: =I6 -> 39900 | P6: =O6*J6 -> 997.5 | Q6: =O6*K6 -> 997.5 | R6: =O6*L6 -> 0 | S6: =SUM(P6:R6) -> 1995 | T6: =I6+S6 -> 41895 | V6: 14453.725 | W6: 5000 | X6: 1000 | Y6: Yaman
V7: =SUM(V2:V6) -> 18453.725 | W7: =SUM(W3:W6) -> 19200 | X7: =SUM(X3:X6) -> 3500

Sheet Sheet12
A2: Mahalaxmi Agro Energies
A3: Trail Date : 20 March 2026 | D3: Trail Date : 20 March 2026
A4: Location : | D4: Location :
A5: Trial on Commercial LPG Gas | D5: Trial on Biomass Pellet
A7: Type of LPG Cylinder Used | B7: Commercial Cylinder | D7: Type of Stove Used | E7: MAE 10K
A8: Weight of LPG Cylinder | B8: 30.38KG | D8: Weight of Pellet Used | E8: 4.5KG
A9: Gas On | B9: 3.19PM | D9: Stove Start Time | E9: 3.06 PM
A10: Water Boiling Start On | B10: 3.19PM | D10: Charge Time (Time to Start Fully) | E10: 4 Min
A11: Water Boiled by | B11: 3.33PM | D11: Water Boiling Start On | E11: 3.10 PM
A12: Total Time required to boil water | B12: 14 Min | D12: 2.5 KG Noodles Start Boiling On | E12: 3.19 PM
A13: 7 KG Rice Start Boiling on | B13: 3.34PM | D13: Noodles Boil on | E13: 3.39 PM
A14: Rice Boiled On | B14: 3.49PM | D14: Time Required to boil Noodles | E14: 20 Min
A15: Total Time required to boil Rice | B15: 15 Min
D16: Water for Rice to Boil Start on | E16: 3.46 PM
A17: Gas Off time | B17: 3.50 PM | D17: 7 KG Rice Start Boiling On | E17: 3.57 PM
A18: Gas Again start time | B18: 3.56 PM | D18: Rice Boiled On | E18: 4.20 PM
A19: Water Start Boiling on | B19: 3.56 PM | D19: Total Time required to Boil Rice | E19: 21 Min
A20: Water Boiled on | B20: 4.12 PM | D20: Stove Burning continuously until | E20: 4.30 PM
A21: Total Time required to boil water | B21: 16 Min
D22: Total Time Stove Burn | E22: 90 Min
A23: 2.5 KG Noodles Start Boiling On | B23: 4.12 PM
A24: Noodles Boil on | B24: 4.25 PM
A25: Time Required to boil Noodles | B25: 13 Min
A27: Gas Off Time | B27: 4.25 PM
A28: Gas Working Time | B28: 61 Min
A29: Weight of LPG Cylinder after Use | B29: 28.60KG
A31: Total Gas Used | B31: 1.78 KG
A32: Rate of Commercial LPG Cylinder | B32: RS 1800
A33: Weight of LPG Gas | B33: 19 KG
A34: Rate per KG | B34: RS 95 | D34: Rate Of Biomass Pellet | E34: RS 16
A35: Used LPG Gas in 61 Min | B35: RS 169 | D35: Amount of Pellets burnt for 90 Mins | E35: RS 72
A37: Cost of Savings in RS for Batch 1 | B37: RS 97
A38: Cost of Savings in RS for Batch 2 | B38: RS 194
A39: Monthly Projected Cost of Saving in RS | B39: RS 5820

Sheet Sheet4
A1: Invoice Number | B1: 1
A2: Consignee Name | B2: 2
A3: Buyer | B3: 3
A4: Dated | B4: 4
A5: Delivery Note | B5: 5
A6: Payment Mode/Terms | B6: 6
A7: Supplier Ref. | B7: 7
A8: Other Reference(s) | B8: 8
A9: Buyer's Order No. | B9: 9
A10: Date | B10: 10
A11: Despatch Document No. | B11: 11
A12: Delivery Note Date | B12: 12
... A33: Tax Total | B33: 33
A37: https://meet.google.com/esr-kgwe-dpp?hl=en
